Workbook
Name APLICA: Tabla3[APLICA]
Name APLICA: Tabla3[APLICA]
Name APLICA: Tabla3[APLICA]
Name APLICA: Tabla3[APLICA]
Name APLICA: [1]!Tabla3[APLICA]
Name APLICA: [1]!Tabla3[APLICA]
Name APLICA: [1]!Tabla3[APLICA]
Name APLICA: [1]!Tabla3[APLICA]
Name APLICA: [1]!Tabla3[APLICA]
Name APLICA: Tabla3[APLICA]
Name APLICA: Tabla3[APLICA]
Name APLICA: [2]!Tabla3[APLICA]
Name APLICA: Tabla3[APLICA]
Name CUMPLIMIENTO: Tabla1[CUMPLIMIENTO]
Name CUMPLIMIENTO: Tabla1[CUMPLIMIENTO]
Name CUMPLIMIENTO: Tabla1[CUMPLIMIENTO]
Name CUMPLIMIENTO: Tabla1[CUMPLIMIENTO]
Name CUMPLIMIENTO: [1]!Tabla13[CUMPLIMIENTO]
Name CUMPLIMIENTO: [1]!Tabla13[CUMPLIMIENTO]
Name CUMPLIMIENTO: [1]!Tabla13[CUMPLIMIENTO]
Name CUMPLIMIENTO: [1]!Tabla13[CUMPLIMIENTO]
Name CUMPLIMIENTO: [1]!Tabla13[CUMPLIMIENTO]
Name CUMPLIMIENTO: Tabla1[CUMPLIMIENTO]
Name CUMPLIMIENTO: [3]!Tabla13[CUMPLIMIENTO]
Name CUMPLIMIENTO: [3]!Tabla13[CUMPLIMIENTO]
Name CUMPLIMIENTO: [3]!Tabla13[CUMPLIMIENTO]
Name CUMPLIMIENTO: Tabla1[CUMPLIMIENTO]
Name CUMPLIMIENTO: [2]!Tabla13[CUMPLIMIENTO]
Name CUMPLIMIENTO: Tabla1[CUMPLIMIENTO]

Sheet ÍNDICE
B2: GERENCIA DE SEGURIDAD Y SALUD OCUPACIONAL - CHUQUICAMATA
B4: Empresa | E4: : | J4: % GENERAL
B5: N° y Nombre de contrato y/u ODS | E5: : | J5: =IFERROR(AVERAGEIF(H12:H41,">=0"),"NO APLICA") -> 0.3375
B7: Gerencia o Dirección | E7: :
B8: Gerente de Area | E8: :
B9: Líder de gestión del cambio | E9: :
A11: ÍNDICE RIESGOS DE FATALIDAD | G11: ¿APLICA? | H11: % CUMPLIMIENTO | I11: IR AL RF | J11: DUEÑO DEL RIESGO
A12: RF01 | B12: ENERGÍA ELÉCTRICA | G12: SÍ | H12: ='RF01'!I7 -> 0.9 | I12: IR AL RF01
A13: RF02 | B13: TRABAJO EN ALTURA | G13: SÍ | H13: ='RF02'!I7 -> 0 | I13: IR AL RF02
A14: RF03 | B14: MANIOBRAS DE IZAJE | G14: SÍ | H14: ='RF03'!I7 -> 0 | I14: IR AL RF03
A15: RF04 | B15: LIBERACIÓN DESCONTROLADA DE ENERGÍAS | G15: SÍ | H15: ='RF04'!I7 -> 0 | I15: IR AL RF04
A16: RF05 | B16: CAÍDA DE ROCAS EN MINA RAJO | G16: SÍ | H16: ='RF05'!I7 -> 0 | I16: IR AL RF05
A17: RF06 | B17: INCENDIO | G17: SÍ | H17: ='RF06'!I7 -> 0.4 | I17: IR AL RF06
A18: RF07 | B18: SUSTANCIAS PELIGROSAS | G18: SÍ | H18: ='RF07'!I7 -> 0.4 | I18: IR AL RF07
A19: RF08 | B19: TRONADURAS Y EXPLOSIVOS | G19: SÍ | H19: ='RF08'!I7 -> 1 | I19: IR AL RF08
A20: RF09 | B20: PARTES MÓVILES | G20: SÍ | H20: ='RF09'!I7 -> #DIV/0! | I20: IR AL RF09
A21: RF10 | B21: VEHÍCULOS | G21: SÍ | H21: ='RF10'!I7 -> #DIV/0! | I21: IR AL RF10
A22: RF11 | B22: ESPACIOS CONFINADOS | G22: SÍ | H22: ='RF11'!I7 -> #DIV/0! | I22: IR AL RF11
A23: RF12 | B23: MATERIALES FUNDIDOS | G23: SÍ | H23: ='RF12'!I7 -> #DIV/0! | I23: IR AL RF12
A24: RF13 | B24: CAÍDA DE OBJETOS | G24: SÍ | H24: ='RF13'!I7 -> #DIV/0! | I24: IR AL RF13
A25: RF14 | B25: OPERACIÓN FERROVIARIA | G25: SÍ | H25: ='RF14'!I7 -> #DIV/0! | I25: IR AL RF14
A26: RF15 | B26: AVALANCHA Y ALUDES | G26: NO | H26: NO APLICA | I26: IR AL RF15
A27: RF16 | B27: VACIADOS, CHIMENEAS Y PIQUES | G27: SÍ | H27: ='RF16'!I7 -> #DIV/0! | I27: IR AL RF16
A28: RF17 | B28: MATERIAL HUMEDO | G28: NO | H28: NO APLICA | I28: IR AL RF17
A29: RF18 | B29: PLANCHONEO | G29: SÍ | H29: ='RF18'!I7 -> #DIV/0! | I29: IR AL RF18
A30: RF19 | B30: ESTALLIDO DE ROCA | G30: NO | H30: NO APLICA | I30: IR AL RF19
A31: RF20 | B31: SÍLICE | G31: SÍ | H31: ='RF20'!I7 -> #DIV/0! | I31: IR AL RF20
A32: RF21 | B32: ARSÉNICO | G32: SÍ | H32: ='RF21'!I7 -> #DIV/0! | I32: IR AL RF21
A33: RF22 | B33: COLAPSO ESTRUCTURAL DE PASILLOS, PISOS Y BARANDAS | G33: SÍ | I33: IR AL RF22
A34: RF23 | B34: COLAPSO ESTRUCTURAL DEL MACIZO ROCOSO | G34: SÍ | H34: ='RF23'!I7 -> #DIV/0! | I34: IR AL RF23
A35: RF24 | B35: TALUDES | G35: SÍ | H35: ='RF24'!I7 -> #DIV/0! | I35: IR AL RF24
A36: RF25 | B36: EQUIPOS MINEROS E INDUSTRIALES | G36: SÍ | H36: ='RF25'!I7 -> #DIV/0! | I36: IR AL RF25
A37: RF26 | B37: EQUIPOS AUTÓNOMOS | G37: NO | H37: NO APLICA | I37: IR AL RF26
A38: RF27 | B38: ATROPELLO | G38: SÍ | H38: ='RF27'!I7 -> #DIV/0! | I38: IR AL RF27
A39: RF28 | B39: CAVING | G39: SÍ | H39: ='RF28'!I7 -> #DIV/0! | I39: IR AL RF28
A40: RF29 | B40: CAIDA A CUERPOS LIQUIDOS | G40: SÍ | H40: ='RF29'!I7 -> #DIV/0! | I40: IR AL RF29
A41: RF30 | B41: TIRO Y ARRASTRE | G41: SÍ | I41: IR AL RF30
B43: RIESGOS DE FATALIDAD (BOWTIE) APLICABLES | G43: =COUNTIF(G12:G41,"SÍ") -> 26
B44: RIESGOS DE FATALIDAD (BOWTIE) "NO" APLICABLES | G44: =COUNTIF(G12:G41,"NO") -> 4

Sheet Listas desplegables
C3: CUMPLIMIENTO | E3: APLICA
C4: N/A | E4: SÍ
C5: 0 | E5: NO
C6: 0.1
C7: 0.2
C8: 0.3
C9: 0.4
C10: 0.5
C11: 0.6
C12: 0.7
C13: 0.8
C14: 0.9
C15: 1

Sheet RF01
B2: GERENCIA DE SEGURIDAD Y SALUD OCUPACIONAL - CHUQUICAMATA
B4: LISTADO DE AUTODIAGNÓSTICO RIESGO DE FATALIDAD N°01: ENERGÍA ELÉCTRICA
B6: ELEMENTOS DEL CONTROL | I6: CUMPLIMIENTO GENERAL
I7: =AVERAGEIF(I14:I67,"<>N/A") -> 0.9
B10: Alcance | C10: Interacción entre energía eléctrica y las personas. Esto puede ocurrir en actividades de operación, mantención, servicios, proyectos en donde se puedan observar exposición a AT - BT (AT > 1000 V y BT <1000 V CA). • Salas eléctricas, Subestaciones eléctricas, Equipos mineros eléctricos (móviles y semi móviles). • Herramientas eléctricas, líneas de media y alta tensión. • Intervención de equipos y sistemas eléctricos energizados. • Generadores, exposición a CC circuitos, bancos de baterías. • También incluye equipos de fuente de alimentación, cable de transmisión eléctrica y electrodos
B11: Exclusión | C11: Este evento considera como exclusión los siguientes escenarios: • Trabajos en torres de alta tensión con líneas energizadas. (maniobras de operación, mediciones, pruebas y seguimiento de fallas).
B13: RIESGO FATALIDAD | C13: CONTROL CRÍTICO | D13: NOMBRE DEL CONTROL CRÍTICO | E13: OBJETIVO | F13: REQUISITO | G13: MONITOREO | H13: EVIDENCIA | I13: CUMPLIMIENTO | J13: OBSERVACIONES | K13: FECHA IMPLEMENTACIÓN | L13: PLAN MITIGADOR
B14: RF01 | C14: CCP1 | D14: Personal acreditado para trabajos eléctricos | E14: Asegurar que toda persona que realice intervenciones en sistemas eléctricos que puedan estar energizados cuente con calificación y autorización formal vigente (Licencia Eléctrica), conforme a los reglamentos corporativos y divisionales. | F14: Trazabilidad de requisitos para la autorización de intervención de sistemas eléctricos. | G14: Semestral | H14: Registro del personal que se encuentra autorizado a intervenir sistemas eléctricos, con sus requisitos en cumplimiento según lo definido en SIG0-I-013. | I14: 0.9
F15: Autorización formal a través de licencia eléctrica. | G15: Trimestral | H15: Credencial física o digital disponible, acorde a las actividades que realiza el personal, según lo definido en SIG0-I-013. | I15: N/A
F16: Auditoría al sistema de autorización. | G16: Anual | H16: Reporte de auditoría que verifica la operatividad y actualización del sistema de autorización, con existencia de respaldos correspondientes y en cumplimiento del SIGO-I-013. | I16: N/A
B17: RF01 | C17: CCP2 | D17: Acceso restringido a equipos e instalaciones eléctricas | E17: Asegurar que únicamente personal autorizado acceda a equipos e instalaciones eléctricas, mediante barreras físicas y sistemas de custodia y/o control de acceso, según aplique. | F17: Procedimiento de ingreso a instalaciones eléctricas | G17: Anual | H17: Procedimiento vigente que define el mecanismo de custodia de instalaciones eléctricas y el proceso para acceder a ellas. | I17: N/A
F18: Integridad de barreras físicas. | G18: Semestral | H18: Inspección documentada que verifica el estado operativo de puertas, cierres y candados de equipos e instalaciones eléctricas. | I18: N/A
F19: Señalización de advertencia. | G19: Trimestral | H19: Verificación en terreno de letreros de advertencia visibles y legibles en equipos e instalaciones eléctricas. | I19: N/A
B20: RF01 | C20: CCP3 | D20: Equipos y herramientas eléctricas verificadas | E20: Asegurar que todo el personal que interviene sistemas eléctricos utilice exclusivamente herramientas e instrumentos que han sido verificados y se encuentran en buenas condiciones. | F20: Verificación de condiciones visibles. | G20: Cada tarea | H20: Lista de verificación en terreno de las herramientas e instrumentos en uso. | I20: N/A
F21: Mantenimiento y calibración de instrumentos. | G21: Semestral | H21: Registro de mantenimiento e inspección para instrumentos de medición y herramientas de maniobra. | I21: N/A
F22: Protecciones en herramientas eléctricas. | G22: Semestral | H22: Registro de inspección que verifica la integridad del sistema de puesta a tierra (tercer pin, cable) de las herramientas eléctricas (ej. generador, tablero móvil). | I22: N/A
B23: RF01 | C23: CCP4 | D23: Intervención de equipos en condición eléctricamente segura | E23: Garantizar que antes de intervenir un sistema eléctrico este se encuentre en condición eléctricamente segura, mediante la aplicación de las 5 Reglas de Oro del Electricista. | F23: Procedimiento de aislación y bloqueo de energía eléctrica. | G23: Anual | H23: Procedimiento vigente que define el proceso de aislación y bloqueo, aplicable para energía eléctrica y registro de instrucción del documento al personal. | I23: N/A
F24: Proceso de solicitud de desconexión e intervención en sistemas de media tensión. | G24: Cada vez | H24: Documento (SODI) en físico o digital autorizado, según lo definido en SIG0-I-012. | I24: N/A
F25: Identificación y aislación. | G25: Cada vez | H25: Registro de identificación de los puntos de aislación y puntos de bloqueo, según mapas de bloqueo o diagramas disponibles para este fin. | I25: N/A
F26: Bloqueo y advertencia. | G26: Cada vez | H26: Verificación en terreno de los dispositivos de bloqueo y advertencia instalados y rotulados adecuadamente. | I26: N/A
F27: Verificación de ausencia de tensión. | G27: Cada vez | H27: Registro de la metodología utilizada para verificar ausencia de tensión y los resultados de prueba. | I27: N/A
F28: Instalación de puesta a tierra temporal. | G28: Cada vez | H28: Verificación en terreno de instalación de puesta a tierra temporal, con lista de verificación del conjunto y en los puntos definidos. | I28: N/A
F29: Segregación del lugar de intervención. | G29: Cada vez | H29: Verificación en terreno de la instalación de barreras (conos con cadenas) y señalización en el lugar de intervención. | I29: N/A
F30: Verificación de prácticas eléctricas. | G30: Anual | H30: Verficación de aplicación de 5 Reglas de Oro, SODI y procedimiento de bloqueo. | I30: N/A
B31: RF01 | C31: CCM1 | D31: Selección y uso de EPP específico para la actividad | E31: Asegurar que todo trabajador que se vea expuesto a riesgo eléctrico seleccione y use correctamente EPP específico y en condiciones, para las actividades a realizar. | F31: Estudio de energía incidental. | G31: Anual | H31: Estudio que determina la energía incidental (cal/cm²), que determina la distancia de seguridad y el EPP específico a utilizar en equipos e instalaciones eléctricas. | I31: N/A
F32: Control de disponibilidad y entrega de elementos de protección personal específicos. | G32: Semestral | H32: Registro de entrega de EPP específicos al personal electricista, de acuerdo con lo definido en el estudio de elementos de protección personal. | I32: N/A
F33: Inspección pre-uso de los elementos de protección personal específicos. | G33: Cada Tarea | H33: Lista de verificación en terreno de los EPP específicos para el arco eléctrico y choque eléctrico en uso. | I33: N/A
B34: RF01 | C34: CCM2 | D34: Protecciones eléctricas en sistemas de alta tensión | E34: Asegurar que los sistemas de protecciones de los sistemas eléctricos, operen adecuadamente para despejar y proteger al personal ante fallas eléctricas. | F34: Plan Matriz de Mantenimiento de Protecciones. | G34: Anual | H34: Plan matriz (ej. SAP) con OTs cerradas de mantenimiento y pruebas funcionales de protecciones (relés, interruptores) según fabricante/norma. | I34: N/A
F35: Estudios Eléctricos Vigentes. | G35: Anual | H35: Estudios de Coordinación de Protecciones y Energía Incidental vigente y disponibles en terreno para consulta. | I35: N/A
F36: Medición de Mallas a Tierra (Instalaciones). | G36: Anual | H36: Informe de medición de resistencia de mallas a tierra y continuidad de puestas a tierra de equipos, vigente (< 1 año). | I36: N/A
F37: Pruebas Funcionales con Trazabilidad. | G37: Anual | H37: Registros de pruebas de protecciones realizadas con instrumentos que poseen trazabilidad vigente. | I37: N/A
F38: Integridad de Infraestructura (Inspección). | G38: Semestral | H38: Registros de inspección (checklist) de condiciones de salas, tableros y S/E (limpieza, orden, integridad física, señalética). | I38: N/A
B40: RIESGO FATALIDAD | C40: CONTROL | D40: NOMBRE DEL CONTROL | E40: REQUISITO | G40: EVIDENCIA | I40: CUMPLIMIENTO | J40: OBSERVACIONES | K40: FECHA IMPLEMENTACIÓN | L40: PLAN MITIGADOR
B41: RF01 | C41: CP1 | D41: Planos unilineales actualizados | E41: Todo trabajo que involucre intervención en sistemas eléctricos debe contar con planos unilineales actualizados, disponibles y legibles en terreno. | G41: A. El supervisor(a) debe asegurar que los planos reflejen la ubicación y características reales de todo el sistema eléctrico. | I41: N/A
G42: B. Los planos deben estar actualizados tras cada modificación en la red eléctrica, con trazabilidad documental | I42: N/A
G43: C. Su disponibilidad debe ser verificada antes de iniciar excavaciones o trabajos de terreno en zonas con riesgo eléctrico | I43: N/A
B44: RF01 | C44: CP2 | D44: Enclavamientos eléctricos operativos | E44: Todos los enclavamientos eléctricos de tableros y equipos deben encontrarse operativos y en condiciones de uso seguro. | G44: A. El supervisor(a) debe verificar en la inspección previa el correcto funcionamiento de enclavamientos para impedir maniobras indebidas o no autorizadas. | I44: N/A
G45: B. Cualquier falla en enclavamientos debe implicar el retiro del equipo del servicio hasta su reparación. | I45: N/A
G46: C. La condición operativa de los enclavamientos debe estar documentada en el programa de mantenimiento eléctrico. | I46: N/A
B47: RF01 | C47: CP3 | D47: Porticos de control de altura para tránsito bajo tendidos eléctricos | E47: En todas las rutas de tránsito bajo tendidos eléctricos de media o alta tensión se deben instalar pórticos de control de altura. | G47: A. Los pórticos deben ubicarse antes de zonas de riesgo, con señalización visible para operadores de equipos de gran altura. | I47: N/A
G48: B. El supervisor(a) debe verificar periódicamente la integridad de los pórticos y su correspondencia con la altura máxima autorizada. | I48: N/A
G49: C. El incumplimiento de la restricción de altura debe implicar la detención inmediata del tránsito del equipo. | I49: N/A
B50: RF01 | C50: CP4 | D50: Monitoreos de fugas de energía | E50: Los tableros eléctricos y circuitos deben contar con sistemas de monitoreo de fugas de energía para la detección temprana de energización no controlada. | G50: A. Los sistemas de monitoreo deben estar calibrados y contar con alertas visibles y audibles en caso de detección de fugas. | I50: N/A
G51: B. El supervisor(a) debe revisar registros de calibración y pruebas funcionales conforme al programa de mantenimiento. | I51: N/A
G52: C. Ante cualquier alerta de fuga, el equipo o tablero debe ser aislado y puesto fuera de servicio hasta su corrección. | I52: N/A
B53: RF01 | C53: CP5 | D53: Señalización visible en puntos de bloque y zonas energizadas | E53: Todos los puntos de bloqueo y zonas energizadas deben estar señalizados de forma clara y permanente. | G53: A. Las señales deben indicar de manera explícita la presencia de energía peligrosa y la prohibición de intervención sin autorización. | I53: N/A
G54: B. El supervisor(a) debe verificar que la señalización esté instalada y sea legible previo al inicio de las tareas. | I54: N/A
G55: C. En caso de pérdida o daño de señalética, el trabajo debe suspenderse hasta reponerla. | I55: N/A
B56: RF01 | C56: CP6 | D56: TAG de identificación de equipos | E56: Todos los equipos y tableros eléctricos deben estar identificados con tag visible que asegure trazabilidad y control en maniobras y bloqueos. | G56: A. Cada TAG debe contener información legible sobre el equipo, circuito y energía que controla. | I56: N/A
G57: B. El supervisor(a) debe confirmar la correspondencia entre el TAG y el registro de bloqueo antes de autorizar la tarea. | I57: N/A
G58: C. El mapa debe estar instalado en un lugar visible del área y respaldado documentalmente. | I58: N/A
B59: RF01 | C59: CP7 | D59: Mapa de energías disponible y actualizado | E59: Toda área de trabajo debe contar con un mapa actualizado de energías presentes, disponible para consulta de personal propio y contratista. | G59: A. El mapa debe identificar claramente las fuentes de energía y sus puntos de bloqueo. | I59: N/A
G60: B. El supervisor(a) debe verificar la actualización del mapa tras cada modificación en el sistema eléctrico. | I60: N/A
G61: C. El mapa debe estar instalado en un lugar visible del área y respaldado documentalmente. | I61: N/A
B62: RF01 | C62: CM1 | D62: Pararrayos | E62: En todas las rutas de tránsito bajo tendidos eléctricos de media o alta tensión se deben instalar pórticos de control de altura. | G62: A. Los pórticos deben ubicarse antes de zonas de riesgo, con señalización visible para operadores de equipos de gran altura. | I62: N/A
G63: B. El mantenimiento preventivo debe incluir revisión de continuidad eléctrica y puesta a tierra. | I63: N/A
G64: C. Ante fallas o daños en el sistema, las tareas deben suspenderse hasta la reparación. | I64: N/A
B65: RF01 | C65: CM2 | D65: Sistema de detección y extinción de incendios en instalaciones eléctricas | E65: Todas las instalaciones eléctricas deben contar con sistemas de detección y extinción de incendios conforme a normativa aplicable. | G65: A. El supervisor(a) debe comprobar la operatividad del sistema antes del inicio de las tareas. | I65: N/A
G66: B. El plan de mantenimiento debe incluir pruebas periódicas y certificaciones vigentes del sistema. | I66: N/A
G67: C. Ante detección de falla en el sistema, la instalación debe quedar fuera de servicio hasta restablecer las condiciones seguras. | I67: N/A

Sheet RF02
B2: GERENCIA DE SEGURIDAD Y SALUD OCUPACIONAL - CHUQUICAMATA
B4: LISTADO DE AUTODIAGNÓSTICO RIESGO DE FATALIDAD N°02: TRABAJO EN ALTURA
B6: ELEMENTOS DEL CONTROL | I6: CUMPLIMIENTO GENERAL
I7: =AVERAGEIF(I14:I60,"<>N/A") -> 0
B10: Alcance | C10: Actividades con potencial de caída desde una altura igual o superior a 1,8 metros, en actividades, tales como: • Trabajos sobre plataformas fijas temporales (como andamios u otras estructuras similares). • Puntos de trabajo sobre equipos. • Trabajos en altura realizados en edificios e instalaciones. • Uso de plataformas móviles (equipos elevadores de personas, manipuladores telescópicos con canastillo / jaula). • Presencia en bordes desprotegidos a una altura mayor a 1,8 metros. • Trabajos realizados sobre escalas que cuenten con plataforma. • Uso de escalas verticales fijas. • Techos inclinados, cualquiera sea el ángulo de inclinación.
B11: Exclusión | C11: • Caída a distinto nivel por colapso estructural. • Aberturas (vanos) por ausencia de grating y/o barandas. • Trabajos verticales (cuerdas, saneamiento de taludes).
B13: RIESGO FATALIDAD | C13: CONTROL CRÍTICO | D13: NOMBRE DEL CONTROL CRÍTICO | E13: OBJETIVO | F13: REQUISITO | G13: MONITOREO | H13: EVIDENCIA | I13: CUMPLIMIENTO | J13: OBSERVACIONES | K13: FECHA IMPLEMENTACIÓN | L13: PLAN MITIGADOR
B14: RC02 | C14: CCP1 | D14: Plataformas y superficies de trabajo estables e íntegras | E14: -Asegurar que las plataformas y superficies de trabajo sean estructuralmente estables, capaces de soportar de manera segura las cargas previstas (personas, equipos, materiales) sin colapsar, cumpliendo todas las normativas aplicables. -Prevenir la falla estructural o la pérdida de estabilidad de las plataformas y superficies durante su uso. | F14: Documentación que Respalda el Diseño, Ingeniería y Componentes | G14: Semestral | H14: Repositorio con: Memorias de cálculo, planos de diseño firmados por personal calificado, certificados de componentes, evidencia de cumplimiento normativo/fabricante, capacidad de carga e informes de verificación visual de componentes vs. diseño. | I14: 0
F15: Evidencias del Correcto Montaje, Instalación y Preparación Inicial | G15: Semanal | H15: -Debe ser realizado por personal capacitado (curso de armado/desarme de andamios, operación de plataformas móviles e instrucción de procedimiento/manual de fabricante) -Verificación de superficie de apoyo, y acta/registro de entrega de plataforma instalada (estable, nivelada y asegurada). | I15: N/A
F16: Registros de Inspecciones y Gestión de Estado Operativo | G16: Cada vez | H16: Registros/evidencia de: Inspecciones pre-uso (checklists firmados), inspecciones periódicas formales (informes firmados), y uso visible y actualizado de tarjetas de estado (Verde/Roja) en plataformas. | I16: N/A
F17: Verificación del Cumplimiento de la Capacidad de Carga de la Plataforma | G17: Cada vez | H17: Evidencia documentada del control de cargas aplicadas a la plataforma (ej. registros de carga, señalética de capacidad máxima) y verificación de que no se excede su capacidad nominal durante el uso (ej. en verificaciones u observaciones en terreno). | I17: N/A
F18: Registros de Mantenimiento de la Plataforma móvil | G18: Anual | H18: Registro de reparaciones o ajustes realizados tras fallas detectadas en inspecciones, con validación previa a su reincorporación al uso. | I18: N/A
B19: RC02 | C19: CCP2 | D19: Personal acreditado realiza trabajos en altura | E19: Asegurar que toda persona que realiza trabajos en altura cuenta con formación teórico / práctica aprobada, evaluación médica vigente y autorización formal, mediante credencial, para desempeñar tareas específicas en altura física. | F19: Curso teórico - práctico en trabajos en altura | G19: Semestral | H19: Documento de aprobación de cursos para trabajadores y supervisores (con foco en inspección), que considere a lo menos: -SPDC: tipos de sistemas, uso, inspección, almacenamiento y líneas de vida. -Entrenamiento práctico: en torre, incluye ascenso/descenso, uso de sistemas, técnicas de posicionamiento, auto rescate y anti-trauma. | I19: N/A
F20: Evaluación médica vigente y compatible | G20: Mensual | H20: Examen médico conforme al “Acuerdo de Homologación de Evaluación de Salud para trabajos en altura física”, emitido por una entidad reconocida. Resultado “Apto”. | I20: N/A
F21: Credencial interna vigente | G21: Mensual | H21: Credencial entregada previa verificación de cumplimiento de requisitos de capacitación y médico. | I21: N/A
F22: Registro consolidado del personal autorizado | G22: Semestral | H22: Base de datos actualizada con trazabilidad del cumplimiento de los requisitos (capacitación, salud, autorización) para cada trabajador. | I22: N/A
F23: Licencia y autorización para operadores de plataformas móviles | G23: Mensual | H23: Para operar plataformas móviles elevadoras, se requiere Licencia Municipal y Autorización Interna específica para el equipo. | I23: N/A
F24: Instrucción en procedimiento de trabajo en altura | G24: Semestral | H24: Instrucción en permiso y procedimiento de trabajo en altura física específico, el que debe incorporar como mínimo los siguientes aspectos: -Uso del SPDC y sus puntos de anclaje. -Uso de plataformas fijas o móviles. -Uso de herramientas en altura. -Respuesta ante emergencia en suspensión. | I24: N/A
B25: RC02 | C25: CCM1 | D25: Uso Correcto de SPDC | E25: Asegurar el uso permanente y correcto (ajuste, conexión) del Sistema Personal para Detención de Caídas (SPDC) certificado e inspeccionado, cada vez que exista exposición a caída desde altura mayor a 1,8 metros. | F25: Certificación del SPDC y sus componentes | G25: Semestral | H25: Todo SPDC (arnés, estrobo, absorbedor, conectores) debe estar certificado por norma chilena o internacional (ej: NCh 1258, ANSI, CE), y registrado como equipo aprobado. | I25: N/A
F26: Inspección periódica por personal autorizado | G26: Mensual | H26: Revisión visual pre-uso por parte del trabajador. Revisión semestral, realizada por un inspector de equipos SPDC, conforme a un programa formal. La frecuencia deberá ajustarse según las condiciones ambientales a las que esté expuesto el equipo. Toda inspección debe quedar registrada en la ficha del equipo. | I26: N/A
F27: Adecuación del SPDC a la tarea | G27: Cada vez | H27: El SPDC debe estar compuesto por elementos compatibles con la tarea y la distancia de caída, incluyendo absorbedores: Tipo 1: Sistema de detención de caídas, incluye absorbedor de energía. Tipo 2: Sistema de sujeción o restricción de desplazamiento, sin absorbedor, evita la caída libre. Sistemas autorretráctiles (SRL) según su clase ANSI: Clase 1 para anclaje sobre el anillo D y Clase 2 a nivel o bajo el anillo D. Todos los componentes deben estar certificados, compatibles y declarados según la tarea. | I27: N/A
F28: Uso correcto del arnés y conexión segura | G28: Cada vez | H28: El arnés debe estar correctamente ajustado y el conector debe estar anclado a un punto seguro (certificado o conforme al diseño original). La organización debe contar con un procedimiento/instructivo que regule esta materia. | I28: N/A
F29: Control del vencimiento del equipo | G29: Mensual | H29: Registro actualizado con fechas de ingreso, vencimiento y baja del SPDC. No se permite uso de equipos vencidos o dañados. | I29: N/A
B30: RC02 | C30: CCM2 | D30: Conexión a Punto Anclaje Certificado | E30: Asegurar que el SPDC esté conectado exclusivamente a un punto de anclaje o sistema de línea de vida que cumpla con certificación vigente, diseño profesional, inspección registrada, identificación visible y capacidad de resistir las cargas de detención de caída según norma. | F30: Certificación y validación de puntos de anclaje | G30: Semestral | H30: Cada punto de anclaje debe estar certificado de fábrica y su instalación debe ser validada por un profesional competente (estructural/calculista) | I30: N/A
F31: Diseño por profesional competente (estructural) | G31: Trimestral | H31: Puntos de anclaje fijos o sistemas de línea de vida deben contar con memoria de cálculo o plano emitido por profesional competente. Toda línea de vida, temporal o permanente, debe estar certificada. No se permiten líneas de vida fabricadas en terreno con prensas tipo candado, aunque cuenten con cálculo estructural. | I31: N/A
F32: Inspección documentada y periódica | G32: Trimestral | H32: Debe existir un programa formal de inspección visual y técnica, con registros físicos o digitales asociados a cada punto de anclaje. | I32: N/A
F33: Identificación clara en terreno | G33: Mensual | H33: Todo punto de anclaje certificado, debe estar identificado en terreno con su resistencia, vigencia y número. No aplica a partes estructurales genéricas como rosetas, salvo que hayan sido certificados expresamente como puntos de anclaje. | I33: N/A
F34: Sistema de control de vigencia y mantenimiento | G34: Trimestral | H34: Registro actualizado del estado de cada punto de anclaje, con fecha de última inspección, próxima revisión y responsable. | I34: N/A
F35: Instrucción al personal sobre puntos de conexión seguros | G35: Anual | H35: Todo trabajador debe estar instruido para identificar visualmente un punto de anclaje seguro y distinguir estructuras no aptas en el área de trabajo. | I35: N/A
B36: RC02 | C36: CCM3 | D36: Capacidad de Rescate en Suspensión | E36: Asegurar que exista un plan específico y operativo de rescate en suspensión, con equipos adecuados, disponibles e inspeccionados en el lugar de trabajo, y con personal entrenado para ejecutar la maniobra en el menor tiempo posible, evitando consecuencias fatales por trauma por suspensión. | F36: Plan de rescate documentado y específico | G36: Semestral | H36: Documento formal asociado a cada tarea en altura que contemple procedimiento, roles, medios y tiempo de respuesta. Debe estar disponible y conocido por el equipo. | I36: N/A
F37: Equipamiento de rescate disponible e inspeccionado | G37: Semestral | H37: Equipos y medios necesarios para rescatar a un trabajador en suspensión deben estar disponibles en el lugar de trabajo, conforme al procedimiento de emergencia aplicable a la tarea. | I37: N/A
F38: Personal entrenado para ejecutar rescates | G38: Semestral | H38: El equipo de trabajo o apoyo debe haber recibido entrenamiento teórico y práctico (incluye uso de sistema anti-trauma). El registro de esto debe estar disponible. | I38: N/A
F39: Simulacros y validación de tiempos de respuesta | G39: Trimestral | H39: Se deben realizar ejercicios que validen el tiempo máximo aceptable de rescate tras una caída con suspensión. Registros deben quedar disponibles. | I39: N/A
F40: Difusión y comunicación del plan de rescate | G40: Trimestral | H40: El plan debe ser comunicado de forma verbal o escrita al equipo antes del inicio de las tareas en altura. | I40: N/A
B42: RIESGO FATALIDAD | C42: CONTROL | D42: NOMBRE DEL CONTROL | E42: REQUISITO | G42: EVIDENCIA | I42: CUMPLIMIENTO | J42: OBSERVACIONES | K42: FECHA IMPLEMENTACIÓN | L42: PLAN MITIGADOR
B43: RC02 | C43: CP1 | D43: Gestión del cambio para modificaciones que afecten trabajos en altura | E43: Toda modificación en el diseño de procesos, tareas o equipos que impliquen cambios en condiciones de trabajo en altura debe ser gestionada a través del sistema de gestión del cambio (GdC). | G43: a. El supervisor(a) debe identificar cambios que afecten seguridad o introduzcan nuevas interacciones no previstas (ej. sustitución de equipos, acceso a nuevas zonas, reubicación de plataformas). | I43: N/A
G44: b. Se debe elaborar un análisis de riesgo específico y documentado antes de implementar cualquier modificación. | I44: N/A
G45: c. Ningún trabajador(a) podrá intervenir estructuras o procesos modificados sin que se haya cerrado formalmente la gestión del cambio. | I45: N/A
B46: RC02 | C46: CP2 | D46: Áreas de tránsito y desplazamiento libres y despejadas | E46: Las zonas de tránsito asociadas a trabajos en altura deben mantenerse libres de obstáculos, materiales, herramientas o residuos que dificulten el desplazamiento seguro del personal. | G46: a. El supervisor(a) debe verificar que los pasillos, accesos a plataformas y escaleras se encuentren habilitados y sin interferencias antes de iniciar tareas. | I46: N/A
G47: b. Se debe implementar una rutina de limpieza y despeje al término de cada jornada o turno de trabajo en altura. | I47: N/A
G48: c. Cualquier obstrucción detectada debe ser retirada de inmediato y registrada como desviación en el checklist de condiciones básicas. | I48: N/A
B49: RC02 | C49: CP3 | D49: Iluminación suficiente y continua en áreas de trabajo en altura (>200 lux) | E49: Todas las áreas donde se realicen trabajos en altura física deben contar con un nivel de iluminación suficiente (de acuerdo a Normativa legal vigente) para permitir el desarrollo seguro de las tareas y el desplazamiento del personal, especialmente en turnos nocturnos o espacios de baja visibilidad. | G49: a. El supervisor(a) deberá verificar que las zonas de trabajo y tránsito asociadas a altura cuenten con una fuente de iluminación funcional, continua y orientada correctamente antes del inicio de cada jornada. | I49: N/A
G50: b. Cuando se trabaje en condiciones de oscuridad parcial (turno noche, túneles, techumbres cerradas o mal iluminadas), se deberán instalar sistemas de iluminación artificial con una intensidad no inferior a 200 lux. | I50: N/A
G51: c. En caso de corte o falla del sistema de iluminación, los trabajos deberán detenerse de inmediato hasta restablecer condiciones de visibilidad segura. | I51: N/A
B52: RC02 | C52: CP4 | D52: Segregación física efectiva del área de trabajo en altura | E52: El área donde se ejecuten trabajos en altura física debe estar segregada mediante barreras físicas y señalización visible, para evitar interferencias de vehículos, equipos móviles u otras actividades que puedan poner en riesgo a los trabajadores. | G52: a. En caso de que la tarea pudiera interactuar con equipos o vehículos, el supervisor(a) debe instalar barreras duras que impidan el ingreso o contacto accidental con estructuras como andamios, plataformas o escaleras. | I52: N/A
G53: b. Se debe señalizar el área de forma visible y continua durante toda la ejecución del trabajo. | I53: N/A
G54: c. La segregación debe verificarse previo al inicio de la tarea y mantenerse hasta el retiro de la estructura. | I54: N/A
B55: RC02 | C55: CP5 | D55: Evaluación y suspensión de trabajos en altura por condiciones climáticas adversas | E55: Antes de iniciar cualquier trabajo en altura al aire libre, se debe evaluar si las condiciones climáticas permiten realizar la tarea de forma segura. En caso contrario, se debe suspender el trabajo de inmediato. | G55: a. El supervisor(a) es responsable de evaluar condiciones climáticas adversas. Ante condiciones como: lluvia, viento, nieve, niebla o riesgo eléctrico por tormentas, se debe considerar la suspensión de los trabajos, si es que la evaluación así lo amerita. | I55: N/A
G56: b. Si las condiciones climáticas superan los límites definidos por el fabricante del equipo o la normativa interna de los Centros de Trabajo, también se debe considerar la suspensión de la actividad. | I56: N/A
G57: c. La decisión de reanudar las actividades debe basarse en una nueva evaluación documentada y validada por supervisor de la tarea. | I57: N/A
B58: RC02 | C58: CM1 | D58: Uso de sistema antitrauma en arnés de cuerpo completo | E58: Todos los Sistemas Personales para Detención de Caídas (SPDC) deben incluir cintas antitrauma integradas al arnés, para reducir los efectos del síndrome de suspensión en caso de caída. | G58: a. El supervisor(a) debe verificar que todos los arneses en uso dispongan de sistema antitrauma incorporado como parte del equipo. | I58: N/A
G59: b. En caso de que el arnés no cuente con dicho sistema, debe ser retirado del área operativa y reemplazado por uno que cumpla con esta exigencia. | I59: N/A
G60: c. El sistema antitrauma debe estar operativo, sin daños visibles, y ser parte de la inspección previa de uso. | I60: N/A

Sheet RF03
B2: GERENCIA DE SEGURIDAD Y SALUD OCUPACIONAL - CHUQUICAMATA
B4: LISTADO DE AUTODIAGNÓSTICO RIESGO DE FATALIDAD N°03: MANIOBRAS DE IZAJE
B6: ELEMENTOS DEL CONTROL | I6: CUMPLIMIENTO GENERAL
I7: =AVERAGEIF(I14:I77,"<>N/A") -> 0
B10: Alcance | C10: El escenario de este riesgo de fatalidad incluye: • Actividades con cargas elevadas por medios mecánicos que incluyen grúas fijas (puente grúa) o móviles (grúas articuladas, grúas telescópicas, grúas de celosía y camión pluma). • Cargas en movimiento, incluido el transporte, elevaciones que involucran múltiples grúas, transferencia de cargas a otras y colapso de grúas. • Operaciones con herramientas manuales de levante (tecle de cadena o palanca, entre otros). • Operaciones de levante con grúa torre. • Operaciones con equipo extiende tubos (sidebooms).
B11: Exclusión | C11: Este evento considera como exclusión los siguientes escenarios: • Operaciones con manipulador de neumáticos. • Operaciones con porta contenedores. • Uso de elevadores en plantas. • Operaciones de levante con grúas horquillas.
B13: RIESGO FATALIDAD | C13: CONTROL CRÍTICO | D13: NOMBRE DEL CONTROL CRÍTICO | E13: OBJETIVO | F13: REQUISITO | G13: MONITOREO | H13: EVIDENCIA | I13: CUMPLIMIENTO | J13: OBSERVACIONES | K13: FECHA IMPLEMENTACIÓN | L13: PLAN MITIGADOR
B14: RC03 | C14: CCP1 | D14: Equipos y elementos de izaje conforme a especificaciones técnicas | E14: Prevenir la falla catastrófica de equipos y elementos de izaje, garantizando que su integridad estructural y funcional se mantiene conforme al diseño del fabricante, a través de un programa de inspección, mantenimiento y certificación. | F14: Plan de Mantenimiento Vigente y Ejecutado. | G14: Trimestral | H14: Solicitar la pauta de mantenimiento del fabricante y los registros de las últimas mantenciones preventivas ejecutadas. | I14: 0
F15: Certificación del Equipo | G15: Anual | H15: Solicitar el certificado del equipo al proveedor, fabricante o representante de la marca. | I15: N/A
F16: Inspección de Pre-uso Diaria Realizada. | G16: Cada vez | H16: Solicitar el checklist de pre-uso del equipo del turno actual, verificando que esté completo y firmado por el operador. | I16: N/A
F17: Integridad y Certificación de Elementos de Izaje. | G17: Semestral | H17: Solicitar que los aparejos (eslingas, grilletes, otros) cuenten con certificación correspondiente. | I17: N/A
F18: Sistemas de Seguridad del Equipo Operativos. | G18: Trimestral | H18: Solicitar registros de pruebas funcionales del sistema limitador de momento de carga (LMI), frenos y paradas de emergencia. | I18: N/A
F19: Personal de Mantenimiento Capacitado | G19: Anual | H19: Solicitar los registros de capacitación del personal (mecánico / eléctrico) en el equipo específico. | I19: N/A
F20: Gestión de Reparaciones Críticas. | G20: Semestral | H20: Toda intervención estructural requiere un procedimiento de reparación y validación de ingeniería documentada. En equipos antiguos o sin información técnica disponible, el área a cargo deberá identificar los componentes críticos y asegurar su integridad. | I20: N/A
B21: RC03 | C21: CCP2 | D21: Estabilizadores operativos y posicionamiento seguro de equipos de izaje | E21: Asegurar que los equipos de izaje móviles posicionen sobre una superficie estable y nivelada, de acuerdo con las especificaciones del fabricante y un análisis del terreno, para prevenir eventuales inestabilidades del equipo durante la maniobra. | F21: Evaluación de Terreno | G21: Cada vez | H21: Solicitar el análisis o protocolo de evaluación de terreno. | I21: N/A
F22: Estabilizadores Completamente Extendidos. | G22: Cada vez | H22: Verificar en terreno que los estabilizadores y sus bases de apoyo (almohadillas) están desplegados al 100% según manual. | I22: N/A
F23: Nivelación del Equipo Verificada. | G23: Cada vez | H23: Verificar visualmente el indicador de nivel(burbuja) del equipo, asegurando que se encuentra dentro de los parámetros de | I23: N/A
F24: Tabla de Carga Visible y Conocida. | G24: Cada vez | H24: Confirmar que la tabla de carga del equipo es visible y legible para el operador y corresponde a la configuración del izaje. | I24: N/A
F25: Condiciones de Viento Controladas. | G25: Cada vez | H25: Solicitar registros de medición de velocidad de viento y verificar que se encuentran dentro de los límites permitidos para la maniobra, según tabla de factores de viento del equipo de izaje. | I25: N/A
F26: Inspección de Sistemas de Estabilidad. | G26: Cada vez | H26: Solicitar checklist de pre-uso que incluya la revisión de neumáticos, sistema de suspensión y sistemas hidráulicos de estabilización. | I26: N/A
F27: Señalización de Barras Estabilizadoras | G27: Semestral | H27: Las barras estabilizadoras del equipo de izaje, deben estar señalizadas con elementos reflectantes, que indiquen sus distintas. | I27: N/A
B28: RC03 | C28: CCP3 | D28: Personal acreditado para maniobras de izaje | E28: Asegurar que toda persona que participe en una maniobra de izaje (operador, rigger, personal de apoyo) posea las competencias técnicas y capacitaciones requeridas, y se encuentre en condiciones físicas y psicológicas adecuadas, para garantizar una ejecución segura y precisa de la tarea. | F28: Acreditación Vigente de Operador y rigger. | G28: Trimestral | H28: Revisar si está operativo y actualizado el sistema que registra las licencias de cada operador y rigger. En terreno solicitar que el operador y riggger porten su licencia, la que debe ser adecuada al equipo y tonelaje. | I28: N/A
F29: Exámenes Psicosensotécnico Vigente. | G29: Anual | H29: Solicitar respaldo de que los exámenes psico- sensotécnicos rigurosos del personal que opera se encuentran vigentes y aprobados, conforme al Acuerdo de Homologación de Salud. | I29: N/A
F30: Evaluación Médica de Aptitud. | G30: Anual | H30: Verificar en el sistema que el personal cuenta con un examen de salud compatible y sin restricciones para el cargo. | I30: N/A
F31: Competencias y Capacitación | G31: Anual | H31: -Solicitar registros de aprobación de curso del riesgo de fatalidad para toda persona que participa en la actividad. -Los operadores deben disponer de la aprobación de un curso teórico y práctico, realizado por OTEC o fabricante/representante de la marca, en la operación del tipo de equipo de izaje de carga (grúas móviles, camiones pluma, puentes grúa, monorrieles, tecles u otros). Se debe considerar evaluación teorica y práctica sobre operación y conocimiento de los sistemas del equipo en marca y modelo, realizada por organismo certificador validado por Chile Valora o fabricante/representantes de la marca. Todo operador de equipos de izaje del tipo móvil, debe contar con Licencia Municipal vigente. -Los Rigger deben cumplir con la aprobación de una capacitación teórico / práctica, realizada por una OTEC. Se debe considerar la certificación o evaluación de sus competencias, según el límite de carga (nivel A, B o C) de la tarea, por un centro acreditado por Chilevalora. | I31: N/A
B32: RC03 | C32: CCP4 | D32: Comunicación bidireccional efectiva entre operador y rigger | E32: Asegurar una comunicación clara, continua y sin ambigüedades entre el rigger y el operador durante toda la maniobra de izaje, utilizando un sistema de comunicación bidireccional radial, para garantizar que cada movimiento sea ejecutado de forma coordinada y segura. | F32: Protocolo de Comunicación para Izaje. | G32: Anual | H32: Solicitar el procedimiento que estandariza las comunicaciones y señales de mano para maniobras de izaje. | I32: N/A
F33: Canal de Radio de Uso Exclusivo. | G33: Por evento | H33: Verificar en el plan de izaje o procedimiento que se ha asignado un canal de radio de uso exclusivo para la maniobra. | I33: N/A
F34: Equipos de Radio Operativos. | G34: Diario | H34: Verificar en terreno que el operador y rigger cuentan con equipos de radio y que estos han sido inspeccionados (batería, funcionalidad). | I34: N/A
F35: Prueba de Comunicación Pre-Izaje. | G35: Diario | H35: Consultar al operador y rigger si realizaron la prueba de comunicación antes de iniciar la maniobra y cómo la documentaron (ej. en ART). | I35: N/A
F36: Señales de Mano Estandarizadas. | G36: Mensual | H36: Verificar que en el área de izaje se encuentre visible la infografía con las señales de mano estandarizadas. | I36: N/A
F37: Protocolo ante Pérdida de Comunicación | G37: Anual | H37: Verificar que el procedimiento de izaje incluye la obligatoriedad de detener toda maniobra ante la pérdida de comunicación. | I37: N/A
B38: RC03 | C38: CCP5 | D38: Plan de Izaje | E38: Asegurar que toda maniobra de izaje sea planificada, coordinada y ejecutada bajo condiciones controladas, considerando la capacidad técnica del equipo, la estabilidad del terreno, las características y centro de gravedad de la carga, las condiciones ambientales y la competencia del personal, garantizando además la integridad y estabilidad de la carga en su disposición final. | F38: Clasificación de Izaje (*Crítico o No Crítico) | G38: Cada vez | H38: Se debe definir si la maniobra de izaje será crítica o no. En caso de ser crítico el Plan debe ser revisado y autorizado por personal especialista de operaciones, mantención, servicios o proyectos de Codelco, independiente de si la tarea es realizada por personal propio o empresa contratista. | I38: N/A
F39: Requisitos y Autorización del Plan de Izaje | H39: El plan de Izaje debe contar al menos con: -Nombre del especialista. -Especificaciones técnicas para asegurar medidas de control para la estabilidad de terreno. -Ángulo de inclinación seguro del equipo respecto al plano de terreno. -Calculo de estabilidad del suelo. (para equipos de mayor tonelaje) -Requerimientos y exigencias para maniobras de izaje críticos y no críticos. -Layout o esquema para las maniobras de izaje críticas. -Tipo de cálculo. -Peso de la carga -Ubicación del centro de gravedad (dentro o fuera del cuerpo del elemento). -Punto de Izaje, entre otros. | I39: N/A
F40: Certificación de Equipos y Elementos de Izaje | G40: Semestral | H40: Solicitar los certificados vigentes de los equipos de izaje (grúas) y de todos los accesorios (eslingas, grilletes, etc.). Verificar en terreno que los elementos físicos coincidan con lo certificado y tengan su inspección del período vigente. | I40: N/A
F41: Análisis de Entorno y Estabilidad del Terreno | G41: Cada vez | H41: Solicitar el registro de evaluación de la superficie de operación. (Para izajes críticos, verificar que el plan esté respaldado por un informe de mecánica de suelos que valide la estabilidad del terreno). | I41: N/A
F42: Análisis y Validación de Punto de Descarga Final | G42: Cada vez | H42: Verificar que el plan de izaje incluye un análisis explícito de la estructura o superficie donde se depositará la carga, respaldado por una memoria de cálculo o validación de ingeniería que garantice su capacidad para soportar el peso. | I42: N/A
F43: Coordinación y Comunicación Previa a la Maniobra | G43: Cada vez | H43: Solicitar el registro de la reunión de coordinación (ej. en ART), donde se demuestre que el plan de izaje completo, incluyendo riesgos, controles y protocolo de comunicación, fue difundido y comprendido por todo el equipo de trabajo antes de iniciar. | I43: N/A
B44: RC03 | C44: CCM1 | D44: Segregación y control de acceso en área de maniobras | E44: Evitar la exposición de personas a la línea de fuego de una maniobra de izaje (caída de carga, volcamiento de equipo, golpe de látigo), asegurando que el área de peligro sea físicamente segregada y el acceso controlado antes, durante y después de la operación. | F44: Plan de Segregación en Plan de Izaje. | G44: Cada vez | H44: Solicitar el plan de izaje y verificar que incluye un diagrama o esquema que define el radio y tipo de segregación requerida. | I44: N/A
F45: Delimitación de Área de Exposición a Cargas Suspendidas | G45: Cada vez | H45: Verificar en terreno que la segregación está implementada con barreras físicas (ej. barreras de concreto, conos con cadena). | I45: N/A
F46: Señalización de Peligro Clara y Visible. | G46: Cada vez | H46: Verificar en terreno la existencia de letreros de advertencia claros ("Peligro: Izaje de Cargas", "No Pasar") en todos los accesos. | I46: N/A
F47: Control de Puntos de Acceso. | G47: Cada vez | H47: Verificar que los puntos de acceso a la zona segregada están controlados, ya sea por barreras o por personal designado (vigía). | I47: N/A
F48: Inspección de la Segregación Pre-Izaje. | G48: Cada vez | H48: Solicitar el checklist o ART donde el supervisor verifica la correcta instalación de la segregación antes de iniciar la maniobra. | I48: N/A
F49: Protocolo de Interacción de Equipos con Infraestructura | G49: Semestral | H49: Solicitar el Plan de Izaje/Rigging revisado y aprobado, verificando que incluya Layouts de montaje y planos constructivos. Solicitar el registro de la reunión de coordinación previa firmada por el ejecutor, empresas afectadas y el dueño de área. En alto tonelaje, exigir además memoria de suelo y catastro subterráneo. | I49: N/A
B50: RC03 | C50: CCM2 | D50: Capacidad de respuesta ante emergencia | E50: Garantizar una respuesta sistémica, inmediata y eficaz ante una emergencia asociada a maniobras de izaje. | F50: Plan de Respuesta a Emergencia Específico. | G50: Por evento | H50: Solicitar el plan de rescate para la maniobra de izaje, verificando que define roles, recursos y comunicaciones. Se debe definir el tipo de emergencia y la forma de actuar para una de ellas. | I50: N/A
F51: Personal Entrenado en el Plan de Emergencia. | G51: Anual | H51: Solicitar los registros de capacitación del equipo de trabajo en el plan de emergencia y en la activación de la alarma. Este registro debe ser validad por el Jefe Emergencia del Centro de Trabajo. | I51: N/A
F52: Brigada de Rescate Capacitada. | G52: Semestral | H52: Solicitar los registros de entrenamiento y simulacros de la brigada de emergencia en escenarios de accidentes de izaje. | I52: N/A
F53: Equipos de Rescate Disponibles e Inspeccionados. | G53: Mensual | H53: Verificar que la brigada de emergencia cuente con la existencia y el registro de inspección vigente del kit de respuesta a emergencias (camilla, inmovilizadores, etc.). | I53: N/A
F54: Canales de Comunicación de Emergencia Claros. | G54: Mensual | H54: Verificar que el plan de izaje y la señalización en terreno indiquen claramente el número de teléfono o canal de radio de emergencia. | I54: N/A
B56: RIESGO FATALIDAD | C56: CONTROL | D56: NOMBRE DEL CONTROL | E56: REQUISITO | G56: EVIDENCIA | I56: CUMPLIMIENTO | J56: OBSERVACIONES | K56: FECHA IMPLEMENTACIÓN | L56: PLAN MITIGADOR
B57: RC03 | C57: CP1 | D57: Uso de Anemómetro | E57: Todos los equipos de izaje móviles, como grúas móviles y camiones pluma, deben contar con un anemómetro operativo para medir la velocidad del viento | G57: a. El operador del equipo debe verificar la operatividad y correcta lectura del anemómetro durante la inspección pre-operacional, dejando registro de esta verificación en la lista de chequeo del equipo. | I57: N/A
G58: b. Antes de iniciar y durante la maniobra de izaje, el operador debe medir la velocidad del viento y suspender la maniobra si esta supera el límite máximo permitido por el fabricante en la tabla de carga para la configuración específica del izaje. | I58: N/A
G59: c. Toda falla, daño o descalibración del anemómetro debe ser reportada de inmediato al supervisor, y el equipo no debe ser utilizado para maniobras de izaje hasta que el instrumento sea reparado y certificado. | I59: N/A
B60: RC03 | C60: CP2 | D60: Tabla de carga del equipo visible en cabina | E60: La cabina de todo equipo de izaje debe contar con la tabla de capacidades de carga original del fabricante, la cual debe estar permanentemente disponible, legible y en idioma español. | G60: a. El operador debe verificar en su inspección pre-operacional que la tabla de carga se encuentra en la cabina, está completa, no presenta daños que impidan su lectura y corresponde al modelo y serie del equipo que opera. | I60: N/A
G61: b. El operador tiene la prohibición de ejecutar maniobras si la tabla de carga no está disponible, es ilegible o está en un idioma que no comprende. | I61: N/A
G62: c. Para planificar y ejecutar la maniobra, el operador y el rigger deben utilizar obligatoriamente los datos de esta tabla para confirmar que el peso, ángulo, radio y configuración de la pluma no exceden la capacidad del equipo. | I62: N/A
B63: RC03 | C63: CP3 | D63: Evaluación y suspensión por condiciones climáticas | E63: Toda maniobra de izaje debe ser suspendida si las condiciones climáticas adversas impiden la operación segura del equipo o la correcta visibilidad y comunicación entre el operador y el rigger. | G63: a. El supervisor a cargo de la maniobra es responsable de evaluar las condiciones climáticas antes y durante el izaje, teniendo la autoridad para ordenar la detención inmediata de las tareas. | I63: N/A
G64: b. La operación debe ser detenida en presencia de tormentas eléctricas, vientos que superen los límites de la tabla de carga, lluvia intensa, nieve o neblina densa que restrinja la visibilidad de la carga, del área de maniobra o las señales del rigger. | I64: N/A
G65: c. El operador del equipo tiene la obligación de detener la maniobra si considera que las condiciones climáticas ponen en riesgo la seguridad, aun sin recibir una instrucción directa de la supervisión, debiendo informar inmediatamente su decisión. | I65: N/A
B66: RC03 | C66: CP4 | D66: Uso de llaves de bloqueo | E66: Las llaves para desbloquear o puentear los sistemas de seguridad de un equipo de izaje (limitadores de carrera, LMI, etc.) deben ser de uso restringido y custodiadas por la supervisión del área. | G66: a. El operador del equipo tiene prohibido mantener en su poder o utilizar la llave de desbloqueo de sistemas de seguridad para operar el equipo fuera de sus límites de diseño. | I66: N/A
G67: b. El uso de la llave de desbloqueo solo será autorizado por el supervisor responsable del equipo y únicamente para fines de mantenimiento o para resolver una emergencia, dejando un registro documentado que justifique su uso. | I67: N/A
G68: c. El personal de mantenimiento debe retirar la llave y devolverla a custodia de la supervisión inmediatamente después de finalizada la intervención que requirió su uso. | I68: N/A
B69: RC03 | C69: CP5 | D69: Código de colores mensual de inspección | E69: Todos los aparejos y elementos de izaje deben ser inspeccionados formalmente con una frecuencia definida y ser marcados con el color del mes o período correspondiente para evidenciar su revisión. | G69: a. El supervisor del área debe asegurar que exista un programa de inspección periódica para todos los elementos de izaje, asignando un código de colores que se actualiza mensualmente o según la frecuencia que defina el área. | I69: N/A
G70: b. El rigger, antes de utilizar un aparejo, debe verificar que este porte la cinta o marca del color correspondiente al período vigente, indicando que la inspección formal está al día. | I70: N/A
G71: c. Está prohibido utilizar cualquier elemento de izaje que no cuente con el código de color vigente o que, a pesar de tenerlo, presente daños evidentes en la inspección pre-uso. | I71: N/A
B72: RC03 | C72: CP6 | D72: Señalización visible en puntos de bloqueo y zonas energizadas | E72: Todos los puntos de aislamiento y bloqueo de energías de un equipo de izaje deben estar claramente identificados y señalizados, así como las zonas cercanas a líneas eléctricas aéreas. | G72: a. El personal de mantenimiento debe verificar que las fuentes de energía (eléctrica, hidráulica, neumática) del equipo estén señalizadas en terreno para facilitar su bloqueo seguro antes de una intervención. | I72: N/A
G73: b. En maniobras cercanas a líneas eléctricas, el supervisor debe instalar señalización de advertencia visible que indique el peligro y la distancia mínima de seguridad que debe mantenerse entre el equipo y los conductores energizados. | I73: N/A
G74: c. El operador y el rigger deben conocer la simbología de advertencia de peligro eléctrico y respetar las distancias de seguridad establecidas en el plan de izaje. | I74: N/A
B75: RC03 | C75: CM2 | D75: Sistema de Parada de Emergencia | E75: Todos los equipos y máquinas deben contar con un sistema de parada de emergencia que cumpla con los criterios de diseño, instalación, funcionamiento y competencia del personal. | G75: a. El dispositivo de parada de emergencia debe estar claramente identificado y señalizado en el equipo, con su ubicación definida en planos, y contar con un instructivo de uso en español que asegure su accesibilidad y protección contra obstrucciones como barro o nieve. | I75: N/A
G76: b. La operatividad del sistema debe ser asegurada mediante una inspección de pre-uso por parte del operador y su confiabilidad debe ser validada a través de un programa de mantenimiento preventivo que incluya pruebas de funcionamiento documentadas. | I76: N/A
G77: c. El operador del equipo debe estar formalmente entrenado y ser evaluado en la ejecución práctica de la activación de la parada de emergencia durante una operación y en la correcta desactivación posterior. | I77: N/A

Sheet RF04
B2: GERENCIA DE SEGURIDAD Y SALUD OCUPACIONAL - CHUQUICAMATA
B4: LISTADO DE AUTODIAGNÓSTICO RIESGO DE FATALIDAD N°04: LIBERACIÓN DESCONTROLADA DE ENERGÍAS
B6: ELEMENTOS DEL CONTROL | I6: CUMPLIMIENTO GENERAL
I7: =AVERAGEIF(I14:I62,"<>N/A") -> 0
B10: Alcance | C10: Su alcance comprende actividades tales como: Construcción, instalación, montaje, intervención, ajustes, inspección, mantención, reparación, pruebas, puesta en marcha, operación y modificaciones en herramientas, equipos, maquinaria, instalaciones y sistemas con presencia de estas energías. Este riesgo aplica a todas aquellas energías que pudieran provocar un accidente grave o fatal, tales como: • Potencial • Mecánica • Neumática • Hidráulica • Entre otras.
B11: Exclusión | C11: Se excluyen de este Riesgo las siguientes energías: • Energía Eléctrica • Energía Cinética de Vehículos y Equipos • Energía Química • Energía Calórica • Interacción Mecánica / Atrapamientos • Tiro y Arrastre • Explosivos • Caída de Objetos y Personas • Sistemas de Baja Energía (que no representen riesgo de accidentes graves y/o fatales)
B13: RIESGO FATALIDAD | C13: CONTROL CRÍTICO | D13: NOMBRE DEL CONTROL CRÍTICO | E13: OBJETIVO | F13: REQUISITO | G13: MONITOREO | H13: EVIDENCIA | I13: CUMPLIMIENTO | J13: OBSERVACIONES | K13: FECHA IMPLEMENTACIÓN | L13: PLAN MITIGADOR
B14: RC04 | C14: CCP1 | D14: Identificación, aislación, bloqueo y verificación de energía cero | E14: Garantizar que toda intervención en equipos y sistemas se ejecute bajo una condición verificada de energía cero, asegurando la identificación, aislación, bloqueo y control de energias residuales para eliminar la liberación descontrolada de energía. | F14: Procedimiento de Aislación y Bloqueo Vigente. | G14: Anual | H14: Solicitar el procedimiento de bloqueo para sistemas de alta presión y verificar su última fecha de revisión y su difusión. | I14: 0
F15: Información Técnica y Diagramas Actualizados. | G15: Semestral | H15: Solicitar o planos/manuales técnicos (mecánica/potencial) y verificar en terreno que los puntos de bloqueo y liberación de energía residual coinciden con la realidad. Semestral | I15: N/A
F16: Personal Capacitado para Aislación y Bloqueo. | G16: Anual | H16: Solicitar competencias según perfil o descriptor de cargo y los registros de aprobación de capacitaciones para el personal que ejecuta tareas de aislación y bloqueo. | I16: N/A
F17: Dispositivos de Bloqueo Estandarizados. | G17: Trimestral | H17: Verificar en pañol y en terreno que los dispositivos de bloqueo (ej. bloqueadores de válvula) son los estandarizados y están en buen estado. | I17: N/A
F18: Verificación de Energía Cero en terreno. | G18: Semestral | H18: Solicitar el procedimiento y verificar en terreno que se ejecuta la medición o comprobación de ausencia de energía antes de intervenir el equipo. | I18: N/A
F19: Registros de Bloqueo y Permisos de Trabajo. | G19: Mensual | H19: Solicitar los permisos de trabajo y las tarjetas de bloqueo de una intervención reciente y verificar su correcto llenado y autorización. | I19: N/A
B20: RC04 | C20: CCP2 | D20: Sistemas y elementos de contención de energía | E20: Garantizar que todo componente crítico de contención o retención de energía opere bajo sus especificaciones originales de diseño, asegurando su reemplazo oportuno ante el cumplimiento de su vida útil definida o cualquier evidencia de deterioro en su condición, para evitar fallas catastróficas. | F20: Certificación y Especificación de Componentes. | G20: Anual | H20: Verificar que los componentes críticos (mangueras, cables, frenos, acumuladores) instalados corresponden a las especificaciones originales del fabricante y cuentan con su certificación de calidad/origen. | I20: N/A
F21: Plan de Mantenimiento e Inspección. | G21: Mensual | H21: Solicitar el programa de mantenimiento y verificar los registros de inspección de los sistemas de energía, asegurando la detección de fatiga, desgaste o fugas. | I21: N/A
F22: Criterios de Reemplazo (Vida Útil o Condición). | G22: Trimestral | H22: Solicitar la pauta técnica que define el momento de cambio (por fecha de vencimiento/horas o por criterio de rechazo técnico/condición) y verificar su cumplimiento. | I22: N/A
F23: Disponibilidad de Repuestos Críticos. | G23: Semestral | H23: Verificar la disponibilidad de stock o componentes de recambio para elementos de seguridad, asegurando la continuidad operacional sin improvisaciones. | I23: N/A
F24: Competencias del Mantenedor. | G24: Anual | H24: Solicitar registros que definan y respalden las competencias del personal que inspecciona y reemplaza componentes críticos. | I24: N/A
F25: Prohibición de Reparaciones Improvisadas. | G25: Mensual | H25: Verificar en terreno la ausencia de reparaciones no estandarizadas ("parches", soldaduras hechizas, nudos) en elementos sometidos a presión o tensión. | I25: N/A
B26: RC04 | C26: CCP3 | D26: Dispositivos de protección y alivio de presión | E26: Garantizar la operatividad y vigencia de todos los dispositivos diseñados para limitar, aliviar o contener la energía crítica (válvulas de seguridad, limitadores de carrera, frenos de emergencia, celdas de carga), asegurando que se mantengan calibrados y protegidos contra intervenciones no autorizadas. | F26: Inventario de Dispositivos de Protección. | G26: Anual | H26: Solicitar el inventario completo de dispositivos de protección de presión (válvulas de alivio, etc.) por equipo. | I26: N/A
F27: Programa de Calibración y Certificación. | G27: Semestral | H27: Solicitar el programa de mantenimiento y los certificados de calibración vigentes para las válvulas de alivio. | I27: N/A
F28: Inspección de Instrumentos de Medición. | G28: Mensual | H28: Solicitar los registros de inspección de pre-uso y mantenimiento que verifiquen el buen estado de los manómetros. | I28: N/A
F29: Sellos de Seguridad Intactos. | G29: Trimestral | H29: Verificar en terreno que los dispositivos de protección de presión cuentan con sus sellos de seguridad o precintos intactos. | I29: N/A
F30: Prohibición de Modificación no Autorizada. | G30: Anual | H30: Solicitar el procedimiento que prohíbe y sanciona la adulteración de los dispositivos de seguridad de los equipos. | I30: N/A
F31: Gestión de Fallas y Reparaciones. | G31: Por evento | H31: Solicitar los registros de mantenimiento correctivo y verificar que las reparaciones de estos dispositivos se realizan por personal capacitado. | I31: N/A
B32: RC04 | C32: CCM1 | D32: Segregación y control de acceso | E32: Impedir la exposición de personas a la línea de fuego durante pruebas de presión o en zonas con riesgo de falla de componentes hidráulicos/neumáticos, asegurando que el área de peligro sea físicamente segregada y el acceso estrictamente controlado. | F32: Procedimiento de Segregación para Pruebas. | G32: Anual | H32: Solicitar el procedimiento que define el tipo de barrera y el cálculo del radio de exclusión para pruebas de presión. | I32: N/A
F33: Implementación de Barreras Físicas (Duras). | G33: Por evento | H33: Verificar en terreno que el área de la prueba está aislada con barreras físicas efectivas (ej. biombos, barreras de concreto). | I33: N/A
F34: Señalización de Peligro Clara y Visible. | G34: Por evento | H34: Verificar en terreno la existencia de letreros de advertencia claros ("Peligro: Prueba Hidráulica", "No Pasar") en todos los accesos. | I34: N/A
F35: Control de Puntos de Acceso. | G35: Por evento | H35: Verificar que los puntos de acceso a la zona segregada están controlados, ya sea por barreras o por personal designado (vigía). | I35: N/A
F36: Comunicación Radial Previa. | G36: Por evento | H36: Solicitar el registro o consultar al supervisor si se realizó la comunicación radial a todas las áreas antes de iniciar la presurización. | I36: N/A
F37: Verificación al Cumplimiento de Segregación. | G37: Trimestral | H37: Solicitar los informes de verificaciones o inspecciones al cumplimiento de la segregación en terreno. | I37: N/A
B38: RC04 | C38: CCM2 | D38: Capacidad de respuesta ante emergencia | E38: Garantizar una respuesta sistémica, inmediata y eficaz tras una liberación descontrolada de energías, integrando la comunicación, la brigada y la atención médica, para rescatar y atender a las personas afectadas en el menor tiempo posible. | F38: Plan de Emergencia Específico Vigente. | G38: Anual | H38: Solicitar el plan de emergencia y verificar su instrucción a los trabajadores. | I38: N/A
F39: Brigada y Personal Médico Entrenados. | G39: Semestral | H39: Solicitar los registros de entrenamiento de la brigada y del personal de salud en manejo de lesiones por liberación descontrolada de energías. | I39: N/A
F40: Sistemas de Comunicación de Emergencia Funcionales. | G40: Trimestral | H40: Solicitar registros de pruebas funcionales de los sistemas de comunicación y de los canales de emergencia. | I40: N/A
F41: Simulacros Específicos Realizados y Evaluados. | G41: Semestral | H41: Solicitar el informe del último simulacro de liberación de liberación descontrolada de energía, verificando tiempos de respuesta y planes de acción. | I41: N/A
F42: Personal Capacitado en Respuesta Inicial. | G42: Trimestral | H42: Verificar en terreno, mediante entrevistas, que el personal conoce el protocolo de aviso y las acciones de primera respuesta. | I42: N/A
B44: RIESGO FATALIDAD | C44: CONTROL | D44: NOMBRE DEL CONTROL | E44: REQUISITO | G44: EVIDENCIA | I44: CUMPLIMIENTO | J44: OBSERVACIONES | K44: FECHA IMPLEMENTACIÓN | L44: PLAN MITIGADOR
B45: RC04 | C45: CP1 | D45: Mapa actualizado de líneas y sistemas presurizados | E45: Todas las áreas operativas deben contar con diagramas o planos (P&ID) actualizados y disponibles, que identifiquen la totalidad de los sistemas, líneas y equipos que operan con energía hidráulica o neumática a presiones mayores o iguales a 6 bares. | G45: a. El supervisor del área es responsable de asegurar que los diagramas de sus sistemas presurizados se encuentren en su última versión, reflejando fielmente la instalación en terreno, incluyendo todas las modificaciones. | I45: N/A
G46: b. Antes de planificar cualquier intervención, el supervisor y el personal ejecutor deben consultar los diagramas para identificar correctamente las líneas, los puntos de aislación, las válvulas de venteo y otras fuentes de energía. | I46: N/A
G47: c. Los diagramas deben estar disponibles en formato físico o digital en puntos de consulta accesibles para todo el personal del área, como salas de control, oficinas de supervisión o pañoles de mantenimiento. | I47: N/A
B48: RC04 | C48: CP2 | D48: Rotulación e identificación de líneas y componentes | E48: Todas las líneas, cañerías, mangueras y componentes críticos de los sistemas hidráulicos y neumáticos deben estar claramente identificados en terreno mediante rotulación física estandarizada. | G48: a. La rotulación debe indicar, como mínimo, el nombre o código del fluido, la dirección del flujo y la presión nominal de operación del sistema, utilizando el código de colores y la simbología definidos por la compañía. | I48: N/A
G49: b. El personal de mantenimiento, durante sus inspecciones, debe verificar que la rotulación se encuentre presente, legible y en buen estado, gestionando su reposición en caso de deterioro o ausencia. | I49: N/A
G50: c. El personal ejecutor debe usar la rotulación en terreno como una herramienta de verificación para confirmar que la línea o equipo a intervenir coincide con la identificada en los diagramas y en la orden de trabajo. | I50: N/A
B51: RC04 | C51: CP3 | D51: Dispositivos de drenaje y venteo manual | E51: Los sistemas presurizados deben contar con dispositivos de drenaje y venteo instalados en puntos estratégicos que permitan la despresurización manual y segura del sistema antes de una intervención. | G51: a. El personal de mantenimiento debe verificar la operatividad de las válvulas de venteo y drenaje durante las inspecciones programadas, asegurando que no estén obstruidas, dañadas o presenten fugas. | I51: N/A
G52: b. El procedimiento de aislación y bloqueo debe incluir explícitamente la apertura de estas válvulas como paso obligatorio para la verificación de energía cero, después de haber cerrado la fuente de energía principal. | I52: N/A
G53: c. Los puntos de drenaje deben estar diseñados para dirigir el fluido de manera controlada hacia un contenedor o sistema de recolección, evitando derrames o la proyección directa hacia personas o equipos. | I53: N/A
B54: RC04 | C54: CP4 | D54: Protecciones físicas adicionales en equipos | E54: Los equipos y componentes que contengan energía hidráulica o neumática a alta presión deben contar con protecciones físicas, como guardas o cubiertas, para contener la energía en caso de una falla súbita de un componente. | G54: a. El personal de mantenimiento debe asegurar que todas las protecciones físicas asociadas a sistemas presurizados estén correctamente instaladas, en buen estado y sin modificaciones no autorizadas. | I54: N/A
G55: b. Está prohibido operar equipos o sistemas si sus guardas o cubiertas de protección han sido removidas o se encuentran dañadas. | I55: N/A
G56: c. El personal que interviene un equipo debe reinstalar todas las protecciones físicas inmediatamente después de finalizar los trabajos de mantenimiento o reparación y antes de volver a energizar el sistema. | I56: N/A
B57: RC04 | C57: CP5 | D57: Señalización física de zonas de trabajo. | E57: Toda área donde se realicen trabajos de intervención en sistemas con posible liberación de energía, debe ser delimitada y señalizada físicamente para advertir del peligro y restringir el acceso a personal no autorizado. | G57: a. El supervisor a cargo de la tarea es responsable de instalar barreras físicas (barreras duras, conos con cadenas) y señalización de advertencia antes de iniciar cualquier trabajo que implique abrir o intervenir un sistema presurizado. | I57: N/A
G58: b. La señalización debe indicar claramente el tipo de trabajo que se está realizando, el riesgo de liberación de energía y el nombre del responsable de la tarea a quien contactar para autorizar el ingreso. | I58: N/A
G59: c. La segregación debe permanecer instalada durante todo el tiempo que dure la intervención y solo podrá ser retirada por el personal a cargo una vez que el sistema haya sido normalizado y se encuentre en condición segura. | I59: N/A
B60: RC04 | C60: CM1 | D60: Dispositivos de protección contra sobrepresión secundarios | E60: Los sistemas hidráulicos y neumáticos deben contar con dispositivos secundarios de alivio de presión, como válvulas de seguridad o discos de ruptura, para actuar en caso de que el sistema de control principal falle y la presión exceda el límite de diseño. | G60: a. El especialista de mantenimiento debe verificar que estos dispositivos estén instalados, calibrados a la presión correcta y con su sello de certificación vigente, según lo especificado en las fichas técnicas y el plan de mantenimiento. | I60: N/A
G61: b. Está prohibido alterar, bloquear o anular cualquier dispositivo de alivio de presión. Cualquier falla detectada debe ser reparada de inmediato, manteniendo el equipo fuera de servicio hasta su corrección. | I61: N/A
G62: c. La descarga de estos dispositivos debe estar orientada hacia una zona segura, donde una activación inesperada no proyecte fluidos o energía hacia personas, pasillos de tránsito o equipos críticos. | I62: N/A

Sheet RF05
B2: GERENCIA DE SEGURIDAD Y SALUD OCUPACIONAL - CHUQUICAMATA
B4: LISTADO DE AUTODIAGNÓSTICO RIESGO DE FATALIDAD N°05: CAÍDA DE ROCAS EN MINA RAJO
B6: ELEMENTOS DEL CONTROL | I6: CUMPLIMIENTO GENERAL
I7: =AVERAGEIF(I14:I44,"<>N/A") -> 0
B10: Alcance | C10: Caída de rocas individual o masiva en áreas operativas de minería a cielo abierto, que puede resultar en lesiones graves y/o fatales por aplastamiento o impacto a las personas. Escenarios definidos son: • Carguío de mineral en la frente. • Descarga de mineral en stock. • Carguío de estéril. • Descarga de estéril en botaderos. • Limpieza de taludes. • Limpieza o saneamiento de bancos.
B11: Exclusión | C11: Este evento considera como exclusión los siguientes escenarios. • Deslizamiento de rocas en pilas. • Excavaciones para construcción (proyectos). • Tronaduras de producción y cierre. (Fly rock) • Tronadura secundaria.(Fly rock) • Tronaduras civiles (Fly rock) (proyectos) • Inestabilidades a nivel de banco, inter-rampa y talud global. • Caída de rocas desde CAEX durante el transporte de material.
B13: RIESGO FATALIDAD | C13: CONTROL CRÍTICO | D13: NOMBRE DEL CONTROL CRÍTICO | E13: OBJETIVO | F13: REQUISITO | G13: MONITOREO | H13: EVIDENCIA | I13: CUMPLIMIENTO | J13: OBSERVACIONES | K13: FECHA IMPLEMENTACIÓN | L13: PLAN MITIGADOR
B14: RF05 | C14: CCP1 | D14: MODELO Y MONITOREO GEOTÉCNICO DE ESTABILIDAD DE TALUDES Y BANCOS | E14: Anticipar y controlar la inestabilidad de taludes y bancos, asegurando que el diseño minero se base en un modelo geotécnico válido y que la monitoreo continua de las zonas de riesgo permita tomar decisiones operacionales oportunas para prevenir la caída de rocas | F14: Captura Sistemática y Actualización de Modelos. | G14: Trimestral | H14: Solicitar el modelo geotécnico y verificar el registro de sus últimas actualizaciones con data de mapeo y sondajes. | I14: 0
F15: Bases Geotécnicas para Diseño Vigentes. | G15: Anual | H15: Solicitar el informe de bases geotécnicas para el diseño actual del rajo, verificando el cumplimiento de los criterios de aceptabilidad. | I15: N/A
F16: Mapa de RiesgoGeotécnico Actualizado y Difundido | G16: Diario | H16: Solicitar el mapa de riesgos geotécnicos del turno y verificar su actualización y los registros de difusión al personal. | I16: N/A
F17: Monitoreo Continuo Geotécnico | G17: Semanal | H17: Solicitar reportes de disponibilidad del monitoreo geotécnico y verificar en la sala de control que están en línea y vigilando zonas críticas. | I17: N/A
F18: Gestión de Alertas de Monitoreo. | G18: Diario | H18: Solicitar el protocolo de gestión de alertas y los registros de las últimas alertas, verificando su correcta gestión. | I18: N/A
F19: Evaluación Geométrica (Sistema Full Control). | G19: Mensual | H19: Solicitar los reportes del sistema de evaluación de talud (Full Control) para verificar la conciliación geométrica de los bancos | I19: N/A
F20: Personal Especialista Competente. | G20: Anual | H20: Solicitar el listado de competencias según perfil o descriptor del cargo y documentos que respalden su cumplimiento, para el personal que interpreta los datos geotécnicos y toma decisiones 24/7. | I20: N/A
B21: RF05 | C21: CCP2 | D21: SANEAMIENTO Y LIMPIEZA DE BERMAS Y TALUDES | E21: Mantener los bancos y taludes en condiciones de diseño, asegurando que el saneamiento y limpieza sistemática eliminen el material suelto o colgado para prevenir la caída de rocas | F21: Plan de Saneamiento Sistemático. | G21: Mensual | H21: Solicitar el programa de saneamiento de taludes y los registros que demuestren su cumplimiento | I21: N/A
F22: ProcedimientoOperacional de Saneamiento | G22: Trimestral | H22: Solicitar el procedimiento de trabajo seguro para saneamiento y verificar su aplicación en terreno | I22: N/A
F23: Personal Capacitado para Saneamiento. | G23: Anual | H23: Solicitar registros de curso del riesgo de fatalidad e instrucción del procedimiento de saneamiento y respaldos de la experiencia del personal y supervisores a cargo | I23: N/A
F24: Uso de Equipos Adecuados. | G24: Semanal | H24: Verificar en terreno que los equipos utilizados para el saneamiento son los definidos en el estándar para esa tarea. | I24: N/A
F25: Inspección Geotécnica Post-Saneamiento | G25: Por Evento | H25: Solicitar el informe o registro de la inspección geotécnica que valida la efectividad del saneamiento realizado | I25: N/A
F26: Protocolo de Recepción Conforme de Área | G26: Trimestral | H26: Solicitar el registro de "recepción conforme"del área saneada, firmado por la supervisión antes de reanudar las operaciones. | I26: N/A
B27: RF05 | C27: CCP3 | D27: CONTROL TOPOGRÁFICO Y DRENAJE | E27: Controlar la geometría de las frentes de carguío y gestionar los afloramientos de agua, para prevenir la formación de material colgado y la inestabilidad del talud inducida por la presencia de agua | F27: Estándar de Altura de Frente de Carguío. | G27: Anual | H27: Solicitar el estándar que define la altura máxima de la frente de carguío según el tipo de equipo y material. | I27: N/A
F28: Monitoreo Topográfico de Frentes | G28: Semanal | H28: Solicitar informes de medición topográfica que verifiquen el cumplimiento de la altura y geometría de las frentes de carguío | I28: N/A
F29: Procedimiento de Rebaje de Altura. | G29: Por Evento | H29: Solicitar el procedimiento para rebajar frentes fuera de estándar y los registros de su ejecución. | I29: N/A
F30: Mapa de Afloramientos de Agua. | G30: Mensual | H30: Solicitar el mapa que identifica los puntos de afloramiento de agua en bancos y verificar su actualización | I30: N/A
F31: Plan de Gestión de Drenajes | G31: Mensual | H31: Solicitar el plan de acción y los registros de ejecución para la canalización o drenaje de los afloramientos identificados. | I31: N/A
F32: Competencias del Personal | G32: Anual | H32: Solicitar y verificar las competencias del perfil o descriptor del cargo del personal que realiza mediciones topográficas y gestión de drenajes. | I32: N/A
B33: RF05 | C33: CCM1 | D33: ISEGREGACIÓN FÍSICA Y CONTENCIÓN ESTRUCTURAL | E33: Contener la caída de rocas y restringir el acceso a zonas de riesgo, mediante la instalación de sistemas de contención (mallas, pretiles) y la implementación de barreras físicas para proteger a las personas y equipos expuestos. | F33: Diseño Geotécnico de Sistemas de Contención | G33: Anual | H33: Solicitar el diseño o estándar técnico para pretiles, mallas u otras barreras, verificando su aprobación por Geotecnia. | I33: N/A
F34: Implementación y Mantención de Contención | G34: Semanal | H34: Solicitar informes de inspección topográfica y visual que verifiquen el cumplimiento de la geometría y estado de los pretiles y mallas. | I34: N/A
F35: Mapa de Zonas de Riesgo Actualizado. | G35: Diario | H35: Solicitar el mapa de riesgo geotécnico del turno y verificar la clara identificación de zonas que requieren segregación | I35: N/A
F36: Implementación de Barreras Físicas (Duras). | G36: Semanal | H36: Verificar en terreno que las zonas de alto riesgo están aisladas con barreras físicas efectivas según estándar. | I36: N/A
F37: Protocolo de Control de Acceso Formal | G37: Trimestral | H37: Solicitar el procedimiento de autorización de ingreso a áreas restringidas y revisar los registros de permisos emitidos | I37: N/A
F38: Verificación alCumplimiento de contención y segregación | G38: Trimestral | H38: Solicitar los informes de inspección que verifiquen el cumplimiento de la contención y segregación en terreno. | I38: N/A
B39: RF05 | C39: CCM2 | D39: CAPACIDAD DE RESPUESTA ANTE EMERGENCIA | E39: Garantizar una respuesta sistémica, inmediata y eficaz tras un deslizamiento o caída de rocas, integrando la alarma, la evacuación, la brigada de rescate y la atención médica, para rescatar y atender a las personas afectadas en el menor tiempo posible. | F39: Plan de Emergencia Específico para Deslizamientos. | G39: Anual | H39: Solicitar el plan de emergencia y verificar su actualización, incluyendo protocolos de alarma, evacuación y rescate. | I39: N/A
F40: Brigada de Rescate Entrenada | G40: Semestral | H40: Solicitar los registros de entrenamiento de los integrantes de la brigada en rescate en taludes. | I40: N/A
F41: Equipamiento de Rescate y Atención Médica Operativo. | G41: Mensual | H41: Solicitar los registros de inspección mensual de los equipos de rescate (ambulancia, equipos y herramientas especializadas). | I41: N/A
F42: Sistema de Alarma yComunicación Funcional. | G42: Trimestral | H42: Solicitar registros de pruebas funcionales de los sistemas de alarma y de los canales de comunicación de emergencia | I42: N/A
F43: Simulacros Específicos Realizados y Evaluados. | G43: Semestral | H43: Solicitar el informe del último simulacro de deslizamiento, verificando tiempos de respuesta y planes de acción de las brechas. | I43: N/A
F44: Personal Capacitado en el Plan de Emergencia. | G44: trimestral | H44: Verificar que el personal ha sido instruido en el plan de emergencia y conoce el protocolo de aviso y las rutas de evacuación. | I44: N/A
B46: RIESGO FATALIDAD | C46: CONTROL | D46: NOMBRE DEL CONTROL | E46: REQUISITO | G46: EVIDENCIA | I46: CUMPLIMIENTO | J46: OBSERVACIONES | K46: FECHA IMPLEMENTACIÓN | L46: PLAN MITIGADOR
B47: RF05 | C47: CP1 | D47: MONITOREO DE SECTORES DETENIDOS / SIN OPERACIÓN | E47: Toda área de la mina que haya estado inactiva o sin operaciones por un período prolongado debe ser formalmente evaluada por personal especialista antes de autorizar el reingreso y el reinicio de los trabajos. | G47: El supervisor del área es responsable deasegurar que los accesos a sectores detenidos se encuentren físicamente bloqueados con pretiles o barreras y debidamente señalizados, prohibiendo el ingreso no autorizado. | I47: N/A
G48: b. Antes de reprogramar trabajos en el sector, un inspección en terreno, evaluar la estabilidad actual del macizo rocoso y emitir un informe con las recomendaciones de saneamiento,fortificación o monitoreo requeridas. | I48: N/A
G49: c. La reanudación de las operaciones solo podrá ser autorizada por el dueño del área una vez que todas las recomendaciones emitidas en el informe geotécnico hayan sido implementadas y verificadas en terreno. | I49: N/A

Sheet RF06
B2: GERENCIA DE SEGURIDAD Y SALUD OCUPACIONAL - CHUQUICAMATA
B4: LISTADO DE AUTODIAGNÓSTICO RIESGO DE FATALIDAD N°06: INCENDIO
B6: ELEMENTOS DEL CONTROL | I6: CUMPLIMIENTO GENERAL
I7: =AVERAGEIF(I14:I43,"<>N/A") -> 0.4
B10: Alcance | C10: Este documento aplica al riesgo de fatalidad de Incendio, presente en los distintos centros de trabajo, plantas de proceso, minas (rajo y subterránea) y proyectos. Cubre actividades tales como la ejecución de trabajos en caliente (oxicorte, soldadura, corte, desbaste, plasma); el almacenamiento y manipulación de materiales inflamables y combustibles,considerando su separación e incompatibilidades; la intervención en sistemas eléctricos y sus protecciones (sobretensión y sobrecorriente) en equipos e instalaciones; el uso de equipos con superficies de alta fricción susceptibles de generar aumentos de temperatura y el mantenimiento de equipos y componentes críticos con potencial de generar temperatura de ignición.
B11: Exclusión | C11: Se excluyen del Riesgo de Fatalidad: •Manipulación y manejo de explosivos •Actividades de tronadura •Piromanía
B13: RIESGO FATALIDAD | C13: CONTROL CRÍTICO | D13: NOMBRE DEL CONTROL CRÍTICO | E13: OBJETIVO | F13: REQUISITO | G13: MONITOREO | H13: EVIDENCIA | I13: CUMPLIMIENTO | J13: OBSERVACIONES | K13: FECHA IMPLEMENTACIÓN | L13: PLAN MITIGADOR
B14: RF06 | C14: CCP1 | D14: MAPEO DE ÁREAS CRÍTICAS Y GESTIÓN DE MATERIALES COMBUSTIBLES E INFLAMABLES | E14: Establecer las zonas, áreas e instalaciones más susceptibles a la generación de un incendio, asegurando que la organización y el personal las conozcan. Prevenir incendios controlando el combustible, asegurando que todos los materiales inflamables y combustibles sean almacenados en lugares autorizados, segregados según su compatibilidad, y manipulados de acuerdo a procedimientos para evitar su contacto con fuentes de ignición. | F14: Mapa de Áreas Críticas de Riesgo de Incendio | G14: Semestral | H14: Verificar que el proceso para identificar y mapear áreas críticas esté documentado, actualizado y difundido. En terreno verificar que los mapas son visibles y conocidos por el personal. | I14: 0.4
F15: Procedimiento de Almacenamiento y Segregación. | G15: Anual | H15: Solicitar el procedimiento que define los requisitos para bodegas y zonas de almacenamiento (ventilación, contención, señalización). | I15: N/A
F16: Matriz de Incompatibilidad Química Aplicada. | G16: Mensual | H16: Solicitar la matriz de incompatibilidad y verificar en terreno que los productos químicos están segregados según corresponda | I16: N/A
F17: Inventario y Cantidades Máximas Controladas. | G17: Trimestral | H17: Solicitar el inventario de la bodega y verificar que no se exceden las cantidades máximas de almacenamiento permitidas. | I17: N/A
F18: Hojas de Datos de Seguridad (HDS) Disponibles. | G18: Semestral | H18: Verificar que el personal conoce las HDS de todos los productos almacenados están disponibles, actualizadas y son conocidas por el personal. | I18: N/A
F19: Procedimientos de Manipulación y Derrame. | G19: Anual | H19: Solicitar los procedimientos para el trasvasije seguro y para la respuesta a derrames. Verificar que los kits de derrame están completos. | I19: N/A
B20: RF06 | C20: CCP2 | D20: CONTROL DE TRABAJOS EN CALIENTE | E20: Prevenir la ignición de materiales por trabajos que generan calor o chispas, tales como soldadura, oxicorte, corte, desbaste y plasma, asegurando que toda tarea cuente con un permiso formal, el área esté segregada y libre de combustibles, y se mantenga una vigilancia continua | F20: Procedimiento de Trabajo en Caliente. | G20: Anual | H20: Solicitar el procedimiento vigente que define los requisitos para la planificación, autorización y ejecución de trabajos en caliente | I20: N/A
F21: Permiso de Trabajo en Caliente (PTC) | G21: Diario | H21: Solicitar el PTC de una tarea en ejecución o recién terminada, verificando su correcto llenado, firmas y autorización. | I21: N/A
F22: Inspección y Segregación del Área. | G22: Por Evento | H22: Verificar en terreno que el área del trabajo en caliente está limpia de combustibles y segregada físicamente (biombos, mantas). | I22: N/A
F23: Asignación de Vigía de Fuego | G23: Por Evento | H23: Verificar en el PTC o en terreno que se ha designado un vigía de fuego exclusivo para la tarea y que permanece el tiempo requerido. | I23: N/A
F24: Equipos de Extinción Disponibles. | G24: Por Evento | H24: Verificar en terreno la existencia de un extintor operativo y apropiado en el punto de trabajo en caliente | I24: N/A
F25: Personal Capacitado | G25: Anual | H25: Solicitar registros de la capacitación. Estos cursos deben ser: Curso del riesgo de fatalidad y Curso para ejecutor de trabajo en caliente y vigía | I25: N/A
B26: RF05 | C26: CCP3 | D26: SISTEMAS DE PROTECCIÓN CONTRA FUENTES DE IGNICIÓN | E26: Prevenir la ignición de materiales por fallas de equipos, asegurando que los sistemas eléctricos cuenten con protecciones certificadas y operativas, y que se monitoree la temperatura de componentes mecánicos críticos para detectar sobrecalentamientos antes de que generen un incendio. | F26: Protecciones Eléctricas Certificadas y Operativas. | G26: Anual | H26: Solicitar los registros de pruebas y certificación de las protecciones de sobrecarga y cortocircuito de equipos críticos. | I26: N/A
F27: Programa de Inspección Termográfica. | G27: Trimestral | H27: Solicitar el programa de termografía y los informes de las últimas inspecciones a tableros eléctricos y equipos mecánicos. | I27: N/A
F28: Gestión de Hallazgos Termográficos. | G28: Mensual | H28: Solicitar los planes de acción derivados de los informes de termografía y verificar el cierre de las anomalías detectadas | I28: N/A
F29: Integridad de Cables e Instalaciones Eléctricas. | G29: Mensual | H29: Solicitar los registros de inspección planeada que verifiquen el buen estado de cables, canalizaciones y tableros eléctricos | I29: N/A
F30: Sistemas de Detección de Temperatura Operativos. | G30: Semanal | H30: Verificar en terreno o en sala de control que los sensores de temperatura de equipos críticos (correas, motores) están en línea y funcionando. | I30: N/A
F31: Mantenimiento Preventivo de Componentes Mecánicos. | G31: Trimestral | H31: Solicitar el programa de mantenimiento y los registros de ejecución para componentes con riesgo de sobrecalentamiento por fricción. | I31: N/A
B32: RF06 | C32: CCM1 | D32: SISTEMAS DE DETECCIÓN Y EXTINCIÓN DE INCENDIOS | E32: Detectar un incendio en su fase inicial y controlarlo o extinguirlo antes de que se propague, mediante sistemas de detección automática, equipos de supresión fijos y la disponibilidad de equipos de extinción portátiles operativos y de fácil acceso. | F32: Programa de Inspección y Mantenimiento (PIM) | G32: Trimestral | H32: Solicitar el PIM para todos los sistemas contra incendios y los registros que evidencien su cumplimiento. | I32: N/A
F33: Sistemas de Detección Automática Operativos. | G33: Semestral | H33: Solicitar los informes de las últimas pruebas funcionales realizadas a los sistemas de detección de humo, calor o llama. | I33: N/A
F34: Sistemas de Supresión Automática Operativos | G34: Trimestral | H34: Solicitar los certificados de inspección y mantenimiento de los sistemas de supresión de equipos móviles y salas críticas. | I34: N/A
F35: Extintores Portátiles Inspeccionados y Certificados. | G35: Mensual | H35: Verificar en terreno que los extintores tienen su sello de inspección mensual y su certificación anual vigente, y están libres de obstrucción. | I35: N/A
F36: Redes Húmedas y Gabinetes Operativos. | G36: Semestral | H36: Solicitar los registros de inspección y pruebas de caudal/presión de las redes húmedas y el estado de sus gabinetes. | I36: N/A
F37: Personal Capacitado en Uso de Extintores | G37: Anual | H37: Solicitar los registros de capacitación del personal en el uso de extintores portátiles. | I37: N/A
B38: RF06 | C38: CCM2 | D38: CAPACIDAD DE RESPUESTA ANTE EMERGENCIAS | E38: Garantizar una respuesta sistémica, inmediata y eficaz ante un incendio, integrando la comunicación, la brigada de emergencia y la atención médica, para controlar el fuego, evacuar al personal y atender a los lesionados en el menor tiempo posible. | F38: Plan de Emergencia Específico para Incendios. | G38: Anual | H38: Solicitar el plan de emergencia y verificar su actualización, incluyendo roles, protocolos de comunicación y evacuación | I38: N/A
F39: Brigada de Emergencia Entrenada. | G39: Semestral | H39: Solicitar los registros de entrenamiento de los integrantes de la brigada | I39: N/A
F40: Equipamiento de Brigada y Rescate Operativo | G40: Mensual | H40: Solicitar los registros de inspección mensual de los equipos de la brigada (trajes, ERA, herramientas, carro bomba) | I40: N/A
F41: Sistemas de Alarma y Comunicación Funcionales. | G41: Trimestral | H41: Solicitar registros de pruebas funcionales de los sistemas de alarma y de los canales de comunicación de emergencia. | I41: N/A
F42: Simulacros Específico Realizados y Evaluados. | G42: Semestral | H42: Solicitar el informe del último simulacro de incendio, verificando tiempos de respuesta, evacuación y planes de acción | I42: N/A
F43: Vías de Evacuación Despejadas y Señalizadas | G43: Mensual | H43: Realizar inspecciones en terreno para verificar que las rutas de evacuación, salidas y puntos de encuentro están despejados. | I43: N/A
B45: RIESGO FATALIDAD | C45: CONTROL | D45: NOMBRE DEL CONTROL | E45: REQUISITO | G45: EVIDENCIA | I45: CUMPLIMIENTO | J45: OBSERVACIONES | K45: FECHA IMPLEMENTACIÓN | L45: PLAN MITIGADOR
B46: RF06 | C46: CP1 | D46: ZONAS DESIGNADAS PARA FUMAR | E46: Queda estrictamente prohibido fumar en todas las áreas operativas, excepto en aquellas zonas explícitamente designadas, habilitadas para fumadores | G46: a. El supervisor del área debe asegurar que las zonas de fumadores estén claramente señalizadas, delimitadas y equipadas con recipientes seguros (colilleros) disposición de cenizas y colillas. | I46: N/A
G47: b. Las zonas de fumadores deben ubicarse a una distancia y la segura de cualquier material combustible, inflamable o de áreas de almacenamiento de sustancias peligrosas, conforme al mapa de riesgos del área. | I47: N/A
B48: RF06 | C48: CP2 | D48: SISTEMA DE REFRIGERACIÓN DE EQUIPOS | E48: Los equipos y componentes críticos que generan altas temperaturas por su funcionamiento deben contar con sistemas de refrigeración operativos y mantenidos según las especificaciones del fabricante. | G48: a. El personal de mantenimiento debe ejecutar el programa de inspección y mantenimiento de los sistemas de refrigeración (radiadores,ventiladores, niveles de fluidos refrigerantes),dejando registro de cada intervención. | I48: N/A
G49: b. El operador del equipo debe verificar diariamente en la inspección pre-operacional el estado y funcionamiento de los sistemas de refrigeración, y monitorear los indicadores de temperatura durante la operación. | I49: N/A
G50: c. Cualquier anomalía, fuga o sobrecalentamiento detectado en el sistema de refrigeración debe ser reportado de inmediato a la supervisión y el equipo debe ser detenido hasta que se realice la evaluación y reparación por parte de personal calificado. | I50: N/A
B51: RF06 | C51: CP3 | D51: ENCLAVAMIENTO DE SISTEMAS DE AIRE ACONDICIONADO EN SALAS ELÉCTRICAS | E51: Los sistemas de ventilación y aire acondicionado (HVAC) de las salas eléctricas deben estar enclavados con los sistemas de detección de incendios para cortar automáticamente el suministro de aire en caso de amago. | G51: a. El personal de mantenimiento eléctrico e instrumentación debe verificar periódicamente la operatividad de este enclavamiento,realizando pruebas funcionales documentadas para asegurar que la señal del detector activa la detención del sistema HVAC. | I51: N/A
G52: b. La lógica de control del enclavamiento debe estar documentada en los planos eléctricos y de control de la sala, y cualquier modificación debe ser gestionada a través del protocolo de gestión de cambio. | I52: N/A
G53: c. El supervisor de la sala eléctrica debe asegurar que este sistema de protección no sea neutralizado o puesto en modo manual sin una autorización formal y por un período de tiempo acotado y controlado. | I53: N/A
B54: RF06 | C54: CP4 | D54: PROTECCIONES PARA MANGUERAS HIDRÁULICAS | E54: Las mangueras hidráulicas que transportan fluidos inflamables a alta temperatura deben estar protegidas contra el daño mecánico y el contacto con superficies calientes | G54: a. El personal de mantenimiento debe asegurar que las mangueras hidráulicas estén instaladas con sus revestimientos protectores (ej. fundas ignífugas, espirales plásticos) en todos los tramos expuestos a roce, abrasión o cercanía a fuentes de calor como escapes o motores. | I54: N/A
G55: b. Durante las inspecciones de los equipos, el operador debe verificar visualmente que las protecciones de las mangueras estén en su lugar, sin daños, y que no existan mangueras rozando con partes móviles o estructurales. | I55: N/A
G56: c. Se prohíbe operar equipos con mangueras hidráulicas desprotegidas o dañadas. Cualquier condición de riesgo debe ser reportada para su reparación inmediata. | I56: N/A
B57: RF06 | C57: CM1 | D57: ZANJAS CORTA FUEGO | E57: Se deben construir y mantener zanjas o franjas libres de vegetación y material combustible alrededor de instalaciones críticas o en áreas con alta carga de fuego para actuar como barrera de contención y dificultar la propagación de un incendio. | G57: a. El supervisor del área es responsable de definir, según el mapa de riesgos, la ubicación y dimensiones de las zanjas cortafuego, asegurando que su diseño sea el adecuado para la topografía y la carga combustible del sector. | I57: N/A
G58: b. Se debe ejecutar un programa de mantenimiento periódico para asegurar que las zanjas cortafuego permanezcan despejadas, sin acumulación de vegetación seca, basura u otro material combustible que pueda comprometer su efectividad. | I58: N/A
G59: c. Las inspecciones programadas de seguridad del área deben incluir la verificación visual del estado de las zanjas cortafuego, dejando registro de su condición y gestionando las acciones correctivas que sean necesaria. | I59: N/A
B60: RF06 | C60: CM2 | D60: VÍAS DE EVACUACIÓN Y SALIDAS DE EMERGENCIA DESPEJADAS Y SEÑALIZADAS | E60: Todas las instalaciones, plantas y edificios deben contar con vías de evacuación y salidas de emergencia claramente identificadas,señalizadas y permanentemente despejadas. | G60: a. El supervisor de cada área es responsable de asegurar que las vías de evacuación y las salidas de emergencia se mantengan libres de cualquier tipo de obstrucción, como materiales, equipos o mobiliario. | I60: N/A
G61: b. La señalización de las rutas de escape y salidas de emergencia debe ser visible, estar en buen estado y cumplir con la normativa de colores y simbología, incluyendo iluminación emergencia en caso de corte de energía. | I61: N/A
G62: c. Se deben realizar inspecciones periódicas documentadas para verificar la condición de las vías de evacuación, las salidas de emergencia y su señalética, gestionando la corrección inmediata de cualquier desviación. | I62: N/A

Sheet RF07
B2: GERENCIA DE SEGURIDAD Y SALUD OCUPACIONAL - CHUQUICAMATA
B4: LISTADO DE AUTODIAGNÓSTICO RIESGO DE FATALIDAD N°07: SUSTANCIAS PELIGROSAS
B6: ELEMENTOS DEL CONTROL | I6: CUMPLIMIENTO GENERAL
I7: =AVERAGEIF(I14:I39,"<>N/A") -> 0.4
B10: Alcance | C10: Aplica para todas las divisiones y empresas contratistas, las cuales, dentro de sus procesos operativos, existan actividades/tareas con interacción del personal en la carga/descarga, transporte, almacenamiento, muestreo y dosificación, asi como el uso/manipulación de sustancias químicas peligrosas. Se incluyen sustancias químicas peligrosas y sus derivados en los procesos de transporte, almacenamiento, utilización o generación a granel, a presión atmosférica o contenedores presurizados, pudiendo ser estas inflamables, corrosivas, asfixiantes, tóxicas y/o comburentes como: •Sulfhidrato de socio NASH •Cloro - Gas Cloro (Cl₂g) •Ácido Clorhídrico •Ácido Sulfúrico - Ácido Sulfhídrico •Peróxido de Hidrógeno •Hidróxido de Sodio •Ácido Nítrico •Nitrógeno •Óxido de calcio (Cal viva) •Dióxido de Carbono CO₂ (Líquido criogénico) •Sustancias Inflamables. •Sustancias Corrosivas. Sustancias Toxicas Sustancias envasadas en bodegas, almacenamientos menores o áreas de procesos Las sustancias que no aparezcan en el listado anterior requieren de un análisis para evaluar la necesidad de crear un nuevo Control Crítico Específico. No se permiten almacenamientos irregulares o almacenamientos “temporales” en areas de proceso que no cumplan con los requisitos definidos en presente riesgo de fatalidad. En el caso de las sustancias intermedias no aisladas de los procesos, deberan cumplir con los controles CCP1 y CCP2, de tal manera de asegurar el que las actividades con estas sustancias cumplan con la señalización y otros controles básicos, para evitar desviaciones en su manipulación.
B11: Exclusión | C11: Sustancias Químicas NO peligrosas •Residuos Peligrosos •Sustancias biológicas •Sustancias explosivas reguladas en el RF08.
B13: RIESGO FATALIDAD | C13: CONTROL CRÍTICO | D13: NOMBRE DEL CONTROL CRÍTICO | E13: OBJETIVO | F13: REQUISITO | G13: MONITOREO | H13: EVIDENCIA | I13: CUMPLIMIENTO | J13: OBSERVACIONES | K13: FECHA IMPLEMENTACIÓN | L13: PLAN MITIGADOR
B14: RF07 | C14: CCP1 | D14: DISEÑO, OPERACIÓN Y SEÑALIZACIÓN EN PROCESOS DE MANEJO Y ALMACENAMIENTO DE SUSTANCIAS QUÍMICAS PELIGROSAS | E14: Prevenir la liberación (o descontrol) de sustancias químicas peligrosas, asegurando que toda infraestructura de almacenamiento (estanques, bodegas), líneas de transporte y puntos de muestreo / dosificación cumplan con un diseño técnico que contemple la contención/monitoreo preventivo de derrames/fugas, la ventilación de gases, probables generaciones de incendios, señalización de todos los elementos y la segregación según compatibilidad química. | F14: Diseño original y posibles modificaciones. | G14: Cada 2 años | H14: Solicitar evidencias del diseño de instalaciones y componentes (sistemas de bombeo, materialidades, sensores, etc.) y manual de funcionamiento. Protocolos y/o metodologías para analizar y documentar cambios en el diseño. No se permiten almacenamientos irregulares o almacenamientos “temporales” en áreas de proceso que no cumplan con los requisitos | I14: 0.4
F15: Segregación por Incompatibilidad Química. | G15: Trimestral | H15: Solicitar documento de análisis de compatibilidad de sustancias almacenadas/ transportadas. | I15: N/A
F16: Señalización y rotulación | G16: Semestral | H16: Verificar que el transporte, almacenamientos, zonas de carga/descarga, líneas de transporte y puntos de dosificación están señalizadas o demarcadas de acuerdo a normativa aplicada vigente y/o estándares internos. Las sustancias envasadas reguladas por el DS. 57 deben estar etiquetadas. | I16: N/A
F17: Contención Secundaria operativa. | G17: Anual | H17: Solicitar documento con estudio de volumetria del pretil y los registros de inspección que verifican la integridad y estanqueidad del sistema de contención. | I17: N/A
F18: Equipamiento para la detección | G18: Semestral | H18: Solicitar plan, registros de mantenimiento, calibración y pruebas funcionales de equipamientos para la detección temprana de eventos con sustancias químicas en áreas, procesos y/o instalaciones | I18: N/A
F19: Control de Acceso Restringido | G19: Semestral | H19: Verificar que instalación de almacenamiento y procesos consustancias peligrosas cuenten con un sistema de acceso restringido | I19: N/A
F20: Control de tareas críticas | G20: Cada vez | H20: Todas aquellas tareas consideradas como críticas, de acuerdo a Reglamento Corporativo de Sustancias químicas, deberán contar con lo siguientes requisitos: Procedimiento o instructivo específico. Check list de aplicación del procedimiento o instructivo con firma del supervisor y trabajador. Asignación de Supervisión permanente. | I20: N/A
F21: Kits de emergencia específicos disponibles | G21: Mensual | H21: Inspección visual de kits en terreno, registros de inspección de contenido y chequeo de fechas de vencimiento de insumos. | I21: N/A
B22: RF07 | C22: CCP2 | D22: COMPETENCIAS PARA MANIPULACIÓN SEGURA DE SUSTANCIAS PELIGROSAS | E22: Prevenir la exposición a sustancias químicas peligrosas, asegurando que toda tarea de manipulación se realice por personal autorizado y con las competencias necesarias, siguiendo un procedimiento específico, coordinaciones internas y utilizando las herramientas y EPP correctos definidos en la Hoja de Datos de Seguridad (HDS) o en estándares internos. | F22: Planes de Capacitación por Roles | G22: Anual | H22: Solicitar los planes de capacitación de acuerdo a roles y sus respectivos registros de capacitación, considerando a lo menos el curso del riesgo de fatalidad y requisitos legales | I22: N/A
F23: HDS Disponible en Punto de Uso | G23: Semanal | H23: Verificar en terreno que las Hojas de Datos de Seguridad (HDS) de las sustancias en uso estan disponible y accesibles (papel y/o digital) y los trabajadores han recibido instrucción de éstas | I23: N/A
F24: Procedimientos específicos vigentes y difundidos. | G24: Anual | H24: Solicitar el procedimiento para una tarea específica (ej. trasvasije) y verificar que está actualizado, difundido y los trabajadores han recibido instrucción de éstas. | I24: N/A
F25: Actuación ante emergencias | G25: Trimestral | H25: Solicitar registros de instrucción a trabajadores de los Planes de emergencias específicos de las sustancias peligrosas del área. | I25: N/A
B26: RF07 | C26: CCP3 | D26: AISLACIÓN, BLOQUEO Y SEGREGACIÓN EN OPERACIONES CON SUSTANCIAS PELIGROSAS | E26: Mantener un control permanente de las variables operacionales, sensores de fuga, sistemas de detección de incendios y garantizar que, antes de intervenir un sistema con sustancias químicas peligrosas, se aísle la línea, se bloquee la energía, se drene el producto y se segregue el área para prevenir cualquier contacto o liberación inesperada. | F26: Procedimiento de Aislación y Bloqueo de Químicos. | G26: Anual | H26: Solicitar el procedimiento vigente para intervenir procesos con sustancias peligrosas, incluyendo los pasos de aislación, mediciones previas, bloqueo, drenaje y verificación, y los trabajadores han sido | I26: N/A
F27: Puntos de Aislación Identificados. | G27: Semestral | H27: Solicitar el P&ID de la línea y verificar en terreno que las válvulas de bloqueo y puntos de drenaje están claramente identificados. | I27: N/A
F28: Registros de tareas de aislación y bloqueo | G28: Semestral | H28: Evidencias de todos los registros que solicita el procedimiento de aislación y bloqueo (por ejemplo identificación de puntos de bloqueo, segregaciones y candados y tarjetas de bloqueo) | I28: N/A
B29: RF07 | C29: CCM1 | D29: SISTEMAS DE DETECCIÓN / CONTROL DE FUGAS,DERRAMES, INCENDIOS Y EPP QUÍMICOS | E29: Minimizar las consecuencias de un derrame, alertándolo, conteniéndolo en su origen, y proteger al personal de la exposición mediante el uso de Elementos de Protección Personal (EPP) específicos para la sustancia, y la disponibilidad deduchas y lavaojos de emergencia | F29: Estándar de EPP por proceso y/o area con presencia de sustancias quimicas. | G29: Anual | H29: Solicitar el estudio de EPP por proceso y/o área con presencia de sustancia química y verificar evidencia de uso por parte de los trabajadores en el área | I29: N/A
F30: Duchas de Emergencia y Lavaojos Operativos. | G30: Semestral | H30: Evidenciar existencia y registros de inspección y pruebas de activación de las duchas y lavaojos, dejando registro de la prueba, de forma semanal. | I30: N/A
F31: Kits de Contención de Derrames disponibles | G31: Semestral | H31: Verificar en terreno que los kits de contención están completos, sellados y ubicados en los puntos designados. | I31: N/A
F32: Sistemas de control de incendios | G32: Trimestral | H32: Evidenciar existencia, idoneidad del agente de extinción y que los sistemas de control de incendios cuenten con sus mantenciones al día. | I32: N/A
F33: Equipos de Monitoreo Personal. | G33: Semestral | H33: Asegurar la existencia, mantención, calibración y correcto uso de detectores personales, segun el estandar de cada área, proceso y/o instalación | I33: N/A
B34: RF07 | C34: CCM2 | D34: CAPACIDAD DE RESPUESTA ANTE EMERGENCIA QUÍMICA | E34: Garantizar una respuesta sistémica, inmediata y eficaz ante una emergencia química, integrando la comunicación, la brigada especializada (HAZMAT) y la atención médica, para controlar el evento, rescatar y atender a las personas afectadas. | F34: Plan de Emergencia Específico por Sustancia | G34: Anual | H34: Solicitar el plan de emergencia y verificar que incluye escenarios y respuestas específicas para las sustancias peligrosas del área. | I34: N/A
F35: Brigada Especializada en nivel HAZMAT. | G35: Anual | H35: Solicitar los registros de entrenamiento y certificaciones vigentes de la brigada en niveles de respuesta HAZMAT. | I35: N/A
F36: Equipamiento de Brigada y Descontaminación. | G36: Semestral | H36: Solicitar los catastros actualizados y registros de inspección mensual de los equipos de la brigada (trajes encapsulados, SCBA, equipos de monitoreo) | I36: N/A
F37: Sistemas de Alarma y Comunicación Funcionales. | G37: Trimestral | H37: Solicitar registros de pruebas funcionales de los sistemas de alarma (sirenas) y de los canales de comunicación de emergencia | I37: N/A
F38: Simulacros de Emergencia Química Realizados. | G38: Anual | H38: Solicitar el informe de simulacros de emergencia química, verificando tiempos de respuesta y planes de acción. | I38: N/A
F39: Protocolos de Atención Médica Específicos. | G39: Anual | H39: Solicitar los protocolos médicos y verificar la disponibilidad de antídotos o tratamientos especiales para las sustancias críticas | I39: N/A
B41: RIESGO FATALIDAD | C41: CONTROL | D41: NOMBRE DEL CONTROL | E41: REQUISITO | G41: EVIDENCIA | I41: CUMPLIMIENTO | J41: OBSERVACIONES | K41: FECHA IMPLEMENTACIÓN | L41: PLAN MITIGADOR
B42: RF07 | C42: CP1 | D42: ANALISÍS DE COMPATIBILIDAD QUÍMICA | E42: En todas las bodegas y áreas de almacenamiento se deben realizar un análisis compatibilidad química de acuerdo a la sección 10 de las HDS; Estabilidad y reactividad, y así segregar físicamente las sustancias peligrosas, evitando el incompatibles. contacto entre productos | G42: a. El encargado de la bodega o área de almacenamiento debe consultar la HDS de los productos e identificar las posibles incompatibilidades, basada en las características de peligrosidad de las sustancias. | I42: N/A
G43: b. Antes de almacenar cualquier sustancia nueva, el personal responsable debe asegurar que se cumplan los distanciamientos (ej 2,4 metros) y sistemas de contención de derrames independientes. | I43: N/A
G44: c. El supervisor del área debe verificar periódicamente, mediante inspecciones documentadas, que el almacenamiento físico en la bodega es coherente con las segregaciones definidas en el análisis de compatibilidad. | I44: N/A
B45: RF07 | C45: CP2 | D45: ETIQUETADO Y ROTULACIÓN DE ENVASES | E45: Todo recipiente o contenedor, original o de trasvasije, que contenga una sustancia peligrosa debe contar con una etiqueta o rótulo que identifique claramente el producto y sus peligros | G45: a. La etiqueta debe incluir, como mínimo, el nombre del producto, pictogramas de peligro y la información principal de la Hoja de Datos de Seguridad (HDS), conforme a los estándares de comunicación de peligros. | I45: N/A
G46: b. El personal que realiza un trasvasije es responsable de asegurar que el nuevo recipiente sea rotulado inmediatamente con toda la información requerida antes de ser almacenado o utilizado. | I46: N/A
G47: c. El supervisor debe verificar durante sus inspecciones que todos los contenedores en su área se encuentren correctamente rotulados y que las etiquetas sean legibles, indelebles y estén en buen estado. | I47: N/A
B48: RF07 | C48: CP3 | D48: INVENTARIO DE SUSTANCIAS PELIGROSAS | E48: Toda área que almacene o manipule sustancias químicas peligrosas debe mantener un inventario actualizado y detallado de todos los productos presentes con las respectivas distribuciones y/o procesos involucrados | G48: a. El responsable de cada área de almacenamiento debe mantener un registro(físico o digital) con la lista de todas las sustancias químicas, indicando su nombre, fabricante (de acuerdo a la HDS) cantidad, clasificación de peligrosidad ubicación y fecha de ingreso | I48: N/A
G49: b. El inventario debe ser actualizado cada vez que ingrese o se retire un producto de la bodega, y debe ser verificado físicamente mediante un conteo periódico con una frecuencia de al menos 6 meses. | I49: N/A
G50: c. La Hoja de Datos de Seguridad (HDS) actualizada de acuerdo a la normativa vigente, de cada producto listado en el inventario debe estar disponible y accesible de forma inmediata para todo el personal que interactúa con dichas sustancias | I50: N/A
B51: RF07 | C51: CP4 | D51: MONITOREO, PROTECCIÓN, MANTENIMIENTO Y CONTROL DE SUSTANCIAS PELIGROSAS EN TUBERIAS | E51: Las tuberías, de acuerdo al tipo de producto deben utilizar distintas materialidades y sistemas de control o mitigación en caso de derrames, cómo flujómetros en entrada y salida, uniones de tipo flange en cañerías, (especialmente en puntos de alto riesgo o sobre áreas de tránsito) camisas térmicas en sustancias que tienden a cristalizarse o congelarse, etc. | G51: a. El personal de operación/mantenimiento debe verificar/asegurar que todas las tuberías cuenten con los requisitos de diseño o de seguridad en el transporte y que cuenten con sus protecciones operativas. | I51: N/A
G52: b. Está prohibido operar un sistema que no cuente con los dispositivos de protección de acuerdo a la sustancia, han sido removidas o se encuentran dañadas, debiendo ser reportada la condición para su inmediata reposición. | I52: N/A
B53: RF07 | C53: CP5 | D53: DIAGRAMAS DE CICLO DE VIDA DE SUSTANCIAS QUÍMICAS PELIGROSAS EN EL PROCESO. | E53: Se debe contar con planos 'as built'actualizados de toda infraestructura de transporte y almacenamiento, detallando líneas, dosificación, bombeo, válvulas, sensores y sistemas críticos asociados. | G53: a. El dueño del área es responsable de asegurar que cualquier modificación, ampliación o cambio en los sistemas de tuberías sea registrado y actualizado en los planos correspondientes calificado. | I53: N/A
G54: b. Los planos "as built" deben estardisponibles para la planificación de trabajos de mantenimiento, operación y respuesta a emergencias, y deben ser la única fuente de información de ingeniería válida. | I54: N/A
G55: c. El personal ejecutor debe verificar en terreno que la disposición de las líneas y componentes coincide con lo indicado en los planos antes intervención. | I55: N/A
B56: RF06 | C56: CP6 | D56: DISPOSITIVOS DE MEDICIÓN DE VARIABLES CLAVES Y CONTROL DE EMERGENCIAS OPERATIVOS | E56: Los sistemas almacenamiento de bombeo, deben líneas contar y con instrumentación operativa y calibrada (presión, caudal), incorporando sensores específicos (ej. pH, termocuplas) según el tipo de sustancia. | G56: a. El operador de la planta o sistema debe monitorear continuamente las lecturas de los manómetros y flujómetros para asegurar que la operación se mantiene dentro de los rangos de diseño establecidos. | I56: N/A
G57: b. El personal de instrumentación debe ejecutar el plan de calibración y mantenimiento de todos los medidores, asegurando que cada instrumento cuente con un certificado y/o etiqueta de calibración vigente. | I57: N/A
G58: c. Cualquier lectura de presión o caudal que exceda los límites normales de operación debe ser reportada de inmediato al supervisor del área para investigar la causa y tomar las acciones correctivas necesarias, debiendo contar con protocolos de contingencia definido. | I58: N/A
B59: RF07 | C59: CP7 | D59: PROCEDIMIENTO DE GESTIÓN DE CAMBIO EN EL MANEJO DE SUSTANCIAS QUÍMICAS PELIGROSAS. | E59: Con el objetivo de asegurar siempre la utilización de materialidades, componentes y características técnicas de los dispositivos, es que cada vez que se requiera realizar un cambio, cómo puede ser la incorporación de nuevas etapas al proceso, cambio de caracteristicas fisico-química de las sustancias,nuevos procesos asociados a la sustancia, cambios operacionales, desuso de áreas, retiro de borras,actividades de desarme de infraestructura o cambios rutinarios por actividades demantenimiento, se debe asegurar un protocolo de gestión del cambio que asegure el análisis técnico especialista y comunicación/capacitación a todas las áreas involucradas. Dicho procedimiento debe considerar un plan con medidas concretas y especificaciones técnicas que validen la comunicación a todo el personal relacionado y seguridad de las operaciones. | I59: N/A
B60: RF07 | C60: CM1 | D60: SEÑALIZACIÓN Y RUTAS DE EVACUACIÓN EN ÁREAS QUÍMICAS | E60: Toda área con sustancias peligrosas debe mantener rutas de evacuación señalizadas y expeditas, asegurando el desplazamiento seguroa zonas de seguridad ante emergencias químicas. | G60: a. Se deben elaborar y mantener actualizados los Planos de emplazamiento que incluyan la señalización y demarcación de sitios, zonas de seguridad y rutas de evacuación específicas para la respuesta ante emergencias químicas. | I60: N/A
G61: b. El layout de las áreas operativas debe definir y señalizar claramente la ubicación del punto de encuentro de emergencias, las zonas de seguridad y las vías de tránsito de peatones. | I61: N/A
G62: c. Toda la señalización, incluyendo letreros, señales de seguridad, demarcaciones de tuberías, debe implementarse de acuerdo a las normativas técnicas vigentes. | I62: N/A

Sheet RF08
B2: GERENCIA DE SEGURIDAD Y SALUD OCUPACIONAL - CHUQUICAMATA
B4: LISTADO DE AUTODIAGNÓSTICO RIESGO DE FATALIDAD N°08: TRONADURAS Y EXPLOSIVOS
B6: ELEMENTOS DEL CONTROL | I6: CUMPLIMIENTO GENERAL
I7: =AVERAGEIF(I14:I42,"<>N/A") -> 1
B10: Alcance | C10: Su alcance abarca la gestión integral del ciclo de vida de los explosivos: almacenamiento, transporte, manipulación, carguío, conexión, iniciación de tronadura y verificación post-tronadura, manteniendo control permanente sobre explosivos y accesorios en cada etapa del proceso. Este riesgo comprende operaciones con explosivos que pueden generar eventos fatales y/o daños materiales tales como: •Iniciación no controlada y/o espontánea de explosivos o agentes de fragmentación •Iniciación no controlada y/o espontánea de tiros quedados o rezagados •Proyección no controlada de fragmentos de roca (Fly Rocks)En el caso de las sustancias intermedias no aisladas de los procesos, deberan cumplir con los controles CCP1 y CCP2, de tal manera de asegurar el que las actividades con estas sustancias cumplan con la señalización y otros controles básicos, para evitar desviaciones en su manipulación.
B11: Exclusión | C11: Para el carguío automatizado, serán las Divisiones o Proyectos, quienes deberán elaborar un análisis de riesgo, en el cual definan los controles críticos aplicables de este Riesgo de Fatalidad.
B13: RIESGO FATALIDAD | C13: CONTROL CRÍTICO | D13: NOMBRE DEL CONTROL CRÍTICO | E13: OBJETIVO | F13: REQUISITO | G13: MONITOREO | H13: EVIDENCIA | I13: CUMPLIMIENTO | J13: OBSERVACIONES | K13: FECHA IMPLEMENTACIÓN | L13: PLAN MITIGADOR
B14: RF08 | C14: CCP1 | D14: PERSONAL ACREDITADO EN TRONADURA Y MANEJO DE EXPLOSIVOS | E14: Garantizar que todo el personal que diseña, planifica, manipula, transporta y ejecuta maniobras de tronadura posea las competencias, acreditaciones y autorizaciones vigentes requeridas por la ley y la organización, para asegurar una ejecución experta y sin errores del proceso. | F14: Licencia de Manipulador de Explosivos Vigente | G14: Mensual | H14: Solicitar y verificar en terreno que todo el personal que manipula explosivos (incluyendo al conductor del vehículo del transporte de explosivos), porte su licencia de "Manipulador de Explosivos" vigente, emitida por la autoridad fiscalizadora. | I14: 1
F15: Acreditación de Programador Calculista | G15: Cada vez | H15: Solicitar la licencia vigente del "Programador Calculista" responsable del diseño de la tronadura, emitida por la autoridad competente (SERNAGEOMIN) | I15: N/A
F16: Programa de Formación y Competencias | G16: Anual | H16: Solicitar el programa de formación que define las competencias para cada rol: Operador, Mantenedor y supervisor. | I16: N/A
F17: Capacitación Específica del Fabricante | G17: Anual | H17: Para tecnologías específicas (ej. tronadura electrónica), solicitar los certificados de aprobación de capacitación emitidos por el fabricante del sistema al personal que lo opera. | I17: N/A
F18: Entrenamiento Práctico en Terreno | G18: Cada vez | H18: Verificar los registros de entrenamiento práctico en terreno, guiado por un instructor, para todo el personal que se inicia en funciones de manejo de explosivos. | I18: N/A
B19: RF08 | C19: CCP2 | D19: TRONADURAS EJECUTADAS SEGÚN DISEÑO APROBADO | E19: Garantizar que cada tronadura seejecutesiguiendoestrictamente los parámetros definidos en un diseño de ingeniería (conceptual, modelo de bloques), el cual debe estar basado en información geológica, geotécnica y operacional actualizada, y cuyo cumplimiento en terreno sea verificado mediante un riguroso proceso de aseguramiento de calidad (QA/QC). | F19: Diseño Basado en Modelo de Bloques e Información de Terreno | G19: Cada Vez | H19: Solicitar el diseño de tronadura y verificar que sus parámetros (diseño conceptual, malla) se basan en información geológica, geotécnica y operacional actualizada. | I19: N/A
F20: Parámetros de Diseño Definidos y Aprobados | G20: Cada Vez | H20: Verificar que el plan de tronadura esté documentado y aprobado. Debe establecer: malla de perforación, tipo de explosivo, secuencia de carga (fondo/columna), longitud del taco y secuencia de salida. | I20: N/A
F21: Verificación de la Perforación (QA/QC | G21: Cada Vez | H21: Solicitar los registros del aseguramiento de calidad (QA/QC) de la perforación, que validen la posición,nprofundidad y diámetro de los pozos, asegurando su conformidad con el diseño. | I21: N/A
F22: Verificación del Carguío y Amarre (QA/QC) | G22: Cada Vez | H22: Solicitar los registros del QA/QC del carguío, que demuestren la verificación en terreno del tipo de iniciador, la cantidad y tipo de explosivo, y la correcta ejecución del amarre según la secuencia de salida del diseño. | I22: N/A
F23: Gestión de Cambio para Desviaciones | G23: Cada Vez | H23: En caso de cualquier desviación del diseño original, solicitar la evidencia documental de la gestión del cambio, la cual debe estar re-evaluada y aprobada por el especialista responsable (programador calculista). | I23: N/A
F24: Disponibilidad del Diseño Final en Terreno | G24: Cada Vez | H24: Verificar que el equipo de trabajo en terreno cuenta con una copia (física o digital) de la última versión aprobada del diseño de tronadura para su consulta permanente durante la ejecución | I24: N/A
B25: RF08 | C25: CCP3 | D25: DISEÑO Y EJECUCIÓN DE TRONADURA CONFORME A CONDICIONES REALES | E25: Garantizar que cada tronadura se planifique mediante un diseño técnico basado en información geológica, geotécnica y operacional actualizada, que se ajuste a las condiciones reales del terreno del día, y se ejecute siguiendo estrictamente los parámetros de diseño aprobados: carga, amarre y secuencia para ejecutar una fragmentación controlada y segura. | F25: Diseño Basado en Información Actualizada | G25: Cada vez | H25: Solicitar el diseño de tronadura y verificar que se basa en información geológica, geotécnica y operacional actualizada (modelo de bloques,mapeo de frente, etc.). | I25: N/A
F26: Protocolo de Regulación de Desviaciones | G26: Cada vez | H26: Solicitar el procedimiento que define cómo actuar ante desviaciones en la perforación, estableciendo los criterios para ajustar el diseño (ej. reducircargas, cambiar secuencia) | I26: N/A
F27: Ajuste del Diseño a la Condición del Día | G27: Cada vez | H27: Verificar en el plan de tronadura o en undocumento anexo que se consideraron las condiciones reales del terreno del día (evaluación geotécnica, presencia de agua, etc.) para justar el diseño final. | I27: N/A
F28: Verificación en Terreno (QA/QC de Tronadura) | G28: Cada vez | H28: Solicitar los registros del QA/QC de la tronadura, que deben incluir la verificación en terreno de la correcta ejecución del plan de carguío y la secuencia de amarre según el diseño ajustado. | I28: N/A
F29: Control de Parámetros de Diseño (Carga y Taco | G29: Mensual | H29: Realizar inspecciones aleatorias en terreno para verificar que la cantidad de explosivo y la longitud del taco en los pozos corresponden a lo especificado en el diseño final | I29: N/A
F30: Gestión de Cambio para Modificaciones | G30: Cada vez | H30: Solicitar evidencia documental de la gestión del cambio, aprobada por el programador calculista, para cualquier modificación significativa no contemplada en el protocolo de ajuste. | I30: N/A
B31: RF08 | C31: CCP4 | D31: AISLACIÓN FÍSICA Y EVACUACIÓN SEGURA DE LA ZONA DE TRONADURA | E31: Garantizar que el área de influencia definida para una tronadura (Halo) esté físicamente aislada de manera efectiva y completamente evacuada por todo el personal, mediante un sistema de verificación ("Carta de Loros") que confirme la ausencia total de personas y equipos antes de autorizar la detonación. | F31: "Carta de Loro" Implementada y Aprobada | G31: Cada vez | H31: Solicitar la "Carta de Loro" del día, firmada por los responsables, la cual debe incluir el radio de evacuación (halo), ubicación de cada "loro", responsables y horarios. | I31: N/A
F32: Delimitación Física Efectiva del Área | G32: Cada vez | H32: Verificar en terreno que cada acceso al "halo de evacuación" esté bloqueado físicamente por barreras duras o vigías ("loros humanos") capacitados y con comunicación. | I32: N/A
F33: Control de Accesos Verificado | G33: Cada vez | H33: Solicitar el registro de comunicaciones donde el jefe de tronadura confirma positivamente con cada "loro" que su posición está asegurada antes de autorizar la detonación | I33: N/A
F34: Protocolos de Evacuación Validados | G34: Anual | H34: Verificar los registros de simulacros de evacuación para confirmar que el personal conoce las rutas de escape y los puntos de encuentro, y que estos son ensayados. | I34: N/A
F35: Registro de Evacuación Completa | G35: Cada vez | H35: Solicitar el registro (check list o protocolo radial) donde cada supervisor de área confirma que todo su personal ha sido contabilizado y se encuentra en un punto seguro. | I35: N/A
F36: Control de Reingreso Autorizado | G36: Cada vez | H36: Verificar que existe un protocolo claro para autorizar el re-ingreso al área, el cual solo puede ser instruido por el jefe de tronadura una vez que la zona ha sido declarada segura. | I36: N/A
B37: RF08 | C37: CCP5 | D37: VEHÍCULOS ACREDITADOS Y SEGUROS PARA TRANSPORTE Y FABRICACIÓN DE EXPLOSIVOS | E37: Garantizar que todo vehículo utilizado para transportar o fabricar explosivos cumpla permanentemente con las acreditaciones legales, las especificaciones del fabricante (calibración, sistema mata chispas) y los planes de mantenimiento, para prevenir fallas que puedan causar una iniciación accidental. | F37: Acreditación Vigente del Vehículo | G37: Anual | H37: Solicitar las resoluciones de la autoridad fiscalizadora para cada vehículo y verificar que la acreditación para transporte de explosivos esté vigente | I37: N/A
F38: Inspección Pre-Uso (Check list de control diario) | G38: Diario | H38: Solicitar las listas de chequeo pre-uso firmadas por el operador. Verificar que la inspección de sistemas críticos (frenos, sistema mata chispas, ESD) se realiza al inicio de cada turno. | I38: N/A
F39: Plan de Mantenimiento Específico Ejecutado | G39: Trimestral | H39: Solicitar el plan de mantenimiento de la flota y las órdenes de trabajo. Verificar el cumplimiento de las pautas para sistemas eléctricos, mecánicos y de incendio específicos | I39: N/A
F40: Condición de Operación Conforme a Fabricante | G40: Mensual | H40: Verificar que el vehículo opera de acuerdo a las especificaciones del fabricante, sin modificaciones no autorizadas, y con sus sistemas (ej. Retardo dinámico) funcionando correctamente. | I40: N/A
F41: Programa de Calibración de Componentes | G41: Semestral | H41: Solicitar el programa y los certificados de calibración de los componentes que lo requieran (ej. sistemas de dosificación en camiones fábrica). | I41: N/A
F42: Competencias del Personal de Mantenimiento | G42: Anual | H42: Solicitar los registros de capacitación del personal de mantenimiento, que demuestren su competencia para intervenir estos vehículos, según lo indicado por el fabricante | I42: N/A
B43: RF08 | C43: CCM1 | D43: CAPACIDAD DE RESPUESTA ANTE EMERGENCIA | E43: Garantizar una respuesta de emergencia inmediata, coordinada y eficaz ante un evento no deseado de tronadura (explosión no controlada, atropello, flyrock), asegurando la activación de planes, la disponibilidad de brigadas entrenadas y equipamiento especializado para rescatar, estabilizar y atender a los lesionados. | F43: Plan de Emergencia Específico y Difundido | G43: Anual | H43: Solicitar el plan de emergencias que incluya un protocolo específico para incidentes de tronadura (explosión, flyrock, TQ), definiendo roles y flujogramas de comunicación. | I43: N/A
F44: Brigada Entrenada en Rescate Post Explosión | G44: Semestral | H44: Verificar los registros de entrenamiento de la brigada, que deben demostrar capacitación en rescate en ambientes post-explosión (manejo de trauma, ingreso a zonas con gases, estabilización de estructuras). | I44: N/A
F45: Equipamiento de Rescate y Médico Disponible | G45: Mensual | H45: Inspeccionar en terreno el equipamiento de la brigada y del policlínico, verificando la disponibilidad y operatividad de equipos para trauma por explosión y monitoreo de gases. | I45: N/A
F46: Vehículos de Emergencia Operativos | G46: Trimestral | H46: Solicitar el plan de mantenimiento de la ambulancia y vehículos de rescate, y verificar su cumplimiento. Confirmar que los vehículos tienen la certificación para operar en la faena. | I46: N/A
F47: Simulacros Específicos y Medidos | G47: Anual | H47: Solicitar el informe del último simulacro de accidente por tronadura, el cual debe incluir la evaluación de los tiempos de respuesta y la eficacia de las maniobras de rescate | I47: N/A
F48: Protocolo de Disipación de Gases | G48: Anual | H48: Verificar que el plan de emergencia incluye un protocolo específico para la ventilación y disipación de gases post-tronadura, como requisito previo para el ingreso seguro de los equipos de rescate | I48: N/A
B50: RIESGO FATALIDAD | C50: CONTROL | D50: NOMBRE DEL CONTROL | E50: REQUISITO | G50: EVIDENCIA | I50: CUMPLIMIENTO | J50: OBSERVACIONES | K50: FECHA IMPLEMENTACIÓN | L50: PLAN MITIGADOR
B51: RF08 | C51: CP1 | D51: VERIFICACIÓN DE CONDICIONES METEOROLÓGICAS | E51: Se deben establecer y aplicar sistemas de detección y respuesta ante condiciones meteorológicas adversas, suspendiendo los procesos de carguío y tronadura para evitar incidentes causados por tormentas eléctricas, nevazones, ventiscas o vientos fuertes | G51: a. Se debe contar con un sistema de detección de tormentas eléctricas, nevazones, ventiscas y vientos que puedan generar una suspensión automática de los procesos asociados a carguío de explosivos y tronadura. | I51: N/A
G52: b. La planificación del proceso de tronadura debe considerar una gestión de alerta meteorológica y una respuesta definida ante estos eventos, ya que el carguío durante tormentas eléctricas es una causa de incidentes. | I52: N/A
G53: c. Frente a un corte de energía eléctrica que afecte el sistema de ventilación principal en minería subterránea, se debe suspender la tronadura. | I53: N/A
B54: RF08 | C54: CP2 | D54: SEÑALIZACIÓN Y DEMARCACIÓN TEMPORAL DEL ÁREA | E54: Se debe confinar, aislar y señalizar el área de trabajo donde se realizará la tarea con materiales explosivos, utilizando barreras físicas, letreros y personal de vigilancia ("loros vivos") para impedir el ingreso de personal o vehículos no autorizado | G54: a. Los accesos a las áreas comprometidas deben ser aisladas mediante personas “loros vivos”; en casos justificados y reglamentados se puede utilizar tapados, barreras y letreros prohibitivos | I54: N/A
G55: b. El supervisor es responsable de realizar la segregación del área restringida según corresponda, instalando la señalética y los "loros vivos" en las ubicaciones definidas en el plano (layout) de la "carta de loro". | I55: N/A
G56: c. Se deben utilizar elementos de información como pizarras o letreros para comunicar la ejecución de la tronadura, y su ubicación debe estar validada en la "carta de loro". | I56: N/A
B57: RF08 | C57: CP3 | D57: COMUNICACIÓN BIDIRECCIONAL (CARTA DE LORO) | E57: Se debe asegurar la correcta elaboración, difusión y ejecución de la "carta de loro" para garantizar una comunicación efectiva y la evacuación completa del personal antes de autorizar la tronadura. | G57: a. Previo a las tronaduras, se debe emitir una “carta de loros” que incluya todas las tronaduras del área, la cual debe ser aprobada por el responsable del área. | I57: N/A
G58: b. La "carta de loro" debe documentar el diagrama de comunicación, los protocolos de autorización de inicio, el listado de números de contacto o frecuencias radiales y la ubicación de los elementos de segregación. | I58: N/A
G59: El personal a cargo del proceso de tronadura debe ser instruido respecto a la "carta de loro", mientras que el personal no directamente relacionado debe conocer el proceso de evacuación y las áreas seguras. | I59: N/A
B60: RF08 | C60: CP4 | D60: CHEQUEO PRE-OPERACIONAL DE ACCESORIOS | E60: Se deben verificar todos los componentes del proceso de tronadura conforme al diseño técnico para evitar errores en la conexión o uso de materiales inadecuados que puedan llevar a una iniciación no controlada. | G60: a. El diseño técnico de la tronadura debe incluir la descripción del carguío de cada pozo o barreno, especificando el tipo de iniciadores, el tipo de explosivo, y la secuencia de salida (retardos). | I60: N/A
G61: b. Se debe contar con una guía de recepción de los explosivos a utilizar, así como una guía de devolución para los sobrantes, asegurando el control de todo el material. | I61: N/A
G62: c. Un error en el amarre o conexión para la secuencia de salida es una causa directa de eventos no deseados, por lo que su correcta ejecución y verificación es fundamental antes de la detonación. | I62: N/A
B63: RF08 | C63: CM1 | D63: POLVORINES CON PARAPETOS Y RESGUARDOS | E63: Se deben infraestructuras diseñar de e implementaralmacenamiento deexplosivos que cumplan con la normativavigente y los estándares de seguridad, para prevenir aumentos de temperatura odetonaciones accidentales. | G63: a. Todas las instalaciones utilizadas para el almacenamiento de explosivos y materias primas deben contar con las autorizaciones de las autoridades fiscalizadoras. | I63: N/A
G64: b. Los almacenes de explosivos deben contar con un sistema de control y vigilancia permanente. | I64: N/A
G65: c. Todas las unidades de almacenamiento de polvorines, accesorios y sustancias fragmentadoras deben contar con una memoria de cálculo (diseño) aprobada por la autoridad competente. | I65: N/A
B66: RF08 | C66: CM2 | D66: LIMPIEZA PROGRAMADA DE BERMAS COLMATADAS | E66: Se deben ejecutar las descargas y limpiezas de las bermas de seguridad de manera controlada, considerando siempre las condiciones de estabilidad del terreno, para asegurar que mantengan su capacidad de contención y no generen riesgos de deslizamientos. | G66: a. Las operaciones de descarga y limpieza de bermas deben ser ejecutadas únicamente considerando las condiciones de estabilidad de la zona afectada por la tronadura. | I66: N/A
G67: b. Todas las actividades de limpieza de bermas colmatadas deben ser obligatoriamente visadas (aprobadas) por el área de Geotecnia antes de su ejecución. | I67: N/A
G68: c. El área de Geotecnia es responsable de evaluar y definir el grado de inestabilidad de una zona amagada por una tronadura, y el ingreso para realizar tareas como la limpieza de bermas queda supeditado a dicha evaluación de riesgo | I68: N/A
B69: RF08 | C69: CM3 | D69: HUMECTACIÓN DEL MATERIAL FRAGMENTADO | E69: Se debe aplicar la humectación (riego) sobre el área que contenga una carga no iniciada, como un fragmentador de roca (plasma), con el objetivo de controlar las condiciones del entorno y asegurar el área antes de realizar cualquier maniobra de intervención sobre dicha carga. | G69: a. El supervisor a cargo debe solicitar el apoyo de un camión aljibe para humectar el área específica que contiene la carga sin iniciar. | I69: N/A
G70: b. Antes de intervenir una carga no iniciada, y después de la humectación, se deben verificar las condiciones del pozo y las vías de acceso a la carga para garantizar que la intervención sea segura. | I70: N/A
G71: c. La humectación del material es una medida de control que se debe aplicar específicamente en el escenario de detectar una carga no iniciada, para mitigar riesgos antes de la intervención. | I71: N/A

Sheet RF09
B2: GERENCIA DE SEGURIDAD Y SALUD OCUPACIONAL - CHUQUICAMATA
B4: LISTADO DE AUTODIAGNÓSTICO RIESGO DE FATALIDAD N°09: PARTES MÓVILES
B6: ELEMENTOS DEL CONTROL | I6: CUMPLIMIENTO GENERAL
I7: =AVERAGEIF(I14:I42,"<>N/A") -> #DIV/0!
B10: Alcance | C10: Actividades de operación, mantenimiento, construcción y puesta en marcha donde se utilicen máquinas y equipos con sistemas con partes móviles como por ejemplo: rodillos, despegadora de cátodos, correas transportadoras, tambores de aglomeración, equipos con ejes expuestos, conjunto de poleas, sistemas de transmisión por engranajes, sistemas de transmisión por cadenas, sistemas motrices de equipos, entre otros.
B11: Exclusión | C11: Se excluyen los trabajos con: •Herramientas manuales portátiles. •Herramientas eléctricas fijas.
B13: RIESGO FATALIDAD | C13: CONTROL CRÍTICO | D13: NOMBRE DEL CONTROL CRÍTICO | E13: OBJETIVO | F13: REQUISITO | G13: MONITOREO | H13: EVIDENCIA | I13: CUMPLIMIENTO | J13: OBSERVACIONES | K13: FECHA IMPLEMENTACIÓN | L13: PLAN MITIGADOR
B14: RF09 | C14: CCP1 | D14: GUARDAS Y PROTECCIONES EN PARTES MÓVILES | E14: Impedir el contacto con partes móviles, asegurando que todos los equipos y maquinarias cuenten con guardas y protecciones fijas o móviles, diseñadas, instaladas y mantenidas para interponer una barrera física efectiva entre las personas y el peligro. | F14: Docuento que defina el Diseño de Guardas y Protecciones. | G14: Anual | H14: Solicitar el documento que defina el diseño y verificar que las guardas en terreno cumplen con los requisitos (materialidad, distancia de seguridad) | I14: N/A
F15: Catastro de Puntos de Atrapamiento y Protecciones | G15: Anual | H15: Solicitar el inventario y mapa o plano actualizado de los equipos que identifican los puntos de atrapamiento, las guardas asociadas y su ubicación dentro del área de trabajo. | I15: N/A
F16: Inspección de Pre-Uso por Operador | G16: Diario | H16: Solicitar los checklists de pre-uso firmados por el operador, donde se verifique la integridad y correcta instalación de las guardas | I16: N/A
F17: Sistemas de Enclavamiento Operativos. | G17: Trimestral | H17: Solicitar en los casos que corresponda, los registros de las pruebas funcionales de los sistemas de enclavamiento en guardas móviles. | I17: N/A
F18: Programa de Mantenimiento de Protecciones. | G18: Semestral | H18: Solicitar la pauta y los registros de mantenimiento preventivo de las guardas y sus sistemas de fijación. | I18: N/A
F19: Prohibición de Elementos Sueltos | G19: Semanal | H19: Verificar mediante observación en terreno que el personal cumple con la prohibición de uso de ropa suelta, joyas, Pelo largo suelto, etc | I19: N/A
F20: Protocolo de Reposición de Guardas Post-Mantenimiento. | G20: Por evento | H20: Solicitar el procedimiento de mantenimiento y verificar que incluye el paso obligatorio de reposición de guardas y la liberación formal del equipo. | I20: N/A
B21: RF09 | C21: CCP2 | D21: AISLACIÓN, BLOQUEO Y VERIFICACIÓN DE ENERGÍA CERO | E21: Garantizar que toda energía motriz (eléctrica, hidráulica, neumática) y residual (inercia, gravedad) sea completamente aislada y llevada a un estado de energía cero antes de que el personal intervenga o acceda a las partes móviles de un equipo | F21: Procedimiento deb Aislación y Bloqueo Vigente. | G21: Anual | H21: Solicitar el procedimiento de aislación y bloqueo vigente, con sus respectivas instruciones al personal | I21: N/A
F22: Identificación de Todas las Fuentes de Energía | G22: Anual | H22: Solicitar la matriz o diagrama de bloqueo del equipo, verificando que identifica todas las fuentes de energía (eléctrica, neumática, etc.) | I22: N/A
F23: Bloqueo Personal con Candado y Tarjeta. | G23: Por evento | H23: Verificar en terreno que cada trabajador que interviene el sistema ha instalado su propio candado y tarjeta personal en el punto de bloqueo. | I23: N/A
F24: Verificación de Energía Cero y Prueba de Arranque | G24: Por evento | H24: Solicitar el documento donde se registre la ejecución de la verificación de energía cero y la prueba de arranque | I24: N/A
F25: Control de Energías Residuales | G25: Por evento | H25: Verificar en el procedimiento y en terreno el uso de mecanismos para controlar energías residuales (trabas mecánicas, cuñas, tiempo de espera) | I25: N/A
F26: Personal capacitado en Aislación y Bloqueo. | G26: Anual | H26: Registros de capacitación del personal que participa en el proceso de aislación, bloqueo y verificación de energía cero. | I26: N/A
B27: RF09 | C27: CCM 1 | D27: SISTEMA DE PARADA DE EMERGENCIA | E27: Detener de forma inmediata el movimiento de un equipo o maquinaria en caso de una emergencia por atrapamiento, mediante dispositivos de parada accesibles, operativos y de accionamiento manual que requieran un reseteo intencionado para reanudar la marcha. | F27: Catastro y Diseño de Paradas de Emergencia. | G27: Anual | H27: Solicitar el plano o inventario que identifica la ubicación y tipo de todas las paradas de emergencia de un sistema | I27: N/A
F28: Prueba Funcionales Periódicas. | G28: Trimestral | H28: Solicitar los registros del programa de mantenimiento que incluyan las pruebas funcionales de los sistemas de parada de emergencia. | I28: N/A
F29: Inspección de Estado y Accesibilidad | G29: Mensual | H29: Solicitar los registros de inspección que verifiquen el buen estado, la señalización y la accesibilidad de los dispositivos, incluyendo la confirmación operativa en las inspecciones de preuso o listas diarias de seguridad | I29: N/A
F30: Requerimiento de Reset Manual | G30: Anual | H30: Verificar en los manuales de diseño o mediante pruebas que, tras una parada de emergencia, el equipo solo pueda reiniciarse mediante una acción manual controlada (por ejemplo, presionar un botón de reinicio autorizado), evitando el arranque automático. | I30: N/A
F31: Activación de paradas de emergencias | G31: Semestral | H31: Registros de capacitación. Además, mediante entrevistas en terreno, asegurar quque el personal conoce la ubicación y el modo de activación de las paradas de emergencia. | I31: N/A
B32: RF09 | C32: CCM2 | D32: CAPACIDAD DE RESPUESTA ANTE EMERGENCIA | E32: Garantizar una respuesta sistémica, inmediata y eficaz ante un accidente por atrapamiento, integrando el protocolo de rescate, la primera respuesta y la atención médica especializada, para liberar a la persona atrapada y minimizar la severidad de las lesiones. | F32: Plan de Emergencia para Atrapamiento. | G32: Anual | H32: Solicitar el plan de emergencia y verificar que incluye un protocolo específico para rescate en atrapamiento con partes móviles. | I32: N/A
F33: Brigada Entrenada en Rescate Técnico. | G33: Semestral | H33: Solicitar los registros de entrenamiento de la brigada en técnicas de rescate con herramientas de liberación. | I33: N/A
F34: Equipamiento de Rescate Operativo | G34: Mensual | H34: Solicitar los registros de inspección mensual de losnequipos de rescate de la brigada (herramientas hidráulicas, equipos de corte, etc.). | I34: N/A
F35: Sistemas deComunicación de EmergenciaFuncionales | G35: Trimestral | H35: Solicitar registros de pruebas funcionales de los sistemas de alarma y de los canales de comunicación de emergencia | I35: N/A
F36: Simulacros deRescate por Atrapamiento. | G36: Anual | H36: Solicitar el informe del último simulacro de atrapamiento, verificando tiempos de respuesta, técnicas de rescate y planes de acción. | I36: N/A
F37: Personal Capacitado en Primera Respuesta. | G37: Anual | H37: Solicitar registros de capacitación en primeros auxilios para el personal de operaciones y supervisores. | I37: N/A
B39: RIESGO FATALIDAD | C39: CONTROL | D39: NOMBRE DEL CONTROL | E39: REQUISITO | G39: EVIDENCIA | I39: CUMPLIMIENTO | J39: OBSERVACIONES | K39: FECHA IMPLEMENTACIÓN | L39: PLAN MITIGADOR
B40: RF09 | C40: CP1 | D40: SEÑALÉTICA FIJA DE ADVERTENCIA EN ACCESOS Y EQUIPOS | E40: Se debe instalar señalética de advertencia fija y visible en todos los equipos y en los accesos a áreas que contengan partes móviles, para alertar al personal sobre el riesgo de atrapamiento. | G40: a. El supervisor del área es responsable de asegurar que se instale señalización explícita con pictogramas y texto de "Peligro: Riesgo de Atrapamiento" o "No Operar sin Guardas" directamente sobre los equipos o en sus inmediaciones. | I40: N/A
G41: b. El personal de mantenimiento que retire una guarda o protección para realizar un trabajo debe instalar una tarjeta de advertencia temporal que indique el peligro y la prohibición de operar el equipo. | I41: N/A
G42: c. La señalética debe ser de material resistente a las condiciones del entorno y su estado debe ser verificado en las inspecciones de seguridad del área para asegurar su legibilidad permanente | I42: N/A
B43: RF09 | C43: CP2 | D43: ALARMAS VISUALES Y SONORAS DE PRE-ARRANQUE | E43: Todos los equipos fijos con partes móviles que noBestén completamente encapsulados y cuyo arranque no sea visible desde el punto de accionamiento, deben contar con un sistema de alarma audiovisual de pre-arranque. | G43: a. Antes del inicio del movimiento, el sistemaNdebe activar automáticamente una alarma sonora (bocina o sirena) y una alarma visual (baliza estroboscópica) durante un tiempopredefinido para advertir al personal cercano sobre la puesta en marcha inminente. | I43: N/A
G44: b. El personal de mantenimiento eléctrico e instrumentación debe verificar la operatividad de estas alarmas como parte del programa de mantenimiento preventivo del equipo,realizando pruebas funcionales documentadas. | I44: N/A
G45: c. Todo el personal debe ser instruido para reconocer estas alarmas y evacuar inmediatamente la zona de riesgo o alejarse auna distancia segura al momento de su activación | I45: N/A
B46: RF09 | C46: CP3 | D46: DEMARCACIÓN DE ZONAS DE RIESGO DE ATRAPAMIENTO | E46: Se deben demarcar en el piso las zonas de seguridad alrededor de equipos con partes m óviles expuestas para indicar visualmente elárea de riesgo y la distancia mínima a la que se puede aproximar el personal | G46: a. El supervisor del área debe asegurar que se instale y mantenga una demarcación con pintura de alta visibilidad (generalmente amarilla o roja) en el piso, definiendo un perímetro de seguridad alrededor de los puntos de atrapamiento. | I46: N/A
G47: b. Todo el personal que transite por el área debe respetar la demarcación, prohibiéndose cruzar o permanecer dentro del área de riesgo mientras el equipo se encuentre en operación. | I47: N/A
G48: c. Todo el personal debe ser instruido parareconocer estas alarmas y evacuar inmediatamente la zona de riesgo o alejarse auna distancia segura al momento de su Vactivación. | I48: N/A

Sheet RF10
B2: GERENCIA DE SEGURIDAD Y SALUD OCUPACIONAL - CHUQUICAMATA
B4: LISTADO DE AUTODIAGNÓSTICO RIESGO DE FATALIDAD N° 10: VEHÍCULOS
B6: ELEMENTOS DEL CONTROL | I6: CUMPLIMIENTO GENERAL
I7: =AVERAGEIF(I14:I39,"<>N/A") -> #DIV/0!
B10: Alcance | C10: Este riesgo de fatalidad aplica a vehículos que transitan a través de carreteras, tales como: • Camionetas. • Vehículos de transporte de personal como: • Buses • Mini buses • Vehículos de transporte de carga.
B11: Exclusión | C11: Este evento considera como exclusión los siguientes escenarios: • Operación de equipos mineros • Equipos autónomos • Interacciones de vehículos , equipos móviles con peatones e el sitio, incluido el subterráneo
B13: RIESGO FATALIDAD | C13: CONTROL CRÍTICO | D13: NOMBRE DEL CONTROL CRÍTICO | E13: OBJETIVO | F13: REQUISITO | G13: MONITOREO | H13: EVIDENCIA | I13: CUMPLIMIENTO | J13: OBSERVACIONES | K13: FECHA IMPLEMENTACIÓN | L13: PLAN MITIGADOR
B14: RF10 | C14: CCP1 | D14: CONDUCTOR ACREDITADO Y APTO FÍSICA Y PSICOLÓGICAMENTE | E14: Garantizar que toda persona que conduzca un vehículo cuente con las competencias técnicas, una autorización interna vigente para el tipo de vehículo específico y una condición física y psicológica compatible con la tarea de conducir, asegurando así un estado de alerta y una conducta segura en todo momento. | F14: Proceso de Acreditación de Conductores | G14: Anual | H14: Documento que regula los requisitos para la obtención de licencia interna. -Para camionetas: Licencia municipal y curso de manejo a la defensiva. -Para vehículos de transporte de personas y de cargas: Licencia municipal, curso de manejo a la defensiva, evaluación teorico y práctico sobre operación y conocimiento de los sistemas del vehículo en marca y modelo, realizada por organismo certificador validado por Chile Valora o fabricante/representantes de la marca. | I14: N/A
F15: Programa de Salud Compatible | G15: Trimestral | H15: Registros de observaciones de conducta realizadas, análisis de brechas y planes de acción para corregir conductas riesgosas. | I15: N/A
F16: Sistema de Gestión de Conductas | G16: Semestral | H16: Registros de observaciones de conducta realizadas, análisis de brechas y planes de acción para corregir conductas riesgosas. | I16: N/A
F17: Programa Alcohol y Drogas | G17: Anual | H17: Procedimiento documentado que regula la gestión y control de alcohol y drogas. | I17: N/A
F18: Conducción en zonas de alto riesgo | G18: Semestral | H18: En zonas de alto riesgo se deberá realizar una capacitación teórica y práctica para conductores (curso 4x4, alta montaña e instrucción en operación invierno) que debe contener las medidas específicas de control para la formación segura de los conductores. | I18: N/A
B19: RF 10 | C19: CCP2 | D19: INTEGRIDAD MECÁNICA Y SISTEMAS ACTIVOS DEL VEHÍCULO | E19: Asegurar que todos los vehículos que transitan en faena cumplan con las especificaciones técnicas definidas para el entorno minero y que sus sistemas de seguridad activos (frenos, dirección, neumáticos) sean mantenidos e inspeccionados sistemáticamente para garantizar su correcto funcionamiento en todo momento. | F19: Especificaciones técnicas del Vehículo | G19: Anual | H19: Disponer del Manual del Fabricante con las especificaciones técnicas de los vehículos. | I19: N/A
F20: Programa de Mantenimiento Preventivo | G20: Semestral | H20: Registros de cumplimiento del programa de mantenimiento (software, pautas) para sistemas críticos (frenos, neumáticos, dirección, luces). | I20: N/A
F21: Inspección Pre-Uso | G21: Mensual | H21: Verificación en terreno y registros de listas de chequeo pre-operacionales completadas por los conductores. | I21: N/A
F22: Certificación de Componentes Críticos | G22: Anual | H22: Certificados de mantenimiento y operatividad de los sistemas de seguridad, emitidos por personal o taller competente. | I22: N/A
F23: Gestión de Fallas Reportadas | G23: Semestral | H23: Verificar la existencia de un sistema de reporte y seguimiento para las fallas detectadas en las inspecciones pre-uso (órdenes de trabajo). | I23: N/A
B24: RF 10 | C24: CCP3 | D24: SISTEMA INTEGRAL DE ASISTENCIA Y MONITOREO A LA CONDUCCIÓN | E24: Garantizar que la conducción de vehículos sea monitoreada y regulada permanentemente a través de sistemas tecnológicos y reglas operacionales claras, gestionando activamente la velocidad, la fatiga del conductor y las condiciones del entorno para prevenir la pérdida de control. | F24: Control de Velocidad (GPS) | G24: Mensual | H24: Reportes de la plataforma de control de conducción que evidencien el monitoreo de excesos de velocidad y su gestión. | I24: N/A
F25: Gestión de Fatiga (Tecnología) | G25: Semestral | H25: Registros de operatividad y mantenimiento de los dispositivos de detección de fatiga, según matriz de recomendación del estándar técnico (SIGO-ET-010). | I25: N/A
F26: Alerta de proximidad (Tecnología) | G26: Semestral | H26: Registros de operatividad y mantenimiento de los dispositivos de proximidad en vehículos, de acuerdo a lo establecido en (SIGO-ET-012). | I26: N/A
F27: Protocolos por Clima Adverso | G27: Semestral | H27: Existencia de normas de conducción específicas para condiciones de lluvia, nieve, neblina, etc., y evidencia de su gestión. | I27: N/A
F28: Disponibilidad de Sistemas | G28: Semestral | H28: Verificar en terreno que los sistemas de apoyo a la conducción (GPS, proximidad, cámaras, sensores) están instalados, visibles y operativos. | I28: N/A
B29: RF 10 | C29: CCP4 | D29: INFRAESTRUCTURA VIAL CONFORME A DISEÑO | E29: Asegurar que todas las rutas y caminos utilizados en la faena sean diseñados, construidos y mantenidos de acuerdo a estándares definidos, garantizando que elementos como bermas, pretiles, señalización y lechos de frenado estén siempre operativos para prevenir la pérdida de control o mitigar sus consecuencias. | F29: Diseño de Vías y Rutas | G29: Anual | H29: Documento que define los criterios técnicos (referenciado al Manual de Carreteras, Manual de Diseño Geométrico de Carreteras del MOP y el “Reglamento de Seguridad Minera) para el diseño de vías, pretiles y lechos de frenado. | I29: N/A
F30: Plan de Tránsito y Rutas | G30: Trimestral | H30: Documento que regula la gestión de tránsito y rutas, actualizado y difundido. Verificar comunicación de cambios diarios (layout, señalización, otros). | I30: N/A
F31: Programa de Mantenimiento de Rutas | G31: Trimestral | H31: Registros de cumplimiento del programa de mantenimiento de rutas, incluyendo señalización, carpeta de rodado y drenajes. | I31: N/A
F32: Integridad de Pretiles y Bermas | G32: Mensual | H32: Informes de inspección en terreno que verifiquen que la altura y construcción de los pretiles/bermas cumple con el diseño. | I32: N/A
F33: Operatividad de Lechos de Frenado | G33: Trimestral | H33: Registros de mantenimiento que aseguren las condiciones de diseño de los lechos de frenado (señalización, rugosidad de la grava, inclinación, medición de profundidad (>30 cm) y limpieza de material fino u otros elementos existentes en el lecho de frenado). | I33: N/A
F34: Señalización y Segregación | G34: Mensual | H34: Verificación en terreno de que la señalización y segregación de vías está instalada, visible y es coherente con el plan de tránsito. | I34: N/A
B35: RF 10 | C35: CCM1 | D35: CAPACIDAD DE RESPUESTA ANTE EMERGENCIA | E35: Garantizar la existencia de un plan de respuesta a emergencias robusto y ensayado, con personal brigadista capacitado, equipamiento de rescate y extricación vehicular operativo, y una coordinación efectiva con el personal médico para proveer atención oportuna y especializada a las personas lesionadas tras un accidente vehicular. | F35: Plan de Respuesta a Emergencias | G35: Anual | H35: Documento del plan de emergencias que considere específicamente accidentes vehiculares, con roles, recursos y protocolos definidos. | I35: N/A
F36: Entrenamiento de Brigadistas | G36: Semestral | H36: Registros del programa de entrenamiento y capacitación de la brigada de rescate (formación inicial, refuerzo, horas prácticas). | I36: N/A
F37: Equipamiento de Rescate y Extricación | G37: Semestral | H37: Registros de cumplimiento del programa de mantenimiento e inspección del equipamiento de rescate (ej. herramientas de extricación, vehículos). | I37: N/A
F38: Atención Ambulancias | G38: Anual | H38: Verificar que las ambulancias cumplen con el equipamiento y autorizaciones requeridas. | I38: N/A
F39: Ejecución de Simulacros | G39: Semestral | H39: Informes de simulacros de rescate vehicular realizados, que incluyan la evaluación de tiempos de respuesta, coordinación y cierre de brechas. | I39: N/A
B41: RIESGO FATALIDAD | C41: CONTROL | D41: NOMBRE DEL CONTROL | E41: REQUISITO | G41: EVIDENCIA | I41: CUMPLIMIENTO | J41: OBSERVACIONES | K41: FECHA IMPLEMENTACIÓN | L41: PLAN MITIGADOR
B42: RF 10 | C42: CP1 | D42: SISTEMA DE COMUNICACIÓN OPERACIONAL EFECTIVA | E42: Se debe mantener comunicación permanente entre conductores, centro de despacho y supervisión para coordinar movimientos seguros. | G42: a. El conductor debe mantener radio en canal signado, realizar llamados de posición en puntos críticos definidos y confirmar recepción de todas las instrucciones del centro de despacho. | I42: N/A
G43: b. El centro de despacho debe monitorear activamente las comunicaciones, alertar sobre condiciones cambiantes de tránsito, presencia de equipos pesados y coordinar cruces en intersecciones. | I43: N/A
G44: c. Está prohibido operar con sistemas de comunicación defectuosos o cambiar canal sin autorización, debiendo reportar inmediatamente cualquier falla y usar señales visuales de respaldo. | I44: N/A
B45: RF 10 | C45: CP2 | D45: EVALUACIÓN Y SUSPENSIÓN POR CONDICIONES CLIMÁTICAS | E45: La operación debe ajustarse o suspenderse según las condiciones climáticas adversas que afecten la seguridad. | G45: a. El supervisor debe evaluar continuamente condiciones de visibilidad y adherencia, activando protocolos específicos cuando se detecte lluvia, neblina, hielo o viento sobre límites establecidos en el reglamento. | I45: N/A
G46: b. Los conductores deben reducir velocidad al 50% ante lluvia o neblina, duplicar distancia de seguimiento, encender luces y detener operación si la visibilidad es menor a 50 metros. | I46: N/A
G47: c. Está prohibido continuar operando durante alerta roja climática o cuando el supervisor declare suspensión, debiendo estacionar en zona segura señalizada hasta autorización de reinicio. | I47: N/A
B48: RF 10 | C48: CP3 | D48: INSPECCIÓN PREOPERACIONAL DE VEHÍCULO | E48: El conductor debe inspeccionar los sistemas críticos del vehículo antes de cada turno mediante lista de verificación estandarizada. | G48: a. El conductor debe verificar visualmente: indicadores de niveles y estado de neumáticos, funcionamiento de luces, frenos, dirección y bocina, documentando hallazgos en el check list pre-operacional. | I48: N/A
G49: b. Ante detección de fallas en elementos claves de los sistemas críticos (dirección, frenos, neumáticos, sistema eléctrico) el conductor debe etiquetar el vehículo como "fuera de servicio", reportar a mantenimiento y solicitar vehículo de reemplazo. | I49: N/A
G50: c. Está prohibido operar con fallas conocidas en sistemas críticos o sin completar el check list, incluso si el vehículo fue usado en turno anterior sin novedad. | I50: N/A
B51: RF 10 | C51: CP4 | D51: DISPOSITIVOS DE VISIBILIDAD Y SEÑALIZACIÓN | E51: Todo vehículo debe mantener operativos sus elementos de alta visibilidad para ser detectado por otros equipos, utilizando materiales reflectantes, conforme la normativa vigente. | G51: a. El conductor debe verificar en cada turno el funcionamiento de baliza estroboscópica, luces delanteras y traseras, cintas reflectantes perimetrales y banderola en pértiga. | I51: N/A
G52: b. La baliza debe activarse al ingresar a áreas operacionales, las luces mantenerse encendidas permanentemente y portar conos reflectantes para demarcación en detenciones. | I52: N/A
G53: c. Está prohibido operar con dispositivos de visibilidad defectuosos, debiendo reemplazar elementos dañados antes de iniciar operación o solicitar vehículo de respaldo. | I53: N/A
B54: RF 10 | C54: CM1 | D54: PARABRISAS LAMINADO E INASTILLABLE | E54: Los vehículos deben contar con parabrisas de seguridad laminado que evite proyección de fragmentos ante impacto. | G54: a. El parabrisas debe cumplir especificación de vidrio laminado con película intermedia que mantenga los fragmentos adheridos en caso de rotura, evitando lesiones a ocupantes. | I54: N/A
G55: b. Cualquier fisura o daño en el parabrisas debe ser evaluado inmediatamente, reemplazando el vidrio si la grieta supera 10 cm o está en campo visual del conductor. | I55: N/A
G56: c. Está prohibido operar con parabrisas que presente delaminación, opacidad o fisuras múltiples que comprometan la visibilidad o integridad estructural. | I56: N/A
B57: RF 10 | C57: CM2 | D57: EXTINTOR Y BOTIQUÍN EN CABINA | E57: Todo vehículo debe mantener extintor y botiquín de primeros auxilios vigentes y accesibles en cabina. | G57: a. El extintor debe ser tipo ABC de mínimo 1 kg, con carga vigente y manómetro en rango verde, ubicado al alcance del conductor y señalizado claramente. | I57: N/A
G58: b. El botiquín debe contener elementos básicos según estándar divisional, verificando mensualmente fecha de vencimiento de insumos y reponiendo elementos utilizados. | I58: N/A
G59: c. Está prohibido retirar o utilizar el extintor para fines distintos a emergencias, debiendo recargarlo inmediatamente después de cualquier uso parcial o total. | I59: N/A
B60: RF 10 | C60: CM3 | D60: PÉRTIGA CON LUZ, BALIZA, FOCO PARA VISIÓN POSTERIOR (FAENERO) | E60: Los vehículos que operan como faeneros en apoyo a equipos pesados deben contar con dispositivos especiales de visibilidad. | G60: a. La pértiga debe tener altura mínima de 3 metros con luz estroboscópica en extremo superior y banderola reflectante, manteniéndose vertical y asegurada durante toda la operación. | I60: N/A
G61: b. El foco de visión posterior debe iluminar mínimo 10 metros hacia atrás al activar reversa, complementando la baliza giratoria ámbar que debe ser visible a 360 grados. | I61: N/A
G62: c. Está prohibido operar como faenero sin estos dispositivos especiales funcionando correctamente, debiendo mantener distancia mínima de 50 metros de equipos pesados si alguno falla (de acuerdo a lo señalado al Reglamento de Operaciones Mina Rajo del Centro de Trabajo). | I62: N/A
C65: Columna1

Sheet RF11
B2: GERENCIA DE SEGURIDAD Y SALUD OCUPACIONAL - CHUQUICAMATA
B4: LISTADO DE AUTODIAGNÓSTICO RIESGO DE FATALIDAD N° 11: ESPACIOS CONFINADOS
B6: ELEMENTOS DEL CONTROL | I6: CUMPLIMIENTO GENERAL
I7: =AVERAGEIF(I14:I36,"<>N/A") -> #DIV/0!
B10: Alcance | C10: Espacio confinado es cualquier espacio con aberturas limitadas de entrada y salida, no diseñados para ocupación continua por uno o más trabajadores, donde se encuentran con una ventilación natural desfavorable en el que pueden acumularse contaminantes tóxicos, inflamables, explosivos o que tengan una atmósfera deficiente o enriquecida de oxígeno. Aplica para: • Espacios confinados abiertos: Son aquellos que son abiertos en su parte superior y de una profundidad tal que dificulta su ventilación natural, donde se incluyen depósitos abiertos, cubas o cubetas, cubas de desengrasado, pozos abiertos, fosos, bóvedas, cámaras, alcantarillas, zanjas, etc. de más de 1,2 m de profundidad. • Espacios confinados cerrados: Es cualquier espacio, recinto o estructura donde exista un potencial de deficiencia o enriquecimiento de oxígeno generado por partículas, ambientes con atmósferas explosivas, inflamables o tóxicas, y que además tiene la particularidad de que su ingreso se debe hacer a través de un manhole. Según clasificación: • Clase A: Corresponde a aquellos donde existe un inminente peligro para la vida. Generalmente riesgos atmosféricos como gases inflamables y/o tóxicos, deficiencia o enriquecimiento de oxígeno y también riesgos de atrapamiento y/o de derrumbe. • Clase B: En esta clase, los peligros potenciales dentro del espacio confinado pueden ser de lesiones y/o enfermedades que no comprometen la vida ni la salud y pueden controlarse a través de los elementos de protección personal. • Clase C: Esta categoría corresponde a los espacios confinados donde las situaciones de peligro no exigen modificaciones especiales a los procedimientos normales de trabajo o el uso de EPP. Escenarios definidos: Procesos productivos en: Planta ácido, planta oxígeno, planta de gases, fundición, tostación de minerales y plantas concentradoras (incluye molinos, celdas de flotación, chutes), plantas de chancado (primario, secundario, terciario), plantas SX-EW, incluir acidificación o aglomeración y, en general, aquellos procesos donde existan instalaciones o equipos que cumplan con la definición de espacios confinados. También se consideran las excavaciones de más de 1,2 metros de profundidad.
B11: Exclusión | C11: Este evento considera como exclusión los siguientes escenarios. 1.- Desarrollo minero subterráneo. 2.- Convertidor (Reactor). 3.- Domos y stock pile.
B13: RIESGO FATALIDAD | C13: CONTROL CRÍTICO | D13: NOMBRE DEL CONTROL CRÍTICO | E13: OBJETIVO | F13: REQUISITO | G13: MONITOREO | H13: EVIDENCIA | I13: CUMPLIMIENTO | J13: OBSERVACIONES | K13: FECHA IMPLEMENTACIÓN | L13: PLAN MITIGADOR
B14: RF11 | C14: CCP1 | D14: SISTEMA DE INGRESO CONTROLADO Y VIGILADO | E14: Prevenir el ingreso no autorizado o en condiciones inseguras a un espacio confinado, asegurando que toda entrada sea autorizada mediante un permiso de trabajo, con la presencia permanente de un vigía y un sistema de comunicación efectivo. | F14: Procedimiento de Ingreso a Espacio Confinado. | G14: Anual | H14: Solicitar el procedimiento vigente y verificar que define los roles de supervisor, vigía y personal entrante. Verificar que el personal recibió instrucción en el procedimiento. | I14: N/A
F15: Permiso de Ingreso a Espacio Confinado (PTEC). | G15: Por evento | H15: Solicitar el PTEC de una tarea, verificando su correcto llenado, firmas, mediciones de gases y autorización. | I15: N/A
F16: Designación y Presencia de Vigía. | G16: Por evento | H16: Verificar en el PTEC la designación de un vigía exclusivo y confirmar su presencia permanente en el punto de ingreso. | I16: N/A
F17: Sistema de Comunicación Bidireccional. | G17: Por evento | H17: Solicitar el registro de la prueba de comunicación entre el vigía y el personal entrante antes de autorizar el ingreso. | I17: N/A
F18: Control de Acceso y Registro de Personal. | G18: Por evento | H18: Verificar que el vigía mantiene un registro actualizado de quiénes y a qué hora ingresaron y salieron del espacio. | I18: N/A
F19: Personal Acreditado y Capacitado | G19: Anual | H19: Solicitar credencial, registros de aprobación de curso del riesgo de fatalidad e instrucción del procedimiento de trabajo en espacios confinados y los certificados de aptitud médica del personal. | I19: N/A
B20: RF 11 | C20: CCP2 | D20: EVALUACIÓN Y MONITOREO CONTINUO DE ATMÓSFERA | E20: Prevenir la intoxicación, asfixia o explosión, asegurando que la atmósfera de todo espacio confinado sea medida antes de ingresar y monitoreada continuamente durante la permanencia del personal, utilizando equipos calibrados y específicos para los riesgos presentes. | F20: Procedimiento de Medición de Atmósfera. | G20: Anual | H20: Solicitar el procedimiento que define cómo, cuándo y desde dónde se deben realizar las mediciones de atmósfera. | I20: N/A
F21: Medición Inicial Previo al Ingreso. | G21: Por evento | H21: Verificar en el Permiso de Ingreso (PTEC) el registro de la medición inicial de gases (O₂, LEL, CO, H₂S), con fecha, hora y firma. | I21: N/A
F22: Monitoreo Continuo Durante la Tarea. | G22: Por evento | H22: Verificar en terreno que el personal dentro del espacio confinado porta un monitor de gases personal, encendido y operativo. | I22: N/A
F23: Equipos de Medición Calibrados y Certificados. | G23: Mensual | H23: Solicitar el certificado de calibración vigente del equipo de medición de gases y registro de prueba de verificación funcional. | I23: N/A
F24: Personal Entrenado en Medición de Gases. | G24: Anual | H24: Solicitar los registros de instrucción práctica del personal autorizado para realizar mediciones de atmósfera. | I24: N/A
F25: Protocolo de Acción ante Alarmas. | G25: Anual | H25: Verificar en el procedimiento la instrucción de evacuación inmediata del espacio ante cualquier alarma del monitor de gases. | I25: N/A
B26: RF 11 | C26: CCP3 | D26: IDENTIFICACIÓN Y PREPARACIÓN DE ESPACIOS CONFINADOS | E26: Asegurar que todos los espacios confinados estén identificados, señalizados y preparados adecuadamente antes del ingreso, mediante la aislación de energías, el control de flujos de entrada y la implementación de ventilación para mantener una atmósfera segura. | F26: Catastro de Espacios Confinados Actualizado. | G26: Anual | H26: Solicitar el inventario y mapa de todos los espacios confinados del área, con su clasificación de riesgo. | I26: N/A
F27: Señalización de Espacios Confinados. | G27: Semestral | H27: Verificar en terreno que todas las entradas a espacios confinados están señalizadas. | I27: N/A
F28: Aislación y Bloqueo de Energías y Flujos. | G28: Por evento | H28: Solicitar el Permiso de Ingreso (PTEC) y los registros de bloqueo que verifiquen el aislamiento de todas las energías y líneas de proceso. | I28: N/A
F29: Preparación del Espacio (Purga y Limpieza). | G29: Por evento | H29: Verificar en el procedimiento y en el PTEC los requisitos de limpieza, drenaje o inertización previos al ingreso. | I29: N/A
F30: Sistema de Ventilación Adecuado. | G30: Por evento | H30: Verificar que el cálculo de ventilación y el equipo utilizado son los adecuados para el tamaño del espacio y los contaminantes. | I30: N/A
F31: Inspección de Equipos de Ventilación. | G31: Trimestral | H31: Solicitar los registros de inspección y mantenimiento de los equipos de ventilación forzada. | I31: N/A
B32: RF 11 | C32: CCM1 | D32: CAPACIDAD DE RESPUESTA Y RESCATE ANTE EMERGENCIA EN ESPACIOS CONFINADOS | E32: Garantizar un rescate rápido, seguro y eficaz de personas desde un espacio confinado en caso de una emergencia, mediante un plan de rescate específico, personal entrenado y equipamiento adecuado disponible en el lugar. | F32: Plan de Rescate para Espacios Confinados | G32: Por evento | H32: Verificar que el plan de rescate está documentado y aprobado. | I32: N/A
F33: Equipo de Rescate Disponible e Inspeccionado. | G33: Por evento | H33: Verificar en terreno la presencia y el registro de inspección vigente del equipo de rescate (trípode, huinche, ERA, cuerdas, etc.). | I33: N/A
F34: Personal de Rescate Entrenado | G34: Anual | H34: Solicitar los registros de capacitación de la brigada o equipo de rescate en espacios confinados. | I34: N/A
F35: Simulacros de Rescate Realizados y Evaluados. | G35: Semestral | H35: Solicitar el informe del último simulacro de rescate en espacio confinado, verificando tiempos y planes de acción de las brechas. | I35: N/A
F36: Comunicación con Equipo de Rescate. | G36: Por evento | H36: Verificar en el PTEC el registro de la comunicación con la brigada o equipo de rescate para informarles del inicio del trabajo. | I36: N/A
B38: RIESGO FATALIDAD | C38: CONTROL | D38: NOMBRE DEL CONTROL | E38: REQUISITO | G38: EVIDENCIA | I38: CUMPLIMIENTO | J38: OBSERVACIONES | K38: FECHA IMPLEMENTACIÓN | L38: PLAN MITIGADOR
B39: RF 11 | C39: CP1 | D39: VENTILACIÓN FORZADA INSTALADA Y OPERATIVA EN ESPACIOS CONFINADOS (CUANDO APLIQUE) | E39: Cuando la ventilación natural de un espacio confinado sea insuficiente, se debe instalar y mantener un sistema de ventilación forzada para asegurar la renovación del aire y mantener la atmósfera dentro de los límites seguros. | G39: a. El supervisor a cargo debe asegurar que el equipo de ventilación forzada (extractor o inyector) sea de la capacidad adecuada para el volumen del espacio y que se instale según las especificaciones técnicas para garantizar un barrido efectivo del aire. | I39: N/A
G40: b. Antes del ingreso, el equipo de ventilación debe operarse por un tiempo suficiente para realizar múltiples renovaciones del volumen de aire del espacio, verificando su efectividad mediante mediciones de gases. | I40: N/A
G41: c. El sistema de ventilación forzada debe mantenerse operativo durante todo el tiempo que el personal permanezca en el interior del espacio confinado. | I41: N/A
B42: RF 11 | C42: CP2 | D42: ILUMINACIÓN CERTIFICADA Y SEGURA PARA ESPACIOS CONFINADOS | E42: La iluminación artificial utilizada en el interior de un espacio confinado debe ser certificada para el tipo de ambiente presente y operar a un voltaje de seguridad que no exceda los 24 voltios. | G42: a. El supervisor debe asegurar que todas las luminarias, extensiones y equipos eléctricos introducidos en el espacio confinado sean intrínsecamente seguros o a prueba de explosión si existe potencial de atmósfera inflamable. | I42: N/A
G43: b. El personal que ingresa debe verificar que la iluminación instalada sea suficiente para realizar la tarea de forma segura, permitiendo una clara visibilidad del área de trabajo, los equipos y las vías de evacuación. | I43: N/A
G44: c. Cualquier equipo de iluminación que presente fallas o daños en sus cables o conexiones debe ser retirado de servicio de inmediato y reemplazado por uno en buen estado para evitar riesgos de electrocución o ignición. | I44: N/A
B45: RF 11 | C45: CP3 | D45: SALUD COMPATIBLE PARA INGRESO A ESPACIOS CONFINADOS | E45: Todo trabajador que deba ingresar a un espacio confinado debe contar con una evaluación médica que certifique su aptitud física y psicológica para realizar trabajos en estas condiciones. | G45: a. El supervisor del área debe verificar que todo el personal programado para ingresar a un espacio confinado posee su examen de salud compatible vigente, conforme a los protocolos médicos definidos por la organización. | I45: N/A
G46: b. El trabajador tiene la obligación de informar a su supervisor cualquier condición de salud que pueda afectar su capacidad para trabajar de forma segura en un espacio confinado, antes de iniciar la tarea. | I46: N/A
G47: c. No se autorizará el ingreso de ningún trabajador que no cuente con su certificación de salud compatible o que manifieste no encontrarse en condiciones óptimas para la tarea. | I47: N/A
C50: Columna1

Sheet RF12
B2: GERENCIA DE SEGURIDAD Y SALUD OCUPACIONAL - CHUQUICAMATA
B4: LISTADO DE AUTODIAGNÓSTICO RIESGO DE FATALIDAD N° 12: METALES FUNDIDOS
B6: ELEMENTOS DEL CONTROL | I6: CUMPLIMIENTO GENERAL
I7: =AVERAGEIF(I14:I40,"<>N/A") -> #DIV/0!
B10: Alcance | C10: Interacción de metal fundidos en tareas realizadas en procesos de fusión, conversión, refino moldeo y transporte, donde los trabajadores estén expuestos a derrames, proyección de material fundido, temperaturas elevadas:
B11: Exclusión | C11: Este evento considera como exclusión los siguientes escenarios: • Liberación descontrolada de vapor a alta presión en los procesos de fundición. • Explosiones en Planta de oxígeno. • Exposición de gases SO3 y SO2 en Planta de ácido. • Exposición a ácido sulfúrico. • Procesos de almacenamiento y secado de concentrado de cobre.
B13: RIESGO FATALIDAD | C13: CONTROL CRÍTICO | D13: NOMBRE DEL CONTROL CRÍTICO | E13: OBJETIVO | F13: REQUISITO | G13: MONITOREO | H13: EVIDENCIA | I13: CUMPLIMIENTO | J13: OBSERVACIONES | K13: FECHA IMPLEMENTACIÓN | L13: PLAN MITIGADOR
B14: RF12 | C14: CCP1 | D14: PERSONAL CAPACITADO PARA TRABAJAR CON METALES FUNDIDOS | E14: Todo trabajador que desarrolle actividades en contacto directo con metales fundidos debe estar capacitado y autorizado por la administración, demostrando conocimiento en los riesgos y controles de los equipos y procesos específicos del área. | F14: Personal capacitado | G14: Anual | H14: Solicitar registro de aprobación de cursos de riesgo de fatalidad de metales fundidos. Verificar que el personal conoce los parámetros operacionales y el riesgo de explosión, por el contacto de agua con metales fundidos | I14: N/A
F15: Listado de personal autorizado | G15: Trimestral | H15: Solicitar al supervisor el listado de personal autorizado | I15: N/A
F16: Personal autorizado para la operación de equipos | G16: Semestral | H16: Solicitar el listado de personal autorizado para operar equipos específicos del proceso pirometalúrgico, tales como Hornos (Flash, Eléctrico, Refino), Convertidores (CPS, Teniente), Puentes Grúa, Locomotoras, Camiones de Escoria y Rueda de Moldeo, se otorgará únicamente al personal que haya aprobado el curso de operación de equipos. | I16: N/A
B17: RF 12 | C17: CCP2 | D17: CONTROL DE ACCESO A ÁREAS DE FUNDICIÓN | E17: Prevenir la exposición de personal a la línea de fuego del metal fundido, asegurando que todo ingreso y tránsito por las naves de fundición sea estrictamente controlado, comunicado y autorizado, siguiendo un plan de tránsito establecido. | F17: Plan de Tránsito y Control de Ingreso Vigente. | G17: Anual | H17: Solicitar el plan de tránsito del área y el procedimiento de control de ingreso, verificando su actualización y difusión. | I17: N/A
F18: Autorización Formal de Ingreso. | G18: Diario | H18: Solicitar registros (bitácoras, permisos) que evidencien la autorización de ingreso del personal ajeno a la operación. | I18: N/A
F19: Comunicación Radial Bidireccional. | G19: Por evento | H19: Verificar en terreno que el personal en piso cuenta con radio y ha establecido comunicación con la sala de control u operadores. | I19: N/A
F20: Demarcación de Líneas de Fuego y Vías Peatonales. | G20: Mensual | H20: Verificar en terreno que las zonas de alto riesgo y las vías de tránsito seguras están claramente demarcadas y señalizadas. | I20: N/A
F21: Segregación de Ambientes de Trabajo. | G21: Mensual | H21: Verificar en terreno la implementación de barreras que segregan la interacción entre equipos pesados, livianos y personas. | I21: N/A
F22: Personal Capacitado para el Área. | G22: Anual | H22: Solicitar los registros del curso de riesgo de fatalidad e instrucción de la inducción específica para ingresar y trabajar en áreas de fundición. | I22: N/A
B23: RF 12 | C23: CCP3 | D23: CONTROL OPERACIONAL DEL METAL FUNDIDO (TRASLADO, MONITOREO, REFRIGERACIÓN) | E23: Prevenir derrames o proyecciones violentas de metal, asegurando que el traslado, el monitoreo de variables críticas y la integridad de los equipos que contienen o están en contacto con material fundido se gestionen conforme a procedimientos y estándares de mantenimiento. | F23: Programa de Mantenimiento de Equipos Críticos. | G23: Mensual | H23: Solicitar la pauta y los registros de mantenimiento preventivo ejecutado para equipos clave (puentes grúa, hornos, convertidores). | I23: N/A
F24: Inspección de Pre-Uso de Equipos de Traslado. | G24: Diario | H24: Solicitar los checklists de pre-uso firmados por los operadores de puentes grúa y locomotoras del turno. | I24: N/A
F25: Monitoreo de Variables Críticas de Proceso. | G25: Diario | H25: Verificar en sala de control los registros de monitoreo de variables críticas (ej. temperatura de hornos, niveles). | I25: N/A
F26: Sistemas de Refrigeración Operativos. | G26: Semanal | H26: Solicitar los registros de inspección y mantenimiento que verifiquen el correcto funcionamiento de los sistemas de refrigeración. | I26: N/A
F27: Control de Velocidad de Equipos Móviles. | G27: Semanal | H27: Verificar mediante observación o registros (GPS si aplica) que los equipos de traslado operan a velocidades controladas. | I27: N/A
F28: Competencias y Acreditación del Personal Operador | G28: Anual | H28: Solicitar listado de competencias del perfil o descriptor del cargo, aprobación del curso de riesgo de fatalidad y acreditación vigentes para operadores de equipos críticos. | I28: N/A
B29: RF 12 | C29: CCP4 | D29: CONTROL DE HUMEDAD EN OPERACIONES CON METAL FUNDIDO | E29: Prevenir explosiones por contacto de agua/humedad con metal fundido, asegurando que todas las áreas, materiales, herramientas y equipos estén secos, y que los sistemas de drenaje y bombeo de las naves estén permanentemente operativos. | F29: Procedimiento de Control de Humedad. | G29: Anual | H29: Solicitar el procedimiento que define los controles para evitar el contacto de agua con metal fundido. | I29: N/A
F30: Verificación de Materiales Secos. | G30: Diario | H30: Verificar en el procedimiento y mediante observación en terreno, los controles para asegurar la sequedad de los materiales añadidos a los hornos. | I30: N/A
F31: Precalentamiento de Herramientas y Recipientes. | G31: Por evento | H31: Solicitar los registros o verificar en terreno que las ollas, cucharas y herramientas son precalentadas antes de su uso. | I31: N/A
F32: Sistemas de Drenaje y Bombeo Operativos. | G32: Mensual | H32: Solicitar los registros de inspección y mantenimiento de los sistemas de drenaje y bombas de las naves de fundición. | I32: N/A
F33: Inspección de Presencia de Agua en Áreas Críticas. | G33: Diario | H33: Solicitar los checklists de la supervisión que incluyan la inspección de fosos y pisos buscando presencia de agua. | I33: N/A
F34: Personal Capacitado en Riesgo Agua- Metal. | G34: Anual | H34: Solicitar los registros de capacitación que demuestren que el personal ha sido instruido sobre el peligro de explosiones por humedad. | I34: N/A
B35: RF 12 | C35: CCM1 | D35: PROTECCIÓN PERSONAL Y ESTRUCTURAL CONTRA METAL FUNDIDO (EPP, CASETAS Y CONTENCIÓN) | E35: Minimizar las consecuencias de un contacto con metal fundido, asegurando que el personal expuesto utilice EPP especializado que retarde la transferencia de calor, y que existan refugios estructurales (casetas, cabinas) que provean una barrera física contra derrames y proyecciones. | F35: EPP para Metal Fundido. | G35: Anual | H35: Solicitar documento que defina el tipo de traje y elementos de protección según la tarea y el nivel de exposición. | I35: N/A
F36: Inspección de EPP Pre-Uso. | G36: Diario | H36: Verificar mediante observación en terreno que el personal utiliza el EPP correcto y que este se encuentra en buen estado. | I36: N/A
F37: Diseño y Estándar de Salas y Cabinas. | G37: Por Proyecto | H37: Solicitar el estándar de diseño y la memoria de cálculo para salas de control, casetas de refugio y cabinas de equipos. | I37: N/A
F38: Inspección de Integridad de Estructuras. | G38: Mensual | H38: Solicitar los registros de inspección que verifican la integridad de salas, cabinas y casetas (hermeticidad, vidrios, estructura). | I38: N/A
F39: Programa de Mantenimiento de Estructuras. | G39: Trimestral | H39: Solicitar el programa de mantenimiento para las salas, cabinas y casetas de protección y verificar sus registros de ejecución. | I39: N/A
F40: Disponibilidad y Gestión de Stock de EPP. | G40: Trimestral | H40: Solicitar los registros de inventario y verificar la disponibilidad de stock para el EPP específico para metal fundido. | I40: N/A
B41: RF 12 | C41: CCM2 | D41: CAPACIDAD DE RESPUESTA Y RESCATE ANTE EMERGENCIA | E41: Garantizar una respuesta sistémica, inmediata y eficaz ante un accidente con metal fundido, integrando la comunicación, la brigada y la atención médica especializada, para rescatar, enfriar y atender a las personas afectadas y minimizar la severidad de las quemaduras. | F41: Plan de Emergencia Específico para Quemaduras. | G41: Anual | H41: Solicitar el plan de emergencia y verificar que incluye un protocolo específico para contacto con metal fundido. | I41: N/A
F42: Brigada y Personal Médico Entrenados. | G42: Semestral | H42: Solicitar los registros de entrenamiento de la brigada y del personal de salud. | I42: N/A
F43: Duchas de Emergencia y Equipos de Primera Respuesta. | G43: Mensual | H43: Solicitar los registros de inspección y pruebas funcionales semanales de las duchas y lavaojos de emergencia. | I43: N/A
F44: Sistemas de Alarma y Comunicación Funcionales. | G44: Trimestral | H44: Solicitar registros de pruebas funcionales de los sistemas de alarma y de los canales de comunicación de emergencia. | I44: N/A
F45: Simulacros Específicos Realizados y Evaluados. | G45: Semestral | H45: Solicitar el informe del último simulacro de contacto con metal fundido, verificando tiempos de respuesta y planes de acción. | I45: N/A
F46: Personal Capacitado ante Emergencias | G46: Trimestral | H46: Verificar que el personal ha sido instruido en el procedimiento de emergencia y realizó el curso de primeros auxilios. | I46: N/A
B48: RIESGO FATALIDAD | C48: CONTROL | D48: NOMBRE DEL CONTROL | E48: REQUISITO | G48: EVIDENCIA | I48: CUMPLIMIENTO | J48: OBSERVACIONES | K48: FECHA IMPLEMENTACIÓN | L48: PLAN MITIGADOR
B49: RF 10 | C49: CP1 | D49: REGULACIÓN DE PERNOS TENSORES EN PISO Y BÓVEDA | E49: Se debe mantener un control y regulación sistemática de los pernos tensores en la estructura de los hornos, como el Horno Flash, para asegurar la integridad estructural y prevenir la infiltración de líquido fundido. | G49: a. El personal de mantenimiento mecánico debe ejecutar el programa de inspección y torque de los pernos tensores del piso y bóveda del horno, según la frecuencia y especificaciones técnicas definidas en el plan de mantenimiento. | I49: N/A
G50: b. Durante la inspección, se debe verificar el estado de los pernos, tuercas y la estructura circundante, reportando cualquier signo de deformación, corrosión o daño para su evaluación y programación de recambio. | I50: N/A
G51: c. El supervisor de mantenimiento es responsable de mantener los registros de cada campaña de regulación de pernos, asegurando la trazabilidad de las intervenciones y el cumplimiento del programa. | I51: N/A
B52: RF 10 | C52: CP2 | D52: USO DE BOCINA/BALIZA ANTES DE INICIAR MOVIMIENTO | E52: Todo operador de equipo móvil que transporte material fundido (ej. puente grúa, locomotora) debe accionar las señales audibles y visibles (bocina y baliza) antes y durante el desplazamiento del equipo. | G52: a. El operador del equipo debe emitir una señal acústica estandarizada, según el protocolo de comunicación del área, para anunciar el inicio del movimiento de la carga. | I52: N/A
G53: b. La baliza estroboscópica del equipo debe permanecer encendida durante todo el trayecto en que se transporte material fundido, para advertir visualmente de la presencia de un peligro en movimiento. | I53: N/A
G54: c. El supervisor de turno debe verificar, mediante observaciones de tareas, que los operadores cumplan con el uso sistemático de las señales de advertencia, reforzando este comportamiento en las charlas operativas. | I54: N/A
B55: RF 10 | C55: CP3 | D55: SALUD COMPATIBLE PARA TRABAJOS CON METAL FUNDIDO | E55: Todo el personal que trabaje expuesto a la línea de fuego de metales fundidos debe contar con una evaluación de salud vigente que certifique su aptitud física y psicológica para la tarea. | G55: a. El supervisor de turno es responsable de verificar, antes del inicio de las tareas, que cada trabajador asignado a la zona de riesgo cuenta con su certificado de aptitud vigente, el cual debe estar registrado en los sistemas de la compañía. | I55: N/A
G56: b. Todo trabajador tiene la obligación de informar a su supervisión cualquier condición de salud que pueda mermar sus capacidades, como fatiga, somnolencia o malestar, antes de iniciar el trabajo. | I56: N/A
G57: c. Está prohibido el ingreso a las áreas de manejo de metal fundido a cualquier persona que no posea su certificado de aptitud o que reporte no estar en condiciones óptimas para el trabajo, debiendo ser reasignado a otra tarea. | I57: N/A
C60: Columna1

Sheet RF13
B2: GERENCIA DE SEGURIDAD Y SALUD OCUPACIONAL - CHUQUICAMATA
B4: LISTADO DE AUTODIAGNÓSTICO RIESGO DE FATALIDAD N° 13: CAÍDA DE OBJETOS
B6: ELEMENTOS DEL CONTROL | I6: CUMPLIMIENTO GENERAL
I7: =AVERAGEIF(I14:I31,"<>N/A") -> #DIV/0!
B10: Alcance | C10: Caídas de objetos en áreas de proyectos y/o operaciones mineras, esto incluye procesos, plantas y área mina que puede resultar en lesiones graves y/o fatales a personas. Escenarios definidos son: •Trabajos en la vertical sobre andamios y/o estructuras en etapa de construcción y mantención. • Procesos productivos en plantas concentradoras, incluye molinos, cajones, correas, electroimán, etc. • Procesos productivos exterior planta. Ejemplos: aglomeradores, chancadores, alimentador, harneros, correas, etc. • Almacenamiento en bodega. • Procesos productivos en fundiciones: almacenamiento y transporte de concentrado, área fusión, conversión, refino y moldeo, planta de gases, planta de ácidos y planta de oxígeno. • Proceso de Inspección y mantención a equipos donde material pueda deprenderse desde equipos de carguío y transporte.
B11: Exclusión | C11: Este evento considera como exclusión los siguientes escenarios: • Operaciones con aeronaves no tripuladas (drones). • Operaciones con aeronaves tripuladas. • Caídas de rocas por falla de terreno. • Procesos productivos en minería subterráneas. • Falla o colapso estructural. • Perforación en sondaje. • Proyección de rocas en tronaduras.
B13: RIESGO FATALIDAD | C13: CONTROL CRÍTICO | D13: NOMBRE DEL CONTROL CRÍTICO | E13: OBJETIVO | F13: REQUISITO | G13: MONITOREO | H13: EVIDENCIA | I13: CUMPLIMIENTO | J13: OBSERVACIONES | K13: FECHA IMPLEMENTACIÓN | L13: PLAN MITIGADOR
B14: RF13 | C14: CCP1 | D14: ESTRUCTURAS Y MATERIALES SUJETOS EN ALTURA | E14: Prevenir la caída de objetos por fallas estructurales, almacenamiento incorrecto o condiciones ambientales, asegurando que todas las estructuras en altura sean inspeccionadas, los materiales acopiados estén asegurados y se controlen los trabajos ante vibraciones o clima adverso. | F14: Programa de Inspección de Estructuras. | G14: Semestral | H14: Solicitar el programa de inspección estructural y los informes con los hallazgos y planes de acción. | I14: N/A
F15: Procedimiento o instructivo de Acopio Seguro en Altura. | G15: Anual | H15: Solicitar el procedimiento o instructivo que define los criterios para el apilamiento y aseguramiento de materiales en plataformas. | I15: N/A
F16: Barreras para Objetos Rodantes. | G16: Trimestral | H16: Verificar en terreno que las áreas de acopio de objetos cilíndricos cuentan con barreras o sistemas de contención efectivos. | I16: N/A
F17: Retiro Programado de Material Acumulado. | G17: Mensual | H17: Solicitar el programa de limpieza de estructuras de proceso (correas, chutes) y los registros de su ejecución. | I17: N/A
F18: Control por Condiciones Climáticas Adversas. | G18: Anual | H18: Solicitar el procedimiento que define los criterios de suspensión de trabajos por viento, lluvia o nieve. | I18: N/A
F19: Control de Vibraciones. | G19: Trimestral | H19: Verificar que el plan de mantenimiento incluye la inspección de fijaciones y el control de vibraciones en equipos críticos. | I19: N/A
B20: RF 13 | C20: CCP2 | D20: CONTROL DE TRABAJOS EN LA VERTICAL | E20: Prevenir la caída de herramientas y objetos durante la ejecución de trabajos en altura, asegurando que toda tarea en la vertical sea planificada, que las herramientas estén amarradas, y que los trabajos simultáneos en distintos niveles estén coordinados. | F20: Procedimiento de trabajo | G20: Anual | H20: Solicitar el procedimiento de trabajo para una tarea en altura, verificando el análisis de riesgo de caída de objetos y la autorización. | I20: N/A
F21: Control de Trabajos Simultáneos. | G21: Por evento | H21: Solicitar el registro de coordinación (ART cruzado) para trabajos simultáneos en la misma vertical. | I21: N/A
F22: Sistema de Sujeción de Herramientas. | G22: Por evento | H22: Verificar en terreno que el personal utiliza sistemas de amarre (muñequeras, cordeles certificados) para sus herramientas. | I22: N/A
F23: Elementos de Izaje Manual Certificados. | G23: Trimestral | H23: Solicitar la inspección y certificación vigente de los elementos de izaje manual (tecles, eslingas). | I23: N/A
F24: Housekeeping Obligatorio Post-Tarea. | G24: Diaria | H24: Verificar en procedimiento y en terreno, el retiro de todos los materiales al finalizar cada trabajo. | I24: N/A
F25: Personal capacitado para Trabajos en Altura. | G25: Anual | H25: Solicitar los registros de capacitación y acreditación del personal que ejecuta trabajos en la vertical. | I25: N/A
B26: RF 13 | C26: CCM1 | D26: SISTEMAS DE CONTENCIÓN Y SEGREGACIÓN | E26: Minimizar las consecuencias de una caída de objetos, mediante la instalación de sistemas de contención secundaria (mallas, rodapiés) y la segregación física de los niveles inferiores para evitar que personas ingresen a la zona de caída. | F26: Procedimiento que regule la Segregación de Niveles Inferiores. | G26: Anual | H26: Solicitar el procedimiento o instructivo que defina el tipo de barrera física y el radio de exclusión para trabajos en altura. | I26: N/A
F27: Implementación de Segregación Efectiva. | G27: Por evento | H27: Verificar en terreno que el área bajo la zona de trabajo está segregada con barreras físicas y señalizada. | I27: N/A
F28: Instalación de Rodapiés en Plataformas. | G28: Semestral | H28: Inspeccionar los andamios y plataformas de trabajo, verificando que todos los bordes cuentan con rodapiés. | I28: N/A
F29: Uso de Sistemas de Contención Secundaria. | G29: Por evento | H29: Para trabajos sobre áreas críticas, verificar en el plan de trabajo la definición e instalación de mallas o bandejas de contención. | I29: N/A
F30: Inspección de Integridad de Barreras. | G30: Mensual | H30: Solicitar los registros de inspección que verifican el buen estado de las mallas, rodapiés y otros sistemas de contención. | I30: N/A
F31: Personal instruido en Segregación. | G31: Trimestral | H31: Verificar registros de aprobación de instrucción del personal en segregación y, mediante entrevistas en terreno, verificar que el personal conoce su importancia y las aplica. | I31: N/A
B32: RF 13 | C32: CCM2 | D32: CAPACIDAD DE RESPUESTA ANTE EMERGENCIA | E32: Garantizar una respuesta médica rápida, coordinada y eficaz ante un accidente por caída de objetos, para estabilizar al lesionado, minimizar la severidad del trauma y asegurar su evacuación a un centro de atención especializado en el menor tiempo posible. | F32: Plan de Emergencia para Trauma por Impacto. | G32: Anual | H32: Solicitar el plan de emergencia y verificar que incluye un protocolo específico para la atención de lesionados por caída de objetos. | I32: N/A
F33: Brigada Entrenada en Trauma. | G33: Semestral | H33: Solicitar los registros de entrenamiento de la brigada en protocolos de primeros auxilios. | I33: N/A
F34: Equipos de Primera Respuesta y Rescate Disponibles. | G34: Mensual | H34: Solicitar los registros de inspección mensual de los equipos de primera respuesta y rescate. | I34: N/A
F35: Sistemas de Comunicación de Emergencia Funcionales. | G35: Trimestral | H35: Solicitar registros de pruebas funcionales de los canales de radio y los números telefónicos de emergencia. | I35: N/A
F36: Simulacros Específicos Realizados. | G36: Semestral | H36: Solicitar el informe del último simulacro de accidente por caída de objeto, verificando tiempos de respuesta y planes de acción. | I36: N/A
F37: Personal Capacitado en Primera Respuesta. | G37: Anual | H37: Solicitar los registros de capacitación en primeros auxilios básicos para el personal que trabaja en áreas de riesgo. | I37: N/A
B39: RIESGO FATALIDAD | C39: CONTROL | D39: NOMBRE DEL CONTROL | E39: REQUISITO | G39: EVIDENCIA | I39: CUMPLIMIENTO | J39: OBSERVACIONES | K39: FECHA IMPLEMENTACIÓN | L39: PLAN MITIGADOR
B40: RF 13 | C40: CP1 | D40: CONTROL DE ORDEN Y LIMPIEZA EN TRABAJOS EN ALTURA | E40: Todas las plataformas de trabajo en altura deben mantenerse ordenadas, limpias y libres de objetos, herramientas o materiales sueltos que no estén en uso y que puedan caer accidentalmente. | G40: a. El supervisor a cargo de la tarea es responsable de asegurar que el área de trabajo se mantenga despejada, verificando que solo permanezcan en altura las herramientas y materiales necesarios para la ejecución inmediata del trabajo. | I40: N/A
G41: b. Todo el personal que trabaje en altura debe practicar un housekeeping continuo, almacenando temporalmente los pernos, tuercas, piezas menores y herramientas en contenedores o bolsos amarrados a la estructura. | I41: N/A
G42: c. Al finalizar el turno o la tarea, se debe realizar una limpieza completa del área, asegurando el retiro de todos los elementos estructurales, insumos, despuntes y objetos externos a la instalación, prohibiendo abandonar cualquier material en altura. | I42: N/A
B43: RF 13 | C43: CP2 | D43: USO DE PORTA HERRAMIENTAS CERTIFICADOS | E43: Toda herramienta manual utilizada en trabajos en altura debe ser asegurada mediante el uso de bolsos, cinturones o cordeles de sujeción (colas de amarre) diseñados y certificados para evitar su caída. | G43: a. El trabajador es responsable de asegurar cada una de sus herramientas manuales a un punto de anclaje seguro (cinturón, muñeca o estructura) antes de iniciar el ascenso o la tarea en altura. | I43: N/A
G44: b. El supervisor debe verificar que el personal a su cargo cuenta con los dispositivos portaherramientas adecuados y certificados para las herramientas que utilizará, y que los utiliza correctamente durante toda la tarea. | I44: N/A
G45: c. Está prohibido transportar herramientas en los bolsillos, en la mano durante el ascenso o descenso de escaleras, o utilizar elementos hechizos (alambres, cordeles no certificados) para su sujeción. | I45: N/A
B46: RF 13 | C46: CP3 | D46: INSPECCIÓN VISUAL DE ACCESORIOS DE IZAJE MANUAL | E46: Todos los accesorios y sistemas de sujeción utilizados para el izaje manual de objetos en altura (cables, ganchos, seguros, chavetas) deben ser inspeccionados visualmente por el usuario antes de cada maniobra. | G46: a. El trabajador, antes de conectar la carga, debe realizar una inspección visual del sistema de sujeción para verificar la ausencia de daños, deformaciones, desgaste excesivo o mal funcionamiento de sus componentes, como el seguro del gancho. | I46: N/A
G47: b. Cualquier accesorio de izaje que presente una condición subestándar o un defecto debe ser retirado de servicio inmediatamente, etiquetado como "No Usar" y reportado a la supervisión para su reemplazo. | I47: N/A
G48: c. El supervisor a cargo debe verificar que el método de trabajo y los accesorios de izaje seleccionados sean los correctos para el peso y la forma del objeto a izar, asegurando que no se excedan las capacidades de diseño. | I48: N/A
C51: Columna1

Sheet RF14
B2: GERENCIA DE SEGURIDAD Y SALUD OCUPACIONAL - CHUQUICAMATA
B4: LISTADO DE AUTODIAGNÓSTICO RIESGO DE FATALIDAD N°14: OPERACIÓN FERROVIARIA
B6: ELEMENTOS DEL CONTROL | I6: CUMPLIMIENTO GENERAL
I7: =AVERAGEIF(I14:I42,"<>N/A") -> #DIV/0!
B10: Alcance | C10: Este riesgo de fatalidad aplica a las siguientes actividades: •Transporte de mineral vía ferroviaria •Transporte de pasajeros vía ferroviaria •Servicios de apoyo a operaciones ferroviarias •Mantención vías •Mantención de equipos ferroviarios
B11: Exclusión | C11: Este riesgo de fatalidad considera como exclusión los siguientes escenarios: Movimientos ferroviarios fuera de instalaciones de la empresa (áreas de terceros, vías públicas).
B13: RIESGO FATALIDAD | C13: CONTROL CRÍTICO | D13: NOMBRE DEL CONTROL CRÍTICO | E13: OBJETIVO | F13: REQUISITO | G13: MONITOREO | H13: EVIDENCIA | I13: CUMPLIMIENTO | J13: OBSERVACIONES | K13: FECHA IMPLEMENTACIÓN | L13: PLAN MITIGADOR
B14: RF14 | C14: CCP1 | D14: PERSONAL FERROVIARIO ACREDITADO | E14: Garantizar que toda persona que interactúe directamente con la operación ferroviaria posea las competencias técnicas, la aptitud física/psicológica requerida y la autorización formal y vigente para ingresar y ejecutar sus funciones en la vía férrea, previniendo errores operacionales por falta de capacitación o ingreso no controlado | F14: Programa de Capacitación y Entrenamiento | G14: Anual | H14: Solicitar el programa de capacitación y entrenamiento teórico-práctico para maquinistas y cuadrillas. | I14: N/A
F15: Autorización Interna Vigente | G15: Mensual | H15: Verificar en terreno que todo el personal (maquinistas, cuadrillas, entre otros) portan su credencial de autorización vigente. | I15: N/A
F16: Certificado de Aptitud Física y Psicológica | G16: Anual | H16: Verificar que todo el personal de la operación ferroviaria cuenta con sus exámenes preocupacionales y psicosensométricos vigentes y aprobados. | I16: N/A
F17: Protocolo de Autorización de Ingreso a Vía | G17: Semestral | H17: Solicitar el procedimiento que define el proceso de autorización de ingreso a la vía férrea, especificando quién autoriza, el medio de comunicación (ej. frecuencia radial) y los permisos requeridos | I17: N/A
F18: Segregación Física de Accesos a la Ví | G18: Mensual | H18: Verificar en terreno la integridad y funcionalidad de los elementos de segregación (puertas, portones, barreras) definidos en el Layout de segregación para controlar el acceso | I18: N/A
F19: Instrucción en Riesgos Ferroviarios | G19: Anual | H19: Verificar los registros que demuestren que todo el personal que ingresa a la vía ha recibido una instrucción específica sobre los riesgos críticos del área, el reglamento interno y los protocolos de emergencia. | I19: N/A
B20: RF14 | C20: CCP2 | D20: INTEGRIDAD OPERATIVA DE VÍAS Y EQUIPOS FERROVIARIOS | E20: Garantizar la integridad estructural y la plena operatividad tanto de la infraestructura de la vía férrea como de los equipos (locomotoras, carros), a través de un sistema riguroso de mantenimiento preventivo e inspecciones pre-uso, para prevenir desrielos o colisiones por fallas técnicas. | F20: Plan de Mantenimiento Preventivo de Vías | G20: Trimestral | H20: Solicitar el plan de mantenimiento de vías y los registros de ejecución. Debe incluir como mínimo: inspección de desgaste de rieles, estado de durmientes y fijaciones, y geometría de la vía | I20: N/A
F21: Plan de Mantenimiento Preventivo de Equipos | G21: Trimestral | H21: Solicitar el plan de mantenimiento para locomotoras y carros, y verificar su cumplimiento. Debe incluir sistemas de frenos, rodado, motor y sistemas de comunicación. | I21: N/A
F22: Inspección Pre Operacional del Equipo | G22: Diario | H22: Solicitar el registro del check-list de pre-uso, el cual debe ser completado y firmado por el maquinista al inicio de cada turno, verificando daños, luces, frenos y comunicaciones | I22: N/A
